{"Event":{"System":{"Provider":{"@Name":"Microsoft-Windows-Security-Auditing","@Guid":"54849625-5478-4994-a5ba-3e3b0328c30d"},"EventID":"5379","Version":"0","Level":"0","Task":"13824","Opcode":"0","Keywords":"0x8020000000000000","TimeCreated":{"@SystemTime":"2025-05-02 08:52:13.0708607"},"EventRecordID":"89915","Correlation":{"@ActivityID":"1168e054-bb50-0000-2de1-681150bbdb01"},"Execution":{"@ProcessID":"688","@ThreadID":"744"},"Channel":"Security","Computer":"Server002","Security":null},"EventData":{"Data":[{"@Name":"SubjectUserSid","#text":"S-1-5-21-3962163828-2803415714-1403596700-1001"},{"@Name":"SubjectUserName","#text":"lplui"},{"@Name":"SubjectDomainName","#text":"SERVER002"},{"@Name":"SubjectLogonId","#text":"0x39737"},{"@Name":"TargetName","#text":"MicrosoftAccount:user=lpluigi44@gmail.com"},{"@Name":"Type","#text":"0"},{"@Name":"CountOfCredentialsReturned","#text":"1"},{"@Name":"ReadOperation","#text":"%%8100"},{"@Name":"ReturnCode","#text":"0"},{"@Name":"ProcessCreationTime","#text":"2025-05-02 08:51:23.7368016"},{"@Name":"ClientProcessId","#text":"4704"}]}}}
{"Event":{"System":{"Provider":{"@Name":"Microsoft-Windows-Security-Auditing","@Guid":"54849625-5478-4994-a5ba-3e3b0328c30d"},"EventID":"5379","Version":"0","Level":"0","Task":"13824","Opcode":"0","Keywords":"0x8020000000000000","TimeCreated":{"@SystemTime":"2025-05-02 08:52:13.0714737"},"EventRecordID":"89916","Correlation":{"@ActivityID":"1168e054-bb50-0000-2de1-681150bbdb01"},"Execution":{"@ProcessID":"688","@ThreadID":"744"},"Channel":"Security","Computer":"Server002","Security":null},"EventData":{"Data":[{"@Name":"SubjectUserSid","#text":"S-1-5-21-3962163828-2803415714-1403596700-1001"},{"@Name":"SubjectUserName","#text":"lplui"},{"@Name":"SubjectDomainName","#text":"SERVER002"},{"@Name":"SubjectLogonId","#text":"0x39737"},{"@Name":"TargetName","#text":"MicrosoftAccount:user=lpluigi44@gmail.com"},{"@Name":"Type","#text":"1"},{"@Name":"CountOfCredentialsReturned","#text":"1"},{"@Name":"ReadOperation","#text":"%%8099"},{"@Name":"ReturnCode","#text":"0"},{"@Name":"ProcessCreationTime","#text":"2025-05-02 08:51:23.7368016"},{"@Name":"ClientProcessId","#text":"4704"}]}}}
{"Event":{"System":{"Provider":{"@Name":"Microsoft-Windows-Security-Auditing","@Guid":"54849625-5478-4994-a5ba-3e3b0328c30d"},"EventID":"5379","Version":"0","Level":"0","Task":"13824","Opcode":"0","Keywords":"0x8020000000000000","TimeCreated":{"@SystemTime":"2025-05-02 08:52:13.0793977"},"EventRecordID":"89917","Correlation":{"@ActivityID":"1168e054-bb50-0000-2de1-681150bbdb01"},"Execution":{"@ProcessID":"688","@ThreadID":"752"},"Channel":"Security","Computer":"Server002","Security":null},"EventData":{"Data":[{"@Name":"SubjectUserSid","#text":"S-1-5-21-3962163828-2803415714-1403596700-1001"},{"@Name":"SubjectUserName","#text":"lplui"},{"@Name":"SubjectDomainName","#text":"SERVER002"},{"@Name":"SubjectLogonId","#text":"0x39737"},{"@Name":"TargetName","#text":"MicrosoftAccount:user=lpluigi44@gmail.com"},{"@Name":"Type","#text":"0"},{"@Name":"CountOfCredentialsReturned","#text":"1"},{"@Name":"ReadOperation","#text":"%%8100"},{"@Name":"ReturnCode","#text":"0"},{"@Name":"ProcessCreationTime","#text":"2025-05-02 08:51:23.7368016"},{"@Name":"ClientProcessId","#text":"4704"}]}}}
{"Event":{"System":{"Provider":{"@Name":"Microsoft-Windows-Security-Auditing","@Guid":"54849625-5478-4994-a5ba-3e3b0328c30d"},"EventID":"5379","Version":"0","Level":"0","Task":"13824","Opcode":"0","Keywords":"0x8020000000000000","TimeCreated":{"@SystemTime":"2025-05-02 08:52:13.0796063"},"EventRecordID":"89918","Correlation":{"@ActivityID":"1168e054-bb50-0000-2de1-681150bbdb01"},"Execution":{"@ProcessID":"688","@ThreadID":"752"},"Channel":"Security","Computer":"Server002","Security":null},"EventData":{"Data":[{"@Name":"SubjectUserSid","#text":"S-1-5-21-3962163828-2803415714-1403596700-1001"},{"@Name":"SubjectUserName","#text":"lplui"},{"@Name":"SubjectDomainName","#text":"SERVER002"},{"@Name":"SubjectLogonId","#text":"0x39737"},{"@Name":"TargetName","#text":"MicrosoftAccount:user=lpluigi44@gmail.com"},{"@Name":"Type","#text":"0"},{"@Name":"CountOfCredentialsReturned","#text":"1"},{"@Name":"ReadOperation","#text":"%%8100"},{"@Name":"ReturnCode","#text":"0"},{"@Name":"ProcessCreationTime","#text":"2025-05-02 08:51:23.7368016"},{"@Name":"ClientProcessId","#text":"4704"}]}}}
{"Event":{"System":{"Provider":{"@Name":"Microsoft-Windows-Security-Auditing","@Guid":"54849625-5478-4994-a5ba-3e3b0328c30d"},"EventID":"5379","Version":"0","Level":"0","Task":"13824","Opcode":"0","Keywords":"0x8020000000000000","TimeCreated":{"@SystemTime":"2025-05-02 08:52:13.0800299"},"EventRecordID":"89919","Correlation":{"@ActivityID":"1168e054-bb50-0000-2de1-681150bbdb01"},"Execution":{"@ProcessID":"688","@ThreadID":"752"},"Channel":"Security","Computer":"Server002","Security":null},"EventData":{"Data":[{"@Name":"SubjectUserSid","#text":"S-1-5-21-3962163828-2803415714-1403596700-1001"},{"@Name":"SubjectUserName","#text":"lplui"},{"@Name":"SubjectDomainName","#text":"SERVER002"},{"@Name":"SubjectLogonId","#text":"0x39737"},{"@Name":"TargetName","#text":"MicrosoftAccount:user=lpluigi44@gmail.com"},{"@Name":"Type","#text":"0"},{"@Name":"CountOfCredentialsReturned","#text":"1"},{"@Name":"ReadOperation","#text":"%%8100"},{"@Name":"ReturnCode","#text":"0"},{"@Name":"ProcessCreationTime","#text":"2025-05-02 08:51:23.7368016"},{"@Name":"ClientProcessId","#text":"4704"}]}}}
{"Event":{"System":{"Provider":{"@Name":"Microsoft-Windows-Security-Auditing","@Guid":"54849625-5478-4994-a5ba-3e3b0328c30d"},"EventID":"5379","Version":"0","Level":"0","Task":"13824","Opcode":"0","Keywords":"0x8020000000000000","TimeCreated":{"@SystemTime":"2025-05-02 08:52:13.0803575"},"EventRecordID":"89920","Correlation":{"@ActivityID":"1168e054-bb50-0000-2de1-681150bbdb01"},"Execution":{"@ProcessID":"688","@ThreadID":"752"},"Channel":"Security","Computer":"Server002","Security":null},"EventData":{"Data":[{"@Name":"SubjectUserSid","#text":"S-1-5-21-3962163828-2803415714-1403596700-1001"},{"@Name":"SubjectUserName","#text":"lplui"},{"@Name":"SubjectDomainName","#text":"SERVER002"},{"@Name":"SubjectLogonId","#text":"0x39737"},{"@Name":"TargetName","#text":"MicrosoftAccount:user=lpluigi44@gmail.com"},{"@Name":"Type","#text":"0"},{"@Name":"CountOfCredentialsReturned","#text":"1"},{"@Name":"ReadOperation","#text":"%%8100"},{"@Name":"ReturnCode","#text":"0"},{"@Name":"ProcessCreationTime","#text":"2025-05-02 08:51:23.7368016"},{"@Name":"ClientProcessId","#text":"4704"}]}}}
{"Event":{"System":{"Provider":{"@Name":"Microsoft-Windows-Security-Auditing","@Guid":"54849625-5478-4994-a5ba-3e3b0328c30d"},"EventID":"5379","Version":"0","Level":"0","Task":"13824","Opcode":"0","Keywords":"0x8020000000000000","TimeCreated":{"@SystemTime":"2025-05-02 08:52:13.0807130"},"EventRecordID":"89921","Correlation":{"@ActivityID":"1168e054-bb50-0000-2de1-681150bbdb01"},"Execution":{"@ProcessID":"688","@ThreadID":"752"},"Channel":"Security","Computer":"Server002","Security":null},"EventData":{"Data":[{"@Name":"SubjectUserSid","#text":"S-1-5-21-3962163828-2803415714-1403596700-1001"},{"@Name":"SubjectUserName","#text":"lplui"},{"@Name":"SubjectDomainName","#text":"SERVER002"},{"@Name":"SubjectLogonId","#text":"0x39737"},{"@Name":"TargetName","#text":"MicrosoftAccount:user=lpluigi44@gmail.com"},{"@Name":"Type","#text":"0"},{"@Name":"CountOfCredentialsReturned","#text":"1"},{"@Name":"ReadOperation","#text":"%%8100"},{"@Name":"ReturnCode","#text":"0"},{"@Name":"ProcessCreationTime","#text":"2025-05-02 08:51:23.7368016"},{"@Name":"ClientProcessId","#text":"4704"}]}}}
{"Event":{"System":{"Provider":{"@Name":"Microsoft-Windows-Security-Auditing","@Guid":"54849625-5478-4994-a5ba-3e3b0328c30d"},"EventID":"5379","Version":"0","Level":"0","Task":"13824","Opcode":"0","Keywords":"0x8020000000000000","TimeCreated":{"@SystemTime":"2025-05-02 08:52:13.0809906"},"EventRecordID":"89922","Correlation":{"@ActivityID":"1168e054-bb50-0000-2de1-681150bbdb01"},"Execution":{"@ProcessID":"688","@ThreadID":"752"},"Channel":"Security","Computer":"Server002","Security":null},"EventData":{"Data":[{"@Name":"SubjectUserSid","#text":"S-1-5-21-3962163828-2803415714-1403596700-1001"},{"@Name":"SubjectUserName","#text":"lplui"},{"@Name":"SubjectDomainName","#text":"SERVER002"},{"@Name":"SubjectLogonId","#text":"0x39737"},{"@Name":"TargetName","#text":"MicrosoftAccount:user=lpluigi44@gmail.com"},{"@Name":"Type","#text":"0"},{"@Name":"CountOfCredentialsReturned","#text":"1"},{"@Name":"ReadOperation","#text":"%%8100"},{"@Name":"ReturnCode","#text":"0"},{"@Name":"ProcessCreationTime","#text":"2025-05-02 08:51:23.7368016"},{"@Name":"ClientProcessId","#text":"4704"}]}}}
{"Event":{"System":{"Provider":{"@Name":"Microsoft-Windows-Security-Auditing","@Guid":"54849625-5478-4994-a5ba-3e3b0328c30d"},"EventID":"5379","Version":"0","Level":"0","Task":"13824","Opcode":"0","Keywords":"0x8020000000000000","TimeCreated":{"@SystemTime":"2025-05-02 08:52:13.0813272"},"EventRecordID":"89923","Correlation":{"@ActivityID":"1168e054-bb50-0000-2de1-681150bbdb01"},"Execution":{"@ProcessID":"688","@ThreadID":"752"},"Channel":"Security","Computer":"Server002","Security":null},"EventData":{"Data":[{"@Name":"SubjectUserSid","#text":"S-1-5-21-3962163828-2803415714-1403596700-1001"},{"@Name":"SubjectUserName","#text":"lplui"},{"@Name":"SubjectDomainName","#text":"SERVER002"},{"@Name":"SubjectLogonId","#text":"0x39737"},{"@Name":"TargetName","#text":"MicrosoftAccount:user=lpluigi44@gmail.com"},{"@Name":"Type","#text":"0"},{"@Name":"CountOfCredentialsReturned","#text":"1"},{"@Name":"ReadOperation","#text":"%%8100"},{"@Name":"ReturnCode","#text":"0"},{"@Name":"ProcessCreationTime","#text":"2025-05-02 08:51:23.7368016"},{"@Name":"ClientProcessId","#text":"4704"}]}}}
{"Event":{"System":{"Provider":{"@Name":"Microsoft-Windows-Security-Auditing","@Guid":"54849625-5478-4994-a5ba-3e3b0328c30d"},"EventID":"5379","Version":"0","Level":"0","Task":"13824","Opcode":"0","Keywords":"0x8020000000000000","TimeCreated":{"@SystemTime":"2025-05-02 08:52:13.0816420"},"EventRecordID":"89924","Correlation":{"@ActivityID":"1168e054-bb50-0000-2de1-681150bbdb01"},"Execution":{"@ProcessID":"688","@ThreadID":"752"},"Channel":"Security","Computer":"Server002","Security":null},"EventData":{"Data":[{"@Name":"SubjectUserSid","#text":"S-1-5-21-3962163828-2803415714-1403596700-1001"},{"@Name":"SubjectUserName","#text":"lplui"},{"@Name":"SubjectDomainName","#text":"SERVER002"},{"@Name":"SubjectLogonId","#text":"0x39737"},{"@Name":"TargetName","#text":"MicrosoftAccount:user=lpluigi44@gmail.com"},{"@Name":"Type","#text":"0"},{"@Name":"CountOfCredentialsReturned","#text":"1"},{"@Name":"ReadOperation","#text":"%%8100"},{"@Name":"ReturnCode","#text":"0"},{"@Name":"ProcessCreationTime","#text":"2025-05-02 08:51:23.7368016"},{"@Name":"ClientProcessId","#text":"4704"}]}}}
{"Event":{"System":{"Provider":{"@Name":"Microsoft-Windows-Security-Auditing","@Guid":"54849625-5478-4994-a5ba-3e3b0328c30d"},"EventID":"5379","Version":"0","Level":"0","Task":"13824","Opcode":"0","Keywords":"0x8020000000000000","TimeCreated":{"@SystemTime":"2025-05-02 08:52:13.0820297"},"EventRecordID":"89925","Correlation":{"@ActivityID":"1168e054-bb50-0000-2de1-681150bbdb01"},"Execution":{"@ProcessID":"688","@ThreadID":"752"},"Channel":"Security","Computer":"Server002","Security":null},"EventData":{"Data":[{"@Name":"SubjectUserSid","#text":"S-1-5-21-3962163828-2803415714-1403596700-1001"},{"@Name":"SubjectUserName","#text":"lplui"},{"@Name":"SubjectDomainName","#text":"SERVER002"},{"@Name":"SubjectLogonId","#text":"0x39737"},{"@Name":"TargetName","#text":"MicrosoftAccount:user=lpluigi44@gmail.com"},{"@Name":"Type","#text":"0"},{"@Name":"CountOfCredentialsReturned","#text":"1"},{"@Name":"ReadOperation","#text":"%%8100"},{"@Name":"ReturnCode","#text":"0"},{"@Name":"ProcessCreationTime","#text":"2025-05-02 08:51:23.7368016"},{"@Name":"ClientProcessId","#text":"4704"}]}}}
{"Event":{"System":{"Provider":{"@Name":"Microsoft-Windows-Security-Auditing","@Guid":"54849625-5478-4994-a5ba-3e3b0328c30d"},"EventID":"5379","Version":"0","Level":"0","Task":"13824","Opcode":"0","Keywords":"0x8020000000000000","TimeCreated":{"@SystemTime":"2025-05-02 08:52:13.0821662"},"EventRecordID":"89926","Correlation":{"@ActivityID":"1168e054-bb50-0000-2de1-681150bbdb01"},"Execution":{"@ProcessID":"688","@ThreadID":"752"},"Channel":"Security","Computer":"Server002","Security":null},"EventData":{"Data":[{"@Name":"SubjectUserSid","#text":"S-1-5-21-3962163828-2803415714-1403596700-1001"},{"@Name":"SubjectUserName","#text":"lplui"},{"@Name":"SubjectDomainName","#text":"SERVER002"},{"@Name":"SubjectLogonId","#text":"0x39737"},{"@Name":"TargetName","#text":"MicrosoftAccount:user=lpluigi44@gmail.com"},{"@Name":"Type","#text":"0"},{"@Name":"CountOfCredentialsReturned","#text":"1"},{"@Name":"ReadOperation","#text":"%%8100"},{"@Name":"ReturnCode","#text":"0"},{"@Name":"ProcessCreationTime","#text":"2025-05-02 08:51:23.7368016"},{"@Name":"ClientProcessId","#text":"4704"}]}}}
{"Event":{"System":{"Provider":{"@Name":"Microsoft-Windows-Security-Auditing","@Guid":"54849625-5478-4994-a5ba-3e3b0328c30d"},"EventID":"5379","Version":"0","Level":"0","Task":"13824","Opcode":"0","Keywords":"0x8020000000000000","TimeCreated":{"@SystemTime":"2025-05-02 08:52:13.0825095"},"EventRecordID":"89927","Correlation":{"@ActivityID":"1168e054-bb50-0000-2de1-681150bbdb01"},"Execution":{"@ProcessID":"688","@ThreadID":"752"},"Channel":"Security","Computer":"Server002","Security":null},"EventData":{"Data":[{"@Name":"SubjectUserSid","#text":"S-1-5-21-3962163828-2803415714-1403596700-1001"},{"@Name":"SubjectUserName","#text":"lplui"},{"@Name":"SubjectDomainName","#text":"SERVER002"},{"@Name":"SubjectLogonId","#text":"0x39737"},{"@Name":"TargetName","#text":"MicrosoftAccount:user=lpluigi44@gmail.com"},{"@Name":"Type","#text":"0"},{"@Name":"CountOfCredentialsReturned","#text":"1"},{"@Name":"ReadOperation","#text":"%%8100"},{"@Name":"ReturnCode","#text":"0"},{"@Name":"ProcessCreationTime","#text":"2025-05-02 08:51:23.7368016"},{"@Name":"ClientProcessId","#text":"4704"}]}}}
{"Event":{"System":{"Provider":{"@Name":"Microsoft-Windows-Security-Auditing","@Guid":"54849625-5478-4994-a5ba-3e3b0328c30d"},"EventID":"5379","Version":"0","Level":"0","Task":"13824","Opcode":"0","Keywords":"0x8020000000000000","TimeCreated":{"@SystemTime":"2025-05-02 08:52:13.0898554"},"EventRecordID":"89928","Correlation":{"@ActivityID":"1168e054-bb50-0000-2de1-681150bbdb01"},"Execution":{"@ProcessID":"688","@ThreadID":"752"},"Channel":"Security","Computer":"Server002","Security":null},"EventData":{"Data":[{"@Name":"SubjectUserSid","#text":"S-1-5-21-3962163828-2803415714-1403596700-1001"},{"@Name":"SubjectUserName","#text":"lplui"},{"@Name":"SubjectDomainName","#text":"SERVER002"},{"@Name":"SubjectLogonId","#text":"0x39737"},{"@Name":"TargetName","#text":"MicrosoftAccount:user=lpluigi44@gmail.com"},{"@Name":"Type","#text":"0"},{"@Name":"CountOfCredentialsReturned","#text":"1"},{"@Name":"ReadOperation","#text":"%%8100"},{"@Name":"ReturnCode","#text":"0"},{"@Name":"ProcessCreationTime","#text":"2025-05-02 08:51:23.7368016"},{"@Name":"ClientProcessId","#text":"4704"}]}}}
{"Event":{"System":{"Provider":{"@Name":"Microsoft-Windows-Security-Auditing","@Guid":"54849625-5478-4994-a5ba-3e3b0328c30d"},"EventID":"5379","Version":"0","Level":"0","Task":"13824","Opcode":"0","Keywords":"0x8020000000000000","TimeCreated":{"@SystemTime":"2025-05-02 08:52:13.0901627"},"EventRecordID":"89929","Correlation":{"@ActivityID":"1168e054-bb50-0000-2de1-681150bbdb01"},"Execution":{"@ProcessID":"688","@ThreadID":"752"},"Channel":"Security","Computer":"Server002","Security":null},"EventData":{"Data":[{"@Name":"SubjectUserSid","#text":"S-1-5-21-3962163828-2803415714-1403596700-1001"},{"@Name":"SubjectUserName","#text":"lplui"},{"@Name":"SubjectDomainName","#text":"SERVER002"},{"@Name":"SubjectLogonId","#text":"0x39737"},{"@Name":"TargetName","#text":"MicrosoftAccount:user=lpluigi44@gmail.com"},{"@Name":"Type","#text":"0"},{"@Name":"CountOfCredentialsReturned","#text":"1"},{"@Name":"ReadOperation","#text":"%%8100"},{"@Name":"ReturnCode","#text":"0"},{"@Name":"ProcessCreationTime","#text":"2025-05-02 08:51:23.7368016"},{"@Name":"ClientProcessId","#text":"4704"}]}}}
{"Event":{"System":{"Provider":{"@Name":"Microsoft-Windows-Security-Auditing","@Guid":"54849625-5478-4994-a5ba-3e3b0328c30d"},"EventID":"5379","Version":"0","Level":"0","Task":"13824","Opcode":"0","Keywords":"0x8020000000000000","TimeCreated":{"@SystemTime":"2025-05-02 08:52:13.0908339"},"EventRecordID":"89930","Correlation":{"@ActivityID":"1168e054-bb50-0000-2de1-681150bbdb01"},"Execution":{"@ProcessID":"688","@ThreadID":"752"},"Channel":"Security","Computer":"Server002","Security":null},"EventData":{"Data":[{"@Name":"SubjectUserSid","#text":"S-1-5-21-3962163828-2803415714-1403596700-1001"},{"@Name":"SubjectUserName","#text":"lplui"},{"@Name":"SubjectDomainName","#text":"SERVER002"},{"@Name":"SubjectLogonId","#text":"0x39737"},{"@Name":"TargetName","#text":"MicrosoftAccount:user=lpluigi44@gmail.com"},{"@Name":"Type","#text":"0"},{"@Name":"CountOfCredentialsReturned","#text":"1"},{"@Name":"ReadOperation","#text":"%%8100"},{"@Name":"ReturnCode","#text":"0"},{"@Name":"ProcessCreationTime","#text":"2025-05-02 08:51:23.7368016"},{"@Name":"ClientProcessId","#text":"4704"}]}}}
{"Event":{"System":{"Provider":{"@Name":"Microsoft-Windows-Security-Auditing","@Guid":"54849625-5478-4994-a5ba-3e3b0328c30d"},"EventID":"5379","Version":"0","Level":"0","Task":"13824","Opcode":"0","Keywords":"0x8020000000000000","TimeCreated":{"@SystemTime":"2025-05-02 08:52:13.0914494"},"EventRecordID":"89931","Correlation":{"@ActivityID":"1168e054-bb50-0000-2de1-681150bbdb01"},"Execution":{"@ProcessID":"688","@ThreadID":"752"},"Channel":"Security","Computer":"Server002","Security":null},"EventData":{"Data":[{"@Name":"SubjectUserSid","#text":"S-1-5-21-3962163828-2803415714-1403596700-1001"},{"@Name":"SubjectUserName","#text":"lplui"},{"@Name":"SubjectDomainName","#text":"SERVER002"},{"@Name":"SubjectLogonId","#text":"0x39737"},{"@Name":"TargetName","#text":"MicrosoftAccount:user=lpluigi44@gmail.com"},{"@Name":"Type","#text":"0"},{"@Name":"CountOfCredentialsReturned","#text":"1"},{"@Name":"ReadOperation","#text":"%%8100"},{"@Name":"ReturnCode","#text":"0"},{"@Name":"ProcessCreationTime","#text":"2025-05-02 08:51:23.7368016"},{"@Name":"ClientProcessId","#text":"4704"}]}}}
{"Event":{"System":{"Provider":{"@Name":"Microsoft-Windows-Security-Auditing","@Guid":"54849625-5478-4994-a5ba-3e3b0328c30d"},"EventID":"5379","Version":"0","Level":"0","Task":"13824","Opcode":"0","Keywords":"0x8020000000000000","TimeCreated":{"@SystemTime":"2025-05-02 08:52:13.0918151"},"EventRecordID":"89932","Correlation":{"@ActivityID":"1168e054-bb50-0000-2de1-681150bbdb01"},"Execution":{"@ProcessID":"688","@ThreadID":"752"},"Channel":"Security","Computer":"Server002","Security":null},"EventData":{"Data":[{"@Name":"SubjectUserSid","#text":"S-1-5-21-3962163828-2803415714-1403596700-1001"},{"@Name":"SubjectUserName","#text":"lplui"},{"@Name":"SubjectDomainName","#text":"SERVER002"},{"@Name":"SubjectLogonId","#text":"0x39737"},{"@Name":"TargetName","#text":"MicrosoftAccount:user=lpluigi44@gmail.com"},{"@Name":"Type","#text":"0"},{"@Name":"CountOfCredentialsReturned","#text":"1"},{"@Name":"ReadOperation","#text":"%%8100"},{"@Name":"ReturnCode","#text":"0"},{"@Name":"ProcessCreationTime","#text":"2025-05-02 08:51:23.7368016"},{"@Name":"ClientProcessId","#text":"4704"}]}}}
{"Event":{"System":{"Provider":{"@Name":"Microsoft-Windows-Security-Auditing","@Guid":"54849625-5478-4994-a5ba-3e3b0328c30d"},"EventID":"5379","Version":"0","Level":"0","Task":"13824","Opcode":"0","Keywords":"0x8020000000000000","TimeCreated":{"@SystemTime":"2025-05-02 08:52:13.0920802"},"EventRecordID":"89933","Correlation":{"@ActivityID":"1168e054-bb50-0000-2de1-681150bbdb01"},"Execution":{"@ProcessID":"688","@ThreadID":"752"},"Channel":"Security","Computer":"Server002","Security":null},"EventData":{"Data":[{"@Name":"SubjectUserSid","#text":"S-1-5-21-3962163828-2803415714-1403596700-1001"},{"@Name":"SubjectUserName","#text":"lplui"},{"@Name":"SubjectDomainName","#text":"SERVER002"},{"@Name":"SubjectLogonId","#text":"0x39737"},{"@Name":"TargetName","#text":"MicrosoftAccount:user=lpluigi44@gmail.com"},{"@Name":"Type","#text":"0"},{"@Name":"CountOfCredentialsReturned","#text":"1"},{"@Name":"ReadOperation","#text":"%%8100"},{"@Name":"ReturnCode","#text":"0"},{"@Name":"ProcessCreationTime","#text":"2025-05-02 08:51:23.7368016"},{"@Name":"ClientProcessId","#text":"4704"}]}}}
{"Event":{"System":{"Provider":{"@Name":"Microsoft-Windows-Security-Auditing","@Guid":"54849625-5478-4994-a5ba-3e3b0328c30d"},"EventID":"5379","Version":"0","Level":"0","Task":"13824","Opcode":"0","Keywords":"0x8020000000000000","TimeCreated":{"@SystemTime":"2025-05-02 08:52:13.0924572"},"EventRecordID":"89934","Correlation":{"@ActivityID":"1168e054-bb50-0000-2de1-681150bbdb01"},"Execution":{"@ProcessID":"688","@ThreadID":"752"},"Channel":"Security","Computer":"Server002","Security":null},"EventData":{"Data":[{"@Name":"SubjectUserSid","#text":"S-1-5-21-3962163828-2803415714-1403596700-1001"},{"@Name":"SubjectUserName","#text":"lplui"},{"@Name":"SubjectDomainName","#text":"SERVER002"},{"@Name":"SubjectLogonId","#text":"0x39737"},{"@Name":"TargetName","#text":"MicrosoftAccount:user=lpluigi44@gmail.com"},{"@Name":"Type","#text":"0"},{"@Name":"CountOfCredentialsReturned","#text":"1"},{"@Name":"ReadOperation","#text":"%%8100"},{"@Name":"ReturnCode","#text":"0"},{"@Name":"ProcessCreationTime","#text":"2025-05-02 08:51:23.7368016"},{"@Name":"ClientProcessId","#text":"4704"}]}}}
{"Event":{"System":{"Provider":{"@Name":"Microsoft-Windows-Security-Auditing","@Guid":"54849625-5478-4994-a5ba-3e3b0328c30d"},"EventID":"5379","Version":"0","Level":"0","Task":"13824","Opcode":"0","Keywords":"0x8020000000000000","TimeCreated":{"@SystemTime":"2025-05-02 08:52:13.0928073"},"EventRecordID":"89935","Correlation":{"@ActivityID":"1168e054-bb50-0000-2de1-681150bbdb01"},"Execution":{"@ProcessID":"688","@ThreadID":"752"},"Channel":"Security","Computer":"Server002","Security":null},"EventData":{"Data":[{"@Name":"SubjectUserSid","#text":"S-1-5-21-3962163828-2803415714-1403596700-1001"},{"@Name":"SubjectUserName","#text":"lplui"},{"@Name":"SubjectDomainName","#text":"SERVER002"},{"@Name":"SubjectLogonId","#text":"0x39737"},{"@Name":"TargetName","#text":"MicrosoftAccount:user=lpluigi44@gmail.com"},{"@Name":"Type","#text":"0"},{"@Name":"CountOfCredentialsReturned","#text":"1"},{"@Name":"ReadOperation","#text":"%%8100"},{"@Name":"ReturnCode","#text":"0"},{"@Name":"ProcessCreationTime","#text":"2025-05-02 08:51:23.7368016"},{"@Name":"ClientProcessId","#text":"4704"}]}}}
{"Event":{"System":{"Provider":{"@Name":"Microsoft-Windows-Security-Auditing","@Guid":"54849625-5478-4994-a5ba-3e3b0328c30d"},"EventID":"5379","Version":"0","Level":"0","Task":"13824","Opcode":"0","Keywords":"0x8020000000000000","TimeCreated":{"@SystemTime":"2025-05-02 08:52:13.0934073"},"EventRecordID":"89936","Correlation":{"@ActivityID":"1168e054-bb50-0000-2de1-681150bbdb01"},"Execution":{"@ProcessID":"688","@ThreadID":"752"},"Channel":"Security","Computer":"Server002","Security":null},"EventData":{"Data":[{"@Name":"SubjectUserSid","#text":"S-1-5-21-3962163828-2803415714-1403596700-1001"},{"@Name":"SubjectUserName","#text":"lplui"},{"@Name":"SubjectDomainName","#text":"SERVER002"},{"@Name":"SubjectLogonId","#text":"0x39737"},{"@Name":"TargetName","#text":"MicrosoftAccount:user=lpluigi44@gmail.com"},{"@Name":"Type","#text":"0"},{"@Name":"CountOfCredentialsReturned","#text":"1"},{"@Name":"ReadOperation","#text":"%%8100"},{"@Name":"ReturnCode","#text":"0"},{"@Name":"ProcessCreationTime","#text":"2025-05-02 08:51:23.7368016"},{"@Name":"ClientProcessId","#text":"4704"}]}}}
{"Event":{"System":{"Provider":{"@Name":"Microsoft-Windows-Security-Auditing","@Guid":"54849625-5478-4994-a5ba-3e3b0328c30d"},"EventID":"5379","Version":"0","Level":"0","Task":"13824","Opcode":"0","Keywords":"0x8020000000000000","TimeCreated":{"@SystemTime":"2025-05-02 08:52:13.0940408"},"EventRecordID":"89937","Correlation":{"@ActivityID":"1168e054-bb50-0000-2de1-681150bbdb01"},"Execution":{"@ProcessID":"688","@ThreadID":"752"},"Channel":"Security","Computer":"Server002","Security":null},"EventData":{"Data":[{"@Name":"SubjectUserSid","#text":"S-1-5-21-3962163828-2803415714-1403596700-1001"},{"@Name":"SubjectUserName","#text":"lplui"},{"@Name":"SubjectDomainName","#text":"SERVER002"},{"@Name":"SubjectLogonId","#text":"0x39737"},{"@Name":"TargetName","#text":"MicrosoftAccount:user=lpluigi44@gmail.com"},{"@Name":"Type","#text":"0"},{"@Name":"CountOfCredentialsReturned","#text":"1"},{"@Name":"ReadOperation","#text":"%%8100"},{"@Name":"ReturnCode","#text":"0"},{"@Name":"ProcessCreationTime","#text":"2025-05-02 08:51:23.7368016"},{"@Name":"ClientProcessId","#text":"4704"}]}}}
{"Event":{"System":{"Provider":{"@Name":"Microsoft-Windows-Security-Auditing","@Guid":"54849625-5478-4994-a5ba-3e3b0328c30d"},"EventID":"5379","Version":"0","Level":"0","Task":"13824","Opcode":"0","Keywords":"0x8020000000000000","TimeCreated":{"@SystemTime":"2025-05-02 08:52:13.0944138"},"EventRecordID":"89938","Correlation":{"@ActivityID":"1168e054-bb50-0000-2de1-681150bbdb01"},"Execution":{"@ProcessID":"688","@ThreadID":"752"},"Channel":"Security","Computer":"Server002","Security":null},"EventData":{"Data":[{"@Name":"SubjectUserSid","#text":"S-1-5-21-3962163828-2803415714-1403596700-1001"},{"@Name":"SubjectUserName","#text":"lplui"},{"@Name":"SubjectDomainName","#text":"SERVER002"},{"@Name":"SubjectLogonId","#text":"0x39737"},{"@Name":"TargetName","#text":"MicrosoftAccount:user=lpluigi44@gmail.com"},{"@Name":"Type","#text":"0"},{"@Name":"CountOfCredentialsReturned","#text":"1"},{"@Name":"ReadOperation","#text":"%%8100"},{"@Name":"ReturnCode","#text":"0"},{"@Name":"ProcessCreationTime","#text":"2025-05-02 08:51:23.7368016"},{"@Name":"ClientProcessId","#text":"4704"}]}}}
{"Event":{"System":{"Provider":{"@Name":"Microsoft-Windows-Security-Auditing","@Guid":"54849625-5478-4994-a5ba-3e3b0328c30d"},"EventID":"5379","Version":"0","Level":"0","Task":"13824","Opcode":"0","Keywords":"0x8020000000000000","TimeCreated":{"@SystemTime":"2025-05-02 08:52:13.0981310"},"EventRecordID":"89939","Correlation":{"@ActivityID":"1168e054-bb50-0000-2de1-681150bbdb01"},"Execution":{"@ProcessID":"688","@ThreadID":"752"},"Channel":"Security","Computer":"Server002","Security":null},"EventData":{"Data":[{"@Name":"SubjectUserSid","#text":"S-1-5-21-3962163828-2803415714-1403596700-1001"},{"@Name":"SubjectUserName","#text":"lplui"},{"@Name":"SubjectDomainName","#text":"SERVER002"},{"@Name":"SubjectLogonId","#text":"0x39737"},{"@Name":"TargetName","#text":"MicrosoftAccount:user=lpluigi44@gmail.com"},{"@Name":"Type","#text":"0"},{"@Name":"CountOfCredentialsReturned","#text":"1"},{"@Name":"ReadOperation","#text":"%%8100"},{"@Name":"ReturnCode","#text":"0"},{"@Name":"ProcessCreationTime","#text":"2025-05-02 08:51:23.7368016"},{"@Name":"ClientProcessId","#text":"4704"}]}}}
{"Event":{"System":{"Provider":{"@Name":"Microsoft-Windows-Security-Auditing","@Guid":"54849625-5478-4994-a5ba-3e3b0328c30d"},"EventID":"5379","Version":"0","Level":"0","Task":"13824","Opcode":"0","Keywords":"0x8020000000000000","TimeCreated":{"@SystemTime":"2025-05-02 08:52:13.1213622"},"EventRecordID":"89940","Correlation":{"@ActivityID":"1168e054-bb50-0000-2de1-681150bbdb01"},"Execution":{"@ProcessID":"688","@ThreadID":"752"},"Channel":"Security","Computer":"Server002","Security":null},"EventData":{"Data":[{"@Name":"SubjectUserSid","#text":"S-1-5-21-3962163828-2803415714-1403596700-1001"},{"@Name":"SubjectUserName","#text":"lplui"},{"@Name":"SubjectDomainName","#text":"SERVER002"},{"@Name":"SubjectLogonId","#text":"0x39737"},{"@Name":"TargetName","#text":"MicrosoftAccount:user=lpluigi44@gmail.com"},{"@Name":"Type","#text":"0"},{"@Name":"CountOfCredentialsReturned","#text":"1"},{"@Name":"ReadOperation","#text":"%%8100"},{"@Name":"ReturnCode","#text":"0"},{"@Name":"ProcessCreationTime","#text":"2025-05-02 08:51:23.7368016"},{"@Name":"ClientProcessId","#text":"4704"}]}}}
{"Event":{"System":{"Provider":{"@Name":"Microsoft-Windows-Security-Auditing","@Guid":"54849625-5478-4994-a5ba-3e3b0328c30d"},"EventID":"5379","Version":"0","Level":"0","Task":"13824","Opcode":"0","Keywords":"0x8020000000000000","TimeCreated":{"@SystemTime":"2025-05-02 08:52:13.1218042"},"EventRecordID":"89941","Correlation":{"@ActivityID":"1168e054-bb50-0000-2de1-681150bbdb01"},"Execution":{"@ProcessID":"688","@ThreadID":"752"},"Channel":"Security","Computer":"Server002","Security":null},"EventData":{"Data":[{"@Name":"SubjectUserSid","#text":"S-1-5-21-3962163828-2803415714-1403596700-1001"},{"@Name":"SubjectUserName","#text":"lplui"},{"@Name":"SubjectDomainName","#text":"SERVER002"},{"@Name":"SubjectLogonId","#text":"0x39737"},{"@Name":"TargetName","#text":"MicrosoftAccount:user=lpluigi44@gmail.com"},{"@Name":"Type","#text":"0"},{"@Name":"CountOfCredentialsReturned","#text":"1"},{"@Name":"ReadOperation","#text":"%%8100"},{"@Name":"ReturnCode","#text":"0"},{"@Name":"ProcessCreationTime","#text":"2025-05-02 08:51:23.7368016"},{"@Name":"ClientProcessId","#text":"4704"}]}}}
{"Event":{"System":{"Provider":{"@Name":"Microsoft-Windows-Security-Auditing","@Guid":"54849625-5478-4994-a5ba-3e3b0328c30d"},"EventID":"5379","Version":"0","Level":"0","Task":"13824","Opcode":"0","Keywords":"0x8020000000000000","TimeCreated":{"@SystemTime":"2025-05-02 08:52:13.1222007"},"EventRecordID":"89942","Correlation":{"@ActivityID":"1168e054-bb50-0000-2de1-681150bbdb01"},"Execution":{"@ProcessID":"688","@ThreadID":"752"},"Channel":"Security","Computer":"Server002","Security":null},"EventData":{"Data":[{"@Name":"SubjectUserSid","#text":"S-1-5-21-3962163828-2803415714-1403596700-1001"},{"@Name":"SubjectUserName","#text":"lplui"},{"@Name":"SubjectDomainName","#text":"SERVER002"},{"@Name":"SubjectLogonId","#text":"0x39737"},{"@Name":"TargetName","#text":"MicrosoftAccount:user=lpluigi44@gmail.com"},{"@Name":"Type","#text":"0"},{"@Name":"CountOfCredentialsReturned","#text":"1"},{"@Name":"ReadOperation","#text":"%%8100"},{"@Name":"ReturnCode","#text":"0"},{"@Name":"ProcessCreationTime","#text":"2025-05-02 08:51:23.7368016"},{"@Name":"ClientProcessId","#text":"4704"}]}}}
{"Event":{"System":{"Provider":{"@Name":"Microsoft-Windows-Security-Auditing","@Guid":"54849625-5478-4994-a5ba-3e3b0328c30d"},"EventID":"5379","Version":"0","Level":"0","Task":"13824","Opcode":"0","Keywords":"0x8020000000000000","TimeCreated":{"@SystemTime":"2025-05-02 08:52:13.1225676"},"EventRecordID":"89943","Correlation":{"@ActivityID":"1168e054-bb50-0000-2de1-681150bbdb01"},"Execution":{"@ProcessID":"688","@ThreadID":"752"},"Channel":"Security","Computer":"Server002","Security":null},"EventData":{"Data":[{"@Name":"SubjectUserSid","#text":"S-1-5-21-3962163828-2803415714-1403596700-1001"},{"@Name":"SubjectUserName","#text":"lplui"},{"@Name":"SubjectDomainName","#text":"SERVER002"},{"@Name":"SubjectLogonId","#text":"0x39737"},{"@Name":"TargetName","#text":"MicrosoftAccount:user=lpluigi44@gmail.com"},{"@Name":"Type","#text":"0"},{"@Name":"CountOfCredentialsReturned","#text":"1"},{"@Name":"ReadOperation","#text":"%%8100"},{"@Name":"ReturnCode","#text":"0"},{"@Name":"ProcessCreationTime","#text":"2025-05-02 08:51:23.7368016"},{"@Name":"ClientProcessId","#text":"4704"}]}}}
{"Event":{"System":{"Provider":{"@Name":"Microsoft-Windows-Security-Auditing","@Guid":"54849625-5478-4994-a5ba-3e3b0328c30d"},"EventID":"5379","Version":"0","Level":"0","Task":"13824","Opcode":"0","Keywords":"0x8020000000000000","TimeCreated":{"@SystemTime":"2025-05-02 08:52:13.1229474"},"EventRecordID":"89944","Correlation":{"@ActivityID":"1168e054-bb50-0000-2de1-681150bbdb01"},"Execution":{"@ProcessID":"688","@ThreadID":"752"},"Channel":"Security","Computer":"Server002","Security":null},"EventData":{"Data":[{"@Name":"SubjectUserSid","#text":"S-1-5-21-3962163828-2803415714-1403596700-1001"},{"@Name":"SubjectUserName","#text":"lplui"},{"@Name":"SubjectDomainName","#text":"SERVER002"},{"@Name":"SubjectLogonId","#text":"0x39737"},{"@Name":"TargetName","#text":"MicrosoftAccount:user=lpluigi44@gmail.com"},{"@Name":"Type","#text":"0"},{"@Name":"CountOfCredentialsReturned","#text":"1"},{"@Name":"ReadOperation","#text":"%%8100"},{"@Name":"ReturnCode","#text":"0"},{"@Name":"ProcessCreationTime","#text":"2025-05-02 08:51:23.7368016"},{"@Name":"ClientProcessId","#text":"4704"}]}}}
{"Event":{"System":{"Provider":{"@Name":"Microsoft-Windows-Security-Auditing","@Guid":"54849625-5478-4994-a5ba-3e3b0328c30d"},"EventID":"5379","Version":"0","Level":"0","Task":"13824","Opcode":"0","Keywords":"0x8020000000000000","TimeCreated":{"@SystemTime":"2025-05-02 08:52:13.1233161"},"EventRecordID":"89945","Correlation":{"@ActivityID":"1168e054-bb50-0000-2de1-681150bbdb01"},"Execution":{"@ProcessID":"688","@ThreadID":"752"},"Channel":"Security","Computer":"Server002","Security":null},"EventData":{"Data":[{"@Name":"SubjectUserSid","#text":"S-1-5-21-3962163828-2803415714-1403596700-1001"},{"@Name":"SubjectUserName","#text":"lplui"},{"@Name":"SubjectDomainName","#text":"SERVER002"},{"@Name":"SubjectLogonId","#text":"0x39737"},{"@Name":"TargetName","#text":"MicrosoftAccount:user=lpluigi44@gmail.com"},{"@Name":"Type","#text":"0"},{"@Name":"CountOfCredentialsReturned","#text":"1"},{"@Name":"ReadOperation","#text":"%%8100"},{"@Name":"ReturnCode","#text":"0"},{"@Name":"ProcessCreationTime","#text":"2025-05-02 08:51:23.7368016"},{"@Name":"ClientProcessId","#text":"4704"}]}}}
{"Event":{"System":{"Provider":{"@Name":"Microsoft-Windows-Security-Auditing","@Guid":"54849625-5478-4994-a5ba-3e3b0328c30d"},"EventID":"5379","Version":"0","Level":"0","Task":"13824","Opcode":"0","Keywords":"0x8020000000000000","TimeCreated":{"@SystemTime":"2025-05-02 08:52:13.1237280"},"EventRecordID":"89946","Correlation":{"@ActivityID":"1168e054-bb50-0000-2de1-681150bbdb01"},"Execution":{"@ProcessID":"688","@ThreadID":"752"},"Channel":"Security","Computer":"Server002","Security":null},"EventData":{"Data":[{"@Name":"SubjectUserSid","#text":"S-1-5-21-3962163828-2803415714-1403596700-1001"},{"@Name":"SubjectUserName","#text":"lplui"},{"@Name":"SubjectDomainName","#text":"SERVER002"},{"@Name":"SubjectLogonId","#text":"0x39737"},{"@Name":"TargetName","#text":"MicrosoftAccount:user=lpluigi44@gmail.com"},{"@Name":"Type","#text":"0"},{"@Name":"CountOfCredentialsReturned","#text":"1"},{"@Name":"ReadOperation","#text":"%%8100"},{"@Name":"ReturnCode","#text":"0"},{"@Name":"ProcessCreationTime","#text":"2025-05-02 08:51:23.7368016"},{"@Name":"ClientProcessId","#text":"4704"}]}}}
{"Event":{"System":{"Provider":{"@Name":"Microsoft-Windows-Security-Auditing","@Guid":"54849625-5478-4994-a5ba-3e3b0328c30d"},"EventID":"5379","Version":"0","Level":"0","Task":"13824","Opcode":"0","Keywords":"0x8020000000000000","TimeCreated":{"@SystemTime":"2025-05-02 08:52:13.1240964"},"EventRecordID":"89947","Correlation":{"@ActivityID":"1168e054-bb50-0000-2de1-681150bbdb01"},"Execution":{"@ProcessID":"688","@ThreadID":"752"},"Channel":"Security","Computer":"Server002","Security":null},"EventData":{"Data":[{"@Name":"SubjectUserSid","#text":"S-1-5-21-3962163828-2803415714-1403596700-1001"},{"@Name":"SubjectUserName","#text":"lplui"},{"@Name":"SubjectDomainName","#text":"SERVER002"},{"@Name":"SubjectLogonId","#text":"0x39737"},{"@Name":"TargetName","#text":"MicrosoftAccount:user=lpluigi44@gmail.com"},{"@Name":"Type","#text":"0"},{"@Name":"CountOfCredentialsReturned","#text":"1"},{"@Name":"ReadOperation","#text":"%%8100"},{"@Name":"ReturnCode","#text":"0"},{"@Name":"ProcessCreationTime","#text":"2025-05-02 08:51:23.7368016"},{"@Name":"ClientProcessId","#text":"4704"}]}}}
{"Event":{"System":{"Provider":{"@Name":"Microsoft-Windows-Security-Auditing","@Guid":"54849625-5478-4994-a5ba-3e3b0328c30d"},"EventID":"5379","Version":"0","Level":"0","Task":"13824","Opcode":"0","Keywords":"0x8020000000000000","TimeCreated":{"@SystemTime":"2025-05-02 08:52:13.1244567"},"EventRecordID":"89948","Correlation":{"@ActivityID":"1168e054-bb50-0000-2de1-681150bbdb01"},"Execution":{"@ProcessID":"688","@ThreadID":"752"},"Channel":"Security","Computer":"Server002","Security":null},"EventData":{"Data":[{"@Name":"SubjectUserSid","#text":"S-1-5-21-3962163828-2803415714-1403596700-1001"},{"@Name":"SubjectUserName","#text":"lplui"},{"@Name":"SubjectDomainName","#text":"SERVER002"},{"@Name":"SubjectLogonId","#text":"0x39737"},{"@Name":"TargetName","#text":"MicrosoftAccount:user=lpluigi44@gmail.com"},{"@Name":"Type","#text":"0"},{"@Name":"CountOfCredentialsReturned","#text":"1"},{"@Name":"ReadOperation","#text":"%%8100"},{"@Name":"ReturnCode","#text":"0"},{"@Name":"ProcessCreationTime","#text":"2025-05-02 08:51:23.7368016"},{"@Name":"ClientProcessId","#text":"4704"}]}}}
{"Event":{"System":{"Provider":{"@Name":"Microsoft-Windows-Security-Auditing","@Guid":"54849625-5478-4994-a5ba-3e3b0328c30d"},"EventID":"5379","Version":"0","Level":"0","Task":"13824","Opcode":"0","Keywords":"0x8020000000000000","TimeCreated":{"@SystemTime":"2025-05-02 08:52:13.1247959"},"EventRecordID":"89949","Correlation":{"@ActivityID":"1168e054-bb50-0000-2de1-681150bbdb01"},"Execution":{"@ProcessID":"688","@ThreadID":"752"},"Channel":"Security","Computer":"Server002","Security":null},"EventData":{"Data":[{"@Name":"SubjectUserSid","#text":"S-1-5-21-3962163828-2803415714-1403596700-1001"},{"@Name":"SubjectUserName","#text":"lplui"},{"@Name":"SubjectDomainName","#text":"SERVER002"},{"@Name":"SubjectLogonId","#text":"0x39737"},{"@Name":"TargetName","#text":"MicrosoftAccount:user=lpluigi44@gmail.com"},{"@Name":"Type","#text":"0"},{"@Name":"CountOfCredentialsReturned","#text":"1"},{"@Name":"ReadOperation","#text":"%%8100"},{"@Name":"ReturnCode","#text":"0"},{"@Name":"ProcessCreationTime","#text":"2025-05-02 08:51:23.7368016"},{"@Name":"ClientProcessId","#text":"4704"}]}}}
{"Event":{"System":{"Provider":{"@Name":"Microsoft-Windows-Security-Auditing","@Guid":"54849625-5478-4994-a5ba-3e3b0328c30d"},"EventID":"5379","Version":"0","Level":"0","Task":"13824","Opcode":"0","Keywords":"0x8020000000000000","TimeCreated":{"@SystemTime":"2025-05-02 08:52:13.1252196"},"EventRecordID":"89950","Correlation":{"@ActivityID":"1168e054-bb50-0000-2de1-681150bbdb01"},"Execution":{"@ProcessID":"688","@ThreadID":"752"},"Channel":"Security","Computer":"Server002","Security":null},"EventData":{"Data":[{"@Name":"SubjectUserSid","#text":"S-1-5-21-3962163828-2803415714-1403596700-1001"},{"@Name":"SubjectUserName","#text":"lplui"},{"@Name":"SubjectDomainName","#text":"SERVER002"},{"@Name":"SubjectLogonId","#text":"0x39737"},{"@Name":"TargetName","#text":"MicrosoftAccount:user=lpluigi44@gmail.com"},{"@Name":"Type","#text":"0"},{"@Name":"CountOfCredentialsReturned","#text":"1"},{"@Name":"ReadOperation","#text":"%%8100"},{"@Name":"ReturnCode","#text":"0"},{"@Name":"ProcessCreationTime","#text":"2025-05-02 08:51:23.7368016"},{"@Name":"ClientProcessId","#text":"4704"}]}}}
{"Event":{"System":{"Provider":{"@Name":"Microsoft-Windows-Security-Auditing","@Guid":"54849625-5478-4994-a5ba-3e3b0328c30d"},"EventID":"5379","Version":"0","Level":"0","Task":"13824","Opcode":"0","Keywords":"0x8020000000000000","TimeCreated":{"@SystemTime":"2025-05-02 08:52:13.1256474"},"EventRecordID":"89951","Correlation":{"@ActivityID":"1168e054-bb50-0000-2de1-681150bbdb01"},"Execution":{"@ProcessID":"688","@ThreadID":"752"},"Channel":"Security","Computer":"Server002","Security":null},"EventData":{"Data":[{"@Name":"SubjectUserSid","#text":"S-1-5-21-3962163828-2803415714-1403596700-1001"},{"@Name":"SubjectUserName","#text":"lplui"},{"@Name":"SubjectDomainName","#text":"SERVER002"},{"@Name":"SubjectLogonId","#text":"0x39737"},{"@Name":"TargetName","#text":"MicrosoftAccount:user=lpluigi44@gmail.com"},{"@Name":"Type","#text":"0"},{"@Name":"CountOfCredentialsReturned","#text":"1"},{"@Name":"ReadOperation","#text":"%%8100"},{"@Name":"ReturnCode","#text":"0"},{"@Name":"ProcessCreationTime","#text":"2025-05-02 08:51:23.7368016"},{"@Name":"ClientProcessId","#text":"4704"}]}}}
{"Event":{"System":{"Provider":{"@Name":"Microsoft-Windows-Security-Auditing","@Guid":"54849625-5478-4994-a5ba-3e3b0328c30d"},"EventID":"5379","Version":"0","Level":"0","Task":"13824","Opcode":"0","Keywords":"0x8020000000000000","TimeCreated":{"@SystemTime":"2025-05-02 08:52:13.1731843"},"EventRecordID":"89952","Correlation":{"@ActivityID":"1168e054-bb50-0000-2de1-681150bbdb01"},"Execution":{"@ProcessID":"688","@ThreadID":"752"},"Channel":"Security","Computer":"Server002","Security":null},"EventData":{"Data":[{"@Name":"SubjectUserSid","#text":"S-1-5-21-3962163828-2803415714-1403596700-1001"},{"@Name":"SubjectUserName","#text":"lplui"},{"@Name":"SubjectDomainName","#text":"SERVER002"},{"@Name":"SubjectLogonId","#text":"0x39737"},{"@Name":"TargetName","#text":"MicrosoftAccount:user=02ofrizxnslvvfxc"},{"@Name":"Type","#text":"0"},{"@Name":"CountOfCredentialsReturned","#text":"0"},{"@Name":"ReadOperation","#text":"%%8100"},{"@Name":"ReturnCode","#text":"3221226021"},{"@Name":"ProcessCreationTime","#text":"2025-05-02 08:51:23.7368016"},{"@Name":"ClientProcessId","#text":"4704"}]}}}
{"Event":{"System":{"Provider":{"@Name":"Microsoft-Windows-Security-Auditing","@Guid":"54849625-5478-4994-a5ba-3e3b0328c30d"},"EventID":"5379","Version":"0","Level":"0","Task":"13824","Opcode":"0","Keywords":"0x8020000000000000","TimeCreated":{"@SystemTime":"2025-05-02 08:52:13.1732497"},"EventRecordID":"89953","Correlation":{"@ActivityID":"1168e054-bb50-0000-2de1-681150bbdb01"},"Execution":{"@ProcessID":"688","@ThreadID":"752"},"Channel":"Security","Computer":"Server002","Security":null},"EventData":{"Data":[{"@Name":"SubjectUserSid","#text":"S-1-5-21-3962163828-2803415714-1403596700-1001"},{"@Name":"SubjectUserName","#text":"lplui"},{"@Name":"SubjectDomainName","#text":"SERVER002"},{"@Name":"SubjectLogonId","#text":"0x39737"},{"@Name":"TargetName","#text":"WindowsLive:(token):name=02ofrizxnslvvfxc;serviceuri=*"},{"@Name":"Type","#text":"0"},{"@Name":"CountOfCredentialsReturned","#text":"0"},{"@Name":"ReadOperation","#text":"%%8100"},{"@Name":"ReturnCode","#text":"3221226021"},{"@Name":"ProcessCreationTime","#text":"2025-05-02 08:51:23.7368016"},{"@Name":"ClientProcessId","#text":"4704"}]}}}
{"Event":{"System":{"Provider":{"@Name":"Microsoft-Windows-Security-Auditing","@Guid":"54849625-5478-4994-a5ba-3e3b0328c30d"},"EventID":"5379","Version":"0","Level":"0","Task":"13824","Opcode":"0","Keywords":"0x8020000000000000","TimeCreated":{"@SystemTime":"2025-05-02 08:52:13.1736167"},"EventRecordID":"89954","Correlation":{"@ActivityID":"1168e054-bb50-0000-2de1-681150bbdb01"},"Execution":{"@ProcessID":"688","@ThreadID":"752"},"Channel":"Security","Computer":"Server002","Security":null},"EventData":{"Data":[{"@Name":"SubjectUserSid","#text":"S-1-5-21-3962163828-2803415714-1403596700-1001"},{"@Name":"SubjectUserName","#text":"lplui"},{"@Name":"SubjectDomainName","#text":"SERVER002"},{"@Name":"SubjectLogonId","#text":"0x39737"},{"@Name":"TargetName","#text":"WindowsLive:(cert):name=02ofrizxnslvvfxc;serviceuri=*"},{"@Name":"Type","#text":"0"},{"@Name":"CountOfCredentialsReturned","#text":"0"},{"@Name":"ReadOperation","#text":"%%8100"},{"@Name":"ReturnCode","#text":"3221226021"},{"@Name":"ProcessCreationTime","#text":"2025-05-02 08:51:23.7368016"},{"@Name":"ClientProcessId","#text":"4704"}]}}}
{"Event":{"System":{"Provider":{"@Name":"Microsoft-Windows-Security-Auditing","@Guid":"54849625-5478-4994-a5ba-3e3b0328c30d"},"EventID":"5379","Version":"0","Level":"0","Task":"13824","Opcode":"0","Keywords":"0x8020000000000000","TimeCreated":{"@SystemTime":"2025-05-02 08:52:13.3246908"},"EventRecordID":"89955","Correlation":{"@ActivityID":"1168e054-bb50-0000-2de1-681150bbdb01"},"Execution":{"@ProcessID":"688","@ThreadID":"752"},"Channel":"Security","Computer":"Server002","Security":null},"EventData":{"Data":[{"@Name":"SubjectUserSid","#text":"S-1-5-21-3962163828-2803415714-1403596700-1001"},{"@Name":"SubjectUserName","#text":"lplui"},{"@Name":"SubjectDomainName","#text":"SERVER002"},{"@Name":"SubjectLogonId","#text":"0x39737"},{"@Name":"TargetName","#text":"MicrosoftAccount:user=02ofrizxnslvvfxc"},{"@Name":"Type","#text":"0"},{"@Name":"CountOfCredentialsReturned","#text":"0"},{"@Name":"ReadOperation","#text":"%%8100"},{"@Name":"ReturnCode","#text":"3221226021"},{"@Name":"ProcessCreationTime","#text":"2025-05-02 08:51:23.7368016"},{"@Name":"ClientProcessId","#text":"4704"}]}}}
{"Event":{"System":{"Provider":{"@Name":"Microsoft-Windows-Security-Auditing","@Guid":"54849625-5478-4994-a5ba-3e3b0328c30d"},"EventID":"5379","Version":"0","Level":"0","Task":"13824","Opcode":"0","Keywords":"0x8020000000000000","TimeCreated":{"@SystemTime":"2025-05-02 08:52:13.3285557"},"EventRecordID":"89956","Correlation":{"@ActivityID":"1168e054-bb50-0000-2de1-681150bbdb01"},"Execution":{"@ProcessID":"688","@ThreadID":"752"},"Channel":"Security","Computer":"Server002","Security":null},"EventData":{"Data":[{"@Name":"SubjectUserSid","#text":"S-1-5-21-3962163828-2803415714-1403596700-1001"},{"@Name":"SubjectUserName","#text":"lplui"},{"@Name":"SubjectDomainName","#text":"SERVER002"},{"@Name":"SubjectLogonId","#text":"0x39737"},{"@Name":"TargetName","#text":"MicrosoftAccount:user=02ofrizxnslvvfxc"},{"@Name":"Type","#text":"0"},{"@Name":"CountOfCredentialsReturned","#text":"0"},{"@Name":"ReadOperation","#text":"%%8100"},{"@Name":"ReturnCode","#text":"3221226021"},{"@Name":"ProcessCreationTime","#text":"2025-05-02 08:51:23.7368016"},{"@Name":"ClientProcessId","#text":"4704"}]}}}
{"Event":{"System":{"Provider":{"@Name":"Microsoft-Windows-Security-Auditing","@Guid":"54849625-5478-4994-a5ba-3e3b0328c30d"},"EventID":"5379","Version":"0","Level":"0","Task":"13824","Opcode":"0","Keywords":"0x8020000000000000","TimeCreated":{"@SystemTime":"2025-05-02 08:52:13.3336711"},"EventRecordID":"89957","Correlation":{"@ActivityID":"1168e054-bb50-0000-2de1-681150bbdb01"},"Execution":{"@ProcessID":"688","@ThreadID":"752"},"Channel":"Security","Computer":"Server002","Security":null},"EventData":{"Data":[{"@Name":"SubjectUserSid","#text":"S-1-5-21-3962163828-2803415714-1403596700-1001"},{"@Name":"SubjectUserName","#text":"lplui"},{"@Name":"SubjectDomainName","#text":"SERVER002"},{"@Name":"SubjectLogonId","#text":"0x39737"},{"@Name":"TargetName","#text":"MicrosoftAccount:user=02ofrizxnslvvfxc"},{"@Name":"Type","#text":"0"},{"@Name":"CountOfCredentialsReturned","#text":"0"},{"@Name":"ReadOperation","#text":"%%8100"},{"@Name":"ReturnCode","#text":"3221226021"},{"@Name":"ProcessCreationTime","#text":"2025-05-02 08:51:23.7368016"},{"@Name":"ClientProcessId","#text":"4704"}]}}}
{"Event":{"System":{"Provider":{"@Name":"Microsoft-Windows-Security-Auditing","@Guid":"54849625-5478-4994-a5ba-3e3b0328c30d"},"EventID":"5379","Version":"0","Level":"0","Task":"13824","Opcode":"0","Keywords":"0x8020000000000000","TimeCreated":{"@SystemTime":"2025-05-02 08:52:13.3338724"},"EventRecordID":"89958","Correlation":{"@ActivityID":"1168e054-bb50-0000-2de1-681150bbdb01"},"Execution":{"@ProcessID":"688","@ThreadID":"752"},"Channel":"Security","Computer":"Server002","Security":null},"EventData":{"Data":[{"@Name":"SubjectUserSid","#text":"S-1-5-21-3962163828-2803415714-1403596700-1001"},{"@Name":"SubjectUserName","#text":"lplui"},{"@Name":"SubjectDomainName","#text":"SERVER002"},{"@Name":"SubjectLogonId","#text":"0x39737"},{"@Name":"TargetName","#text":"MicrosoftAccount:user=02ofrizxnslvvfxc"},{"@Name":"Type","#text":"0"},{"@Name":"CountOfCredentialsReturned","#text":"0"},{"@Name":"ReadOperation","#text":"%%8100"},{"@Name":"ReturnCode","#text":"3221226021"},{"@Name":"ProcessCreationTime","#text":"2025-05-02 08:51:23.7368016"},{"@Name":"ClientProcessId","#text":"4704"}]}}}
{"Event":{"System":{"Provider":{"@Name":"Microsoft-Windows-Security-Auditing","@Guid":"54849625-5478-4994-a5ba-3e3b0328c30d"},"EventID":"5379","Version":"0","Level":"0","Task":"13824","Opcode":"0","Keywords":"0x8020000000000000","TimeCreated":{"@SystemTime":"2025-05-02 08:52:18.3029266"},"EventRecordID":"89959","Correlation":{"@ActivityID":"1168e054-bb50-0000-2de1-681150bbdb01"},"Execution":{"@ProcessID":"688","@ThreadID":"744"},"Channel":"Security","Computer":"Server002","Security":null},"EventData":{"Data":[{"@Name":"SubjectUserSid","#text":"S-1-5-21-3962163828-2803415714-1403596700-1001"},{"@Name":"SubjectUserName","#text":"lplui"},{"@Name":"SubjectDomainName","#text":"SERVER002"},{"@Name":"SubjectLogonId","#text":"0x39737"},{"@Name":"TargetName","#text":"MicrosoftAccount:user=02ofrizxnslvvfxc"},{"@Name":"Type","#text":"0"},{"@Name":"CountOfCredentialsReturned","#text":"0"},{"@Name":"ReadOperation","#text":"%%8100"},{"@Name":"ReturnCode","#text":"3221226021"},{"@Name":"ProcessCreationTime","#text":"2025-05-02 08:51:23.7368016"},{"@Name":"ClientProcessId","#text":"4704"}]}}}
{"Event":{"System":{"Provider":{"@Name":"Microsoft-Windows-Security-Auditing","@Guid":"54849625-5478-4994-a5ba-3e3b0328c30d"},"EventID":"5379","Version":"0","Level":"0","Task":"13824","Opcode":"0","Keywords":"0x8020000000000000","TimeCreated":{"@SystemTime":"2025-05-02 08:52:18.3029980"},"EventRecordID":"89960","Correlation":{"@ActivityID":"1168e054-bb50-0000-2de1-681150bbdb01"},"Execution":{"@ProcessID":"688","@ThreadID":"744"},"Channel":"Security","Computer":"Server002","Security":null},"EventData":{"Data":[{"@Name":"SubjectUserSid","#text":"S-1-5-21-3962163828-2803415714-1403596700-1001"},{"@Name":"SubjectUserName","#text":"lplui"},{"@Name":"SubjectDomainName","#text":"SERVER002"},{"@Name":"SubjectLogonId","#text":"0x39737"},{"@Name":"TargetName","#text":"WindowsLive:(token):name=02ofrizxnslvvfxc;serviceuri=*"},{"@Name":"Type","#text":"0"},{"@Name":"CountOfCredentialsReturned","#text":"0"},{"@Name":"ReadOperation","#text":"%%8100"},{"@Name":"ReturnCode","#text":"3221226021"},{"@Name":"ProcessCreationTime","#text":"2025-05-02 08:51:23.7368016"},{"@Name":"ClientProcessId","#text":"4704"}]}}}
{"Event":{"System":{"Provider":{"@Name":"Microsoft-Windows-Security-Auditing","@Guid":"54849625-5478-4994-a5ba-3e3b0328c30d"},"EventID":"5379","Version":"0","Level":"0","Task":"13824","Opcode":"0","Keywords":"0x8020000000000000","TimeCreated":{"@SystemTime":"2025-05-02 08:52:18.3033391"},"EventRecordID":"89961","Correlation":{"@ActivityID":"1168e054-bb50-0000-2de1-681150bbdb01"},"Execution":{"@ProcessID":"688","@ThreadID":"744"},"Channel":"Security","Computer":"Server002","Security":null},"EventData":{"Data":[{"@Name":"SubjectUserSid","#text":"S-1-5-21-3962163828-2803415714-1403596700-1001"},{"@Name":"SubjectUserName","#text":"lplui"},{"@Name":"SubjectDomainName","#text":"SERVER002"},{"@Name":"SubjectLogonId","#text":"0x39737"},{"@Name":"TargetName","#text":"WindowsLive:(cert):name=02ofrizxnslvvfxc;serviceuri=*"},{"@Name":"Type","#text":"0"},{"@Name":"CountOfCredentialsReturned","#text":"0"},{"@Name":"ReadOperation","#text":"%%8100"},{"@Name":"ReturnCode","#text":"3221226021"},{"@Name":"ProcessCreationTime","#text":"2025-05-02 08:51:23.7368016"},{"@Name":"ClientProcessId","#text":"4704"}]}}}
{"Event":{"System":{"Provider":{"@Name":"Microsoft-Windows-Security-Auditing","@Guid":"54849625-5478-4994-a5ba-3e3b0328c30d"},"EventID":"5379","Version":"0","Level":"0","Task":"13824","Opcode":"0","Keywords":"0x8020000000000000","TimeCreated":{"@SystemTime":"2025-05-02 08:52:18.4550674"},"EventRecordID":"89962","Correlation":{"@ActivityID":"1168e054-bb50-0000-2de1-681150bbdb01"},"Execution":{"@ProcessID":"688","@ThreadID":"744"},"Channel":"Security","Computer":"Server002","Security":null},"EventData":{"Data":[{"@Name":"SubjectUserSid","#text":"S-1-5-21-3962163828-2803415714-1403596700-1001"},{"@Name":"SubjectUserName","#text":"lplui"},{"@Name":"SubjectDomainName","#text":"SERVER002"},{"@Name":"SubjectLogonId","#text":"0x39737"},{"@Name":"TargetName","#text":"MicrosoftAccount:user=02ofrizxnslvvfxc"},{"@Name":"Type","#text":"0"},{"@Name":"CountOfCredentialsReturned","#text":"0"},{"@Name":"ReadOperation","#text":"%%8100"},{"@Name":"ReturnCode","#text":"3221226021"},{"@Name":"ProcessCreationTime","#text":"2025-05-02 08:51:23.7368016"},{"@Name":"ClientProcessId","#text":"4704"}]}}}
{"Event":{"System":{"Provider":{"@Name":"Microsoft-Windows-Security-Auditing","@Guid":"54849625-5478-4994-a5ba-3e3b0328c30d"},"EventID":"5379","Version":"0","Level":"0","Task":"13824","Opcode":"0","Keywords":"0x8020000000000000","TimeCreated":{"@SystemTime":"2025-05-02 08:52:18.4589213"},"EventRecordID":"89963","Correlation":{"@ActivityID":"1168e054-bb50-0000-2de1-681150bbdb01"},"Execution":{"@ProcessID":"688","@ThreadID":"744"},"Channel":"Security","Computer":"Server002","Security":null},"EventData":{"Data":[{"@Name":"SubjectUserSid","#text":"S-1-5-21-3962163828-2803415714-1403596700-1001"},{"@Name":"SubjectUserName","#text":"lplui"},{"@Name":"SubjectDomainName","#text":"SERVER002"},{"@Name":"SubjectLogonId","#text":"0x39737"},{"@Name":"TargetName","#text":"MicrosoftAccount:user=02ofrizxnslvvfxc"},{"@Name":"Type","#text":"0"},{"@Name":"CountOfCredentialsReturned","#text":"0"},{"@Name":"ReadOperation","#text":"%%8100"},{"@Name":"ReturnCode","#text":"3221226021"},{"@Name":"ProcessCreationTime","#text":"2025-05-02 08:51:23.7368016"},{"@Name":"ClientProcessId","#text":"4704"}]}}}
{"Event":{"System":{"Provider":{"@Name":"Microsoft-Windows-Security-Auditing","@Guid":"54849625-5478-4994-a5ba-3e3b0328c30d"},"EventID":"5379","Version":"0","Level":"0","Task":"13824","Opcode":"0","Keywords":"0x8020000000000000","TimeCreated":{"@SystemTime":"2025-05-02 08:52:18.4621469"},"EventRecordID":"89964","Correlation":{"@ActivityID":"1168e054-bb50-0000-2de1-681150bbdb01"},"Execution":{"@ProcessID":"688","@ThreadID":"744"},"Channel":"Security","Computer":"Server002","Security":null},"EventData":{"Data":[{"@Name":"SubjectUserSid","#text":"S-1-5-21-3962163828-2803415714-1403596700-1001"},{"@Name":"SubjectUserName","#text":"lplui"},{"@Name":"SubjectDomainName","#text":"SERVER002"},{"@Name":"SubjectLogonId","#text":"0x39737"},{"@Name":"TargetName","#text":"MicrosoftAccount:user=02ofrizxnslvvfxc"},{"@Name":"Type","#text":"0"},{"@Name":"CountOfCredentialsReturned","#text":"0"},{"@Name":"ReadOperation","#text":"%%8100"},{"@Name":"ReturnCode","#text":"3221226021"},{"@Name":"ProcessCreationTime","#text":"2025-05-02 08:51:23.7368016"},{"@Name":"ClientProcessId","#text":"4704"}]}}}
{"Event":{"System":{"Provider":{"@Name":"Microsoft-Windows-Security-Auditing","@Guid":"54849625-5478-4994-a5ba-3e3b0328c30d"},"EventID":"5379","Version":"0","Level":"0","Task":"13824","Opcode":"0","Keywords":"0x8020000000000000","TimeCreated":{"@SystemTime":"2025-05-02 08:52:18.4621999"},"EventRecordID":"89965","Correlation":{"@ActivityID":"1168e054-bb50-0000-2de1-681150bbdb01"},"Execution":{"@ProcessID":"688","@ThreadID":"744"},"Channel":"Security","Computer":"Server002","Security":null},"EventData":{"Data":[{"@Name":"SubjectUserSid","#text":"S-1-5-21-3962163828-2803415714-1403596700-1001"},{"@Name":"SubjectUserName","#text":"lplui"},{"@Name":"SubjectDomainName","#text":"SERVER002"},{"@Name":"SubjectLogonId","#text":"0x39737"},{"@Name":"TargetName","#text":"MicrosoftAccount:user=02ofrizxnslvvfxc"},{"@Name":"Type","#text":"0"},{"@Name":"CountOfCredentialsReturned","#text":"0"},{"@Name":"ReadOperation","#text":"%%8100"},{"@Name":"ReturnCode","#text":"3221226021"},{"@Name":"ProcessCreationTime","#text":"2025-05-02 08:51:23.7368016"},{"@Name":"ClientProcessId","#text":"4704"}]}}}
{"Event":{"System":{"Provider":{"@Name":"Microsoft-Windows-Security-Auditing","@Guid":"54849625-5478-4994-a5ba-3e3b0328c30d"},"EventID":"5058","Version":"1","Level":"0","Task":"12292","Opcode":"0","Keywords":"0x8020000000000000","TimeCreated":{"@SystemTime":"2025-05-02 08:52:18.5522099"},"EventRecordID":"89966","Correlation":{"@ActivityID":"1168e054-bb50-0000-2de1-681150bbdb01"},"Execution":{"@ProcessID":"688","@ThreadID":"744"},"Channel":"Security","Computer":"Server002","Security":null},"EventData":{"Data":[{"@Name":"SubjectUserSid","#text":"S-1-5-19"},{"@Name":"SubjectUserName","#text":"LOCAL SERVICE"},{"@Name":"SubjectDomainName","#text":"NT AUTHORITY"},{"@Name":"SubjectLogonId","#text":"0x3E5"},{"@Name":"ClientProcessId","#text":"5628"},{"@Name":"ClientCreationTime","#text":"2025-05-02 08:51:30.4757579"},{"@Name":"ProviderName","#text":"Microsoft Software Key Storage Provider"},{"@Name":"AlgorithmName","#text":"UNKNOWN"},{"@Name":"KeyName","#text":"62cc240bff36fbd2"},{"@Name":"KeyType","#text":"%%2500"},{"@Name":"KeyFilePath","#text":"C:\Windows\ServiceProfiles\LocalService\AppData\Roaming\Microsoft\Crypto\Keys\ba8e5445e2865db08475c1675b57e0dc_dbf410b3-ef0e-4152-ad61-2d9c7d03536d"},{"@Name":"Operation","#text":"%%2458"},{"@Name":"ReturnCode","#text":"0x0"}]}}}
{"Event":{"System":{"Provider":{"@Name":"Microsoft-Windows-Security-Auditing","@Guid":"54849625-5478-4994-a5ba-3e3b0328c30d"},"EventID":"5061","Version":"0","Level":"0","Task":"12290","Opcode":"0","Keywords":"0x8020000000000000","TimeCreated":{"@SystemTime":"2025-05-02 08:52:18.5525627"},"EventRecordID":"89967","Correlation":{"@ActivityID":"1168e054-bb50-0000-2de1-681150bbdb01"},"Execution":{"@ProcessID":"688","@ThreadID":"744"},"Channel":"Security","Computer":"Server002","Security":null},"EventData":{"Data":[{"@Name":"SubjectUserSid","#text":"S-1-5-19"},{"@Name":"SubjectUserName","#text":"LOCAL SERVICE"},{"@Name":"SubjectDomainName","#text":"NT AUTHORITY"},{"@Name":"SubjectLogonId","#text":"0x3E5"},{"@Name":"ProviderName","#text":"Microsoft Software Key Storage Provider"},{"@Name":"AlgorithmName","#text":"ECDSA_P256"},{"@Name":"KeyName","#text":"62cc240bff36fbd2"},{"@Name":"KeyType","#text":"%%2500"},{"@Name":"Operation","#text":"%%2480"},{"@Name":"ReturnCode","#text":"0x0"}]}}}
{"Event":{"System":{"Provider":{"@Name":"Microsoft-Windows-Security-Auditing","@Guid":"54849625-5478-4994-a5ba-3e3b0328c30d"},"EventID":"5059","Version":"1","Level":"0","Task":"12292","Opcode":"0","Keywords":"0x8020000000000000","TimeCreated":{"@SystemTime":"2025-05-02 08:52:18.5528726"},"EventRecordID":"89968","Correlation":{"@ActivityID":"1168e054-bb50-0000-2de1-681150bbdb01"},"Execution":{"@ProcessID":"688","@ThreadID":"744"},"Channel":"Security","Computer":"Server002","Security":null},"EventData":{"Data":[{"@Name":"SubjectUserSid","#text":"S-1-5-19"},{"@Name":"SubjectUserName","#text":"LOCAL SERVICE"},{"@Name":"SubjectDomainName","#text":"NT AUTHORITY"},{"@Name":"SubjectLogonId","#text":"0x3E5"},{"@Name":"ClientProcessId","#text":"5628"},{"@Name":"ClientCreationTime","#text":"2025-05-02 08:51:30.4757579"},{"@Name":"ProviderName","#text":"Microsoft Software Key Storage Provider"},{"@Name":"AlgorithmName","#text":"ECDSA_P256"},{"@Name":"KeyName","#text":"62cc240bff36fbd2"},{"@Name":"KeyType","#text":"%%2500"},{"@Name":"Operation","#text":"%%2464"},{"@Name":"ReturnCode","#text":"0x0"}]}}}
{"Event":{"System":{"Provider":{"@Name":"Microsoft-Windows-Security-Auditing","@Guid":"54849625-5478-4994-a5ba-3e3b0328c30d"},"EventID":"5379","Version":"0","Level":"0","Task":"13824","Opcode":"0","Keywords":"0x8020000000000000","TimeCreated":{"@SystemTime":"2025-05-02 08:52:18.6056472"},"EventRecordID":"89969","Correlation":{"@ActivityID":"1168e054-bb50-0000-2de1-681150bbdb01"},"Execution":{"@ProcessID":"688","@ThreadID":"744"},"Channel":"Security","Computer":"Server002","Security":null},"EventData":{"Data":[{"@Name":"SubjectUserSid","#text":"S-1-5-21-3962163828-2803415714-1403596700-1001"},{"@Name":"SubjectUserName","#text":"lplui"},{"@Name":"SubjectDomainName","#text":"SERVER002"},{"@Name":"SubjectLogonId","#text":"0x39737"},{"@Name":"TargetName","#text":"MicrosoftAccount:user=lpluigi44@gmail.com"},{"@Name":"Type","#text":"0"},{"@Name":"CountOfCredentialsReturned","#text":"1"},{"@Name":"ReadOperation","#text":"%%8100"},{"@Name":"ReturnCode","#text":"0"},{"@Name":"ProcessCreationTime","#text":"2025-05-02 08:51:23.7368016"},{"@Name":"ClientProcessId","#text":"4704"}]}}}
{"Event":{"System":{"Provider":{"@Name":"Microsoft-Windows-Security-Auditing","@Guid":"54849625-5478-4994-a5ba-3e3b0328c30d"},"EventID":"5379","Version":"0","Level":"0","Task":"13824","Opcode":"0","Keywords":"0x8020000000000000","TimeCreated":{"@SystemTime":"2025-05-02 08:52:18.6070322"},"EventRecordID":"89970","Correlation":{"@ActivityID":"1168e054-bb50-0000-2de1-681150bbdb01"},"Execution":{"@ProcessID":"688","@ThreadID":"744"},"Channel":"Security","Computer":"Server002","Security":null},"EventData":{"Data":[{"@Name":"SubjectUserSid","#text":"S-1-5-21-3962163828-2803415714-1403596700-1001"},{"@Name":"SubjectUserName","#text":"lplui"},{"@Name":"SubjectDomainName","#text":"SERVER002"},{"@Name":"SubjectLogonId","#text":"0x39737"},{"@Name":"TargetName","#text":"WindowsLive:(token):name=lpluigi44@gmail.com;serviceuri=*"},{"@Name":"Type","#text":"0"},{"@Name":"CountOfCredentialsReturned","#text":"0"},{"@Name":"ReadOperation","#text":"%%8100"},{"@Name":"ReturnCode","#text":"3221226021"},{"@Name":"ProcessCreationTime","#text":"2025-05-02 08:51:23.7368016"},{"@Name":"ClientProcessId","#text":"4704"}]}}}
{"Event":{"System":{"Provider":{"@Name":"Microsoft-Windows-Security-Auditing","@Guid":"54849625-5478-4994-a5ba-3e3b0328c30d"},"EventID":"5379","Version":"0","Level":"0","Task":"13824","Opcode":"0","Keywords":"0x8020000000000000","TimeCreated":{"@SystemTime":"2025-05-02 08:52:18.6070807"},"EventRecordID":"89971","Correlation":{"@ActivityID":"1168e054-bb50-0000-2de1-681150bbdb01"},"Execution":{"@ProcessID":"688","@ThreadID":"744"},"Channel":"Security","Computer":"Server002","Security":null},"EventData":{"Data":[{"@Name":"SubjectUserSid","#text":"S-1-5-21-3962163828-2803415714-1403596700-1001"},{"@Name":"SubjectUserName","#text":"lplui"},{"@Name":"SubjectDomainName","#text":"SERVER002"},{"@Name":"SubjectLogonId","#text":"0x39737"},{"@Name":"TargetName","#text":"WindowsLive:(cert):name=lpluigi44@gmail.com;serviceuri=*"},{"@Name":"Type","#text":"0"},{"@Name":"CountOfCredentialsReturned","#text":"0"},{"@Name":"ReadOperation","#text":"%%8100"},{"@Name":"ReturnCode","#text":"3221226021"},{"@Name":"ProcessCreationTime","#text":"2025-05-02 08:51:23.7368016"},{"@Name":"ClientProcessId","#text":"4704"}]}}}
{"Event":{"System":{"Provider":{"@Name":"Microsoft-Windows-Security-Auditing","@Guid":"54849625-5478-4994-a5ba-3e3b0328c30d"},"EventID":"5379","Version":"0","Level":"0","Task":"13824","Opcode":"0","Keywords":"0x8020000000000000","TimeCreated":{"@SystemTime":"2025-05-02 08:52:18.6072825"},"EventRecordID":"89972","Correlation":{"@ActivityID":"1168e054-bb50-0000-2de1-681150bbdb01"},"Execution":{"@ProcessID":"688","@ThreadID":"744"},"Channel":"Security","Computer":"Server002","Security":null},"EventData":{"Data":[{"@Name":"SubjectUserSid","#text":"S-1-5-21-3962163828-2803415714-1403596700-1001"},{"@Name":"SubjectUserName","#text":"lplui"},{"@Name":"SubjectDomainName","#text":"SERVER002"},{"@Name":"SubjectLogonId","#text":"0x39737"},{"@Name":"TargetName","#text":"MicrosoftAccount:user=lpluigi44@gmail.com"},{"@Name":"Type","#text":"0"},{"@Name":"CountOfCredentialsReturned","#text":"1"},{"@Name":"ReadOperation","#text":"%%8100"},{"@Name":"ReturnCode","#text":"0"},{"@Name":"ProcessCreationTime","#text":"2025-05-02 08:51:23.7368016"},{"@Name":"ClientProcessId","#text":"4704"}]}}}
{"Event":{"System":{"Provider":{"@Name":"Microsoft-Windows-Security-Auditing","@Guid":"54849625-5478-4994-a5ba-3e3b0328c30d"},"EventID":"5379","Version":"0","Level":"0","Task":"13824","Opcode":"0","Keywords":"0x8020000000000000","TimeCreated":{"@SystemTime":"2025-05-02 08:52:18.6080121"},"EventRecordID":"89973","Correlation":{"@ActivityID":"1168e054-bb50-0000-2de1-681150bbdb01"},"Execution":{"@ProcessID":"688","@ThreadID":"752"},"Channel":"Security","Computer":"Server002","Security":null},"EventData":{"Data":[{"@Name":"SubjectUserSid","#text":"S-1-5-21-3962163828-2803415714-1403596700-1001"},{"@Name":"SubjectUserName","#text":"lplui"},{"@Name":"SubjectDomainName","#text":"SERVER002"},{"@Name":"SubjectLogonId","#text":"0x39737"},{"@Name":"TargetName","#text":"WindowsLive:(token):name=lpluigi44@gmail.com;serviceuri=*"},{"@Name":"Type","#text":"0"},{"@Name":"CountOfCredentialsReturned","#text":"0"},{"@Name":"ReadOperation","#text":"%%8100"},{"@Name":"ReturnCode","#text":"3221226021"},{"@Name":"ProcessCreationTime","#text":"2025-05-02 08:51:23.7368016"},{"@Name":"ClientProcessId","#text":"4704"}]}}}
{"Event":{"System":{"Provider":{"@Name":"Microsoft-Windows-Security-Auditing","@Guid":"54849625-5478-4994-a5ba-3e3b0328c30d"},"EventID":"5379","Version":"0","Level":"0","Task":"13824","Opcode":"0","Keywords":"0x8020000000000000","TimeCreated":{"@SystemTime":"2025-05-02 08:52:18.6080583"},"EventRecordID":"89974","Correlation":{"@ActivityID":"1168e054-bb50-0000-2de1-681150bbdb01"},"Execution":{"@ProcessID":"688","@ThreadID":"752"},"Channel":"Security","Computer":"Server002","Security":null},"EventData":{"Data":[{"@Name":"SubjectUserSid","#text":"S-1-5-21-3962163828-2803415714-1403596700-1001"},{"@Name":"SubjectUserName","#text":"lplui"},{"@Name":"SubjectDomainName","#text":"SERVER002"},{"@Name":"SubjectLogonId","#text":"0x39737"},{"@Name":"TargetName","#text":"WindowsLive:(cert):name=lpluigi44@gmail.com;serviceuri=*"},{"@Name":"Type","#text":"0"},{"@Name":"CountOfCredentialsReturned","#text":"0"},{"@Name":"ReadOperation","#text":"%%8100"},{"@Name":"ReturnCode","#text":"3221226021"},{"@Name":"ProcessCreationTime","#text":"2025-05-02 08:51:23.7368016"},{"@Name":"ClientProcessId","#text":"4704"}]}}}
{"Event":{"System":{"Provider":{"@Name":"Microsoft-Windows-Security-Auditing","@Guid":"54849625-5478-4994-a5ba-3e3b0328c30d"},"EventID":"5379","Version":"0","Level":"0","Task":"13824","Opcode":"0","Keywords":"0x8020000000000000","TimeCreated":{"@SystemTime":"2025-05-02 08:52:18.6080301"},"EventRecordID":"89975","Correlation":{"@ActivityID":"1168e054-bb50-0000-2de1-681150bbdb01"},"Execution":{"@ProcessID":"688","@ThreadID":"744"},"Channel":"Security","Computer":"Server002","Security":null},"EventData":{"Data":[{"@Name":"SubjectUserSid","#text":"S-1-5-21-3962163828-2803415714-1403596700-1001"},{"@Name":"SubjectUserName","#text":"lplui"},{"@Name":"SubjectDomainName","#text":"SERVER002"},{"@Name":"SubjectLogonId","#text":"0x39737"},{"@Name":"TargetName","#text":"MicrosoftAccount:user=lpluigi44@gmail.com"},{"@Name":"Type","#text":"0"},{"@Name":"CountOfCredentialsReturned","#text":"1"},{"@Name":"ReadOperation","#text":"%%8100"},{"@Name":"ReturnCode","#text":"0"},{"@Name":"ProcessCreationTime","#text":"2025-05-02 08:51:23.7368016"},{"@Name":"ClientProcessId","#text":"4704"}]}}}
{"Event":{"System":{"Provider":{"@Name":"Microsoft-Windows-Security-Auditing","@Guid":"54849625-5478-4994-a5ba-3e3b0328c30d"},"EventID":"5379","Version":"0","Level":"0","Task":"13824","Opcode":"0","Keywords":"0x8020000000000000","TimeCreated":{"@SystemTime":"2025-05-02 08:52:18.6092135"},"EventRecordID":"89976","Correlation":{"@ActivityID":"1168e054-bb50-0000-2de1-681150bbdb01"},"Execution":{"@ProcessID":"688","@ThreadID":"744"},"Channel":"Security","Computer":"Server002","Security":null},"EventData":{"Data":[{"@Name":"SubjectUserSid","#text":"S-1-5-21-3962163828-2803415714-1403596700-1001"},{"@Name":"SubjectUserName","#text":"lplui"},{"@Name":"SubjectDomainName","#text":"SERVER002"},{"@Name":"SubjectLogonId","#text":"0x39737"},{"@Name":"TargetName","#text":"MicrosoftAccount:user=lpluigi44@gmail.com"},{"@Name":"Type","#text":"0"},{"@Name":"CountOfCredentialsReturned","#text":"1"},{"@Name":"ReadOperation","#text":"%%8100"},{"@Name":"ReturnCode","#text":"0"},{"@Name":"ProcessCreationTime","#text":"2025-05-02 08:51:23.7368016"},{"@Name":"ClientProcessId","#text":"4704"}]}}}
{"Event":{"System":{"Provider":{"@Name":"Microsoft-Windows-Security-Auditing","@Guid":"54849625-5478-4994-a5ba-3e3b0328c30d"},"EventID":"5379","Version":"0","Level":"0","Task":"13824","Opcode":"0","Keywords":"0x8020000000000000","TimeCreated":{"@SystemTime":"2025-05-02 08:52:18.6111996"},"EventRecordID":"89977","Correlation":{"@ActivityID":"1168e054-bb50-0000-2de1-681150bbdb01"},"Execution":{"@ProcessID":"688","@ThreadID":"744"},"Channel":"Security","Computer":"Server002","Security":null},"EventData":{"Data":[{"@Name":"SubjectUserSid","#text":"S-1-5-21-3962163828-2803415714-1403596700-1001"},{"@Name":"SubjectUserName","#text":"lplui"},{"@Name":"SubjectDomainName","#text":"SERVER002"},{"@Name":"SubjectLogonId","#text":"0x39737"},{"@Name":"TargetName","#text":"MicrosoftAccount:user=lpluigi44@gmail.com"},{"@Name":"Type","#text":"0"},{"@Name":"CountOfCredentialsReturned","#text":"1"},{"@Name":"ReadOperation","#text":"%%8100"},{"@Name":"ReturnCode","#text":"0"},{"@Name":"ProcessCreationTime","#text":"2025-05-02 08:51:23.7368016"},{"@Name":"ClientProcessId","#text":"4704"}]}}}
{"Event":{"System":{"Provider":{"@Name":"Microsoft-Windows-Security-Auditing","@Guid":"54849625-5478-4994-a5ba-3e3b0328c30d"},"EventID":"5379","Version":"0","Level":"0","Task":"13824","Opcode":"0","Keywords":"0x8020000000000000","TimeCreated":{"@SystemTime":"2025-05-02 08:52:18.6125460"},"EventRecordID":"89978","Correlation":{"@ActivityID":"1168e054-bb50-0000-2de1-681150bbdb01"},"Execution":{"@ProcessID":"688","@ThreadID":"744"},"Channel":"Security","Computer":"Server002","Security":null},"EventData":{"Data":[{"@Name":"SubjectUserSid","#text":"S-1-5-21-3962163828-2803415714-1403596700-1001"},{"@Name":"SubjectUserName","#text":"lplui"},{"@Name":"SubjectDomainName","#text":"SERVER002"},{"@Name":"SubjectLogonId","#text":"0x39737"},{"@Name":"TargetName","#text":"MicrosoftAccount:user=lpluigi44@gmail.com"},{"@Name":"Type","#text":"0"},{"@Name":"CountOfCredentialsReturned","#text":"1"},{"@Name":"ReadOperation","#text":"%%8100"},{"@Name":"ReturnCode","#text":"0"},{"@Name":"ProcessCreationTime","#text":"2025-05-02 08:51:23.7368016"},{"@Name":"ClientProcessId","#text":"4704"}]}}}
{"Event":{"System":{"Provider":{"@Name":"Microsoft-Windows-Security-Auditing","@Guid":"54849625-5478-4994-a5ba-3e3b0328c30d"},"EventID":"5379","Version":"0","Level":"0","Task":"13824","Opcode":"0","Keywords":"0x8020000000000000","TimeCreated":{"@SystemTime":"2025-05-02 08:52:18.7903586"},"EventRecordID":"89979","Correlation":{"@ActivityID":"1168e054-bb50-0000-2de1-681150bbdb01"},"Execution":{"@ProcessID":"688","@ThreadID":"744"},"Channel":"Security","Computer":"Server002","Security":null},"EventData":{"Data":[{"@Name":"SubjectUserSid","#text":"S-1-5-21-3962163828-2803415714-1403596700-1001"},{"@Name":"SubjectUserName","#text":"lplui"},{"@Name":"SubjectDomainName","#text":"SERVER002"},{"@Name":"SubjectLogonId","#text":"0x39737"},{"@Name":"TargetName","#text":"MicrosoftAccount:user=lpluigi44@gmail.com"},{"@Name":"Type","#text":"0"},{"@Name":"CountOfCredentialsReturned","#text":"1"},{"@Name":"ReadOperation","#text":"%%8100"},{"@Name":"ReturnCode","#text":"0"},{"@Name":"ProcessCreationTime","#text":"2025-05-02 08:51:23.7368016"},{"@Name":"ClientProcessId","#text":"4704"}]}}}
{"Event":{"System":{"Provider":{"@Name":"Microsoft-Windows-Security-Auditing","@Guid":"54849625-5478-4994-a5ba-3e3b0328c30d"},"EventID":"5379","Version":"0","Level":"0","Task":"13824","Opcode":"0","Keywords":"0x8020000000000000","TimeCreated":{"@SystemTime":"2025-05-02 08:52:18.7905607"},"EventRecordID":"89980","Correlation":{"@ActivityID":"1168e054-bb50-0000-2de1-681150bbdb01"},"Execution":{"@ProcessID":"688","@ThreadID":"744"},"Channel":"Security","Computer":"Server002","Security":null},"EventData":{"Data":[{"@Name":"SubjectUserSid","#text":"S-1-5-21-3962163828-2803415714-1403596700-1001"},{"@Name":"SubjectUserName","#text":"lplui"},{"@Name":"SubjectDomainName","#text":"SERVER002"},{"@Name":"SubjectLogonId","#text":"0x39737"},{"@Name":"TargetName","#text":"MicrosoftAccount:user=lpluigi44@gmail.com"},{"@Name":"Type","#text":"0"},{"@Name":"CountOfCredentialsReturned","#text":"1"},{"@Name":"ReadOperation","#text":"%%8100"},{"@Name":"ReturnCode","#text":"0"},{"@Name":"ProcessCreationTime","#text":"2025-05-02 08:51:23.7368016"},{"@Name":"ClientProcessId","#text":"4704"}]}}}
{"Event":{"System":{"Provider":{"@Name":"Microsoft-Windows-Security-Auditing","@Guid":"54849625-5478-4994-a5ba-3e3b0328c30d"},"EventID":"5379","Version":"0","Level":"0","Task":"13824","Opcode":"0","Keywords":"0x8020000000000000","TimeCreated":{"@SystemTime":"2025-05-02 08:52:18.7907794"},"EventRecordID":"89981","Correlation":{"@ActivityID":"1168e054-bb50-0000-2de1-681150bbdb01"},"Execution":{"@ProcessID":"688","@ThreadID":"744"},"Channel":"Security","Computer":"Server002","Security":null},"EventData":{"Data":[{"@Name":"SubjectUserSid","#text":"S-1-5-21-3962163828-2803415714-1403596700-1001"},{"@Name":"SubjectUserName","#text":"lplui"},{"@Name":"SubjectDomainName","#text":"SERVER002"},{"@Name":"SubjectLogonId","#text":"0x39737"},{"@Name":"TargetName","#text":"MicrosoftAccount:user=lpluigi44@gmail.com"},{"@Name":"Type","#text":"0"},{"@Name":"CountOfCredentialsReturned","#text":"1"},{"@Name":"ReadOperation","#text":"%%8100"},{"@Name":"ReturnCode","#text":"0"},{"@Name":"ProcessCreationTime","#text":"2025-05-02 08:51:23.7368016"},{"@Name":"ClientProcessId","#text":"4704"}]}}}
{"Event":{"System":{"Provider":{"@Name":"Microsoft-Windows-Security-Auditing","@Guid":"54849625-5478-4994-a5ba-3e3b0328c30d"},"EventID":"5379","Version":"0","Level":"0","Task":"13824","Opcode":"0","Keywords":"0x8020000000000000","TimeCreated":{"@SystemTime":"2025-05-02 08:52:18.7911750"},"EventRecordID":"89982","Correlation":{"@ActivityID":"1168e054-bb50-0000-2de1-681150bbdb01"},"Execution":{"@ProcessID":"688","@ThreadID":"744"},"Channel":"Security","Computer":"Server002","Security":null},"EventData":{"Data":[{"@Name":"SubjectUserSid","#text":"S-1-5-21-3962163828-2803415714-1403596700-1001"},{"@Name":"SubjectUserName","#text":"lplui"},{"@Name":"SubjectDomainName","#text":"SERVER002"},{"@Name":"SubjectLogonId","#text":"0x39737"},{"@Name":"TargetName","#text":"MicrosoftAccount:user=lpluigi44@gmail.com"},{"@Name":"Type","#text":"0"},{"@Name":"CountOfCredentialsReturned","#text":"1"},{"@Name":"ReadOperation","#text":"%%8100"},{"@Name":"ReturnCode","#text":"0"},{"@Name":"ProcessCreationTime","#text":"2025-05-02 08:51:23.7368016"},{"@Name":"ClientProcessId","#text":"4704"}]}}}
{"Event":{"System":{"Provider":{"@Name":"Microsoft-Windows-Security-Auditing","@Guid":"54849625-5478-4994-a5ba-3e3b0328c30d"},"EventID":"5379","Version":"0","Level":"0","Task":"13824","Opcode":"0","Keywords":"0x8020000000000000","TimeCreated":{"@SystemTime":"2025-05-02 08:52:18.7914023"},"EventRecordID":"89983","Correlation":{"@ActivityID":"1168e054-bb50-0000-2de1-681150bbdb01"},"Execution":{"@ProcessID":"688","@ThreadID":"744"},"Channel":"Security","Computer":"Server002","Security":null},"EventData":{"Data":[{"@Name":"SubjectUserSid","#text":"S-1-5-21-3962163828-2803415714-1403596700-1001"},{"@Name":"SubjectUserName","#text":"lplui"},{"@Name":"SubjectDomainName","#text":"SERVER002"},{"@Name":"SubjectLogonId","#text":"0x39737"},{"@Name":"TargetName","#text":"MicrosoftAccount:user=lpluigi44@gmail.com"},{"@Name":"Type","#text":"0"},{"@Name":"CountOfCredentialsReturned","#text":"1"},{"@Name":"ReadOperation","#text":"%%8100"},{"@Name":"ReturnCode","#text":"0"},{"@Name":"ProcessCreationTime","#text":"2025-05-02 08:51:23.7368016"},{"@Name":"ClientProcessId","#text":"4704"}]}}}
{"Event":{"System":{"Provider":{"@Name":"Microsoft-Windows-Security-Auditing","@Guid":"54849625-5478-4994-a5ba-3e3b0328c30d"},"EventID":"5379","Version":"0","Level":"0","Task":"13824","Opcode":"0","Keywords":"0x8020000000000000","TimeCreated":{"@SystemTime":"2025-05-02 08:52:18.7915633"},"EventRecordID":"89984","Correlation":{"@ActivityID":"1168e054-bb50-0000-2de1-681150bbdb01"},"Execution":{"@ProcessID":"688","@ThreadID":"744"},"Channel":"Security","Computer":"Server002","Security":null},"EventData":{"Data":[{"@Name":"SubjectUserSid","#text":"S-1-5-21-3962163828-2803415714-1403596700-1001"},{"@Name":"SubjectUserName","#text":"lplui"},{"@Name":"SubjectDomainName","#text":"SERVER002"},{"@Name":"SubjectLogonId","#text":"0x39737"},{"@Name":"TargetName","#text":"MicrosoftAccount:user=lpluigi44@gmail.com"},{"@Name":"Type","#text":"0"},{"@Name":"CountOfCredentialsReturned","#text":"1"},{"@Name":"ReadOperation","#text":"%%8100"},{"@Name":"ReturnCode","#text":"0"},{"@Name":"ProcessCreationTime","#text":"2025-05-02 08:51:23.7368016"},{"@Name":"ClientProcessId","#text":"4704"}]}}}
{"Event":{"System":{"Provider":{"@Name":"Microsoft-Windows-Security-Auditing","@Guid":"54849625-5478-4994-a5ba-3e3b0328c30d"},"EventID":"5379","Version":"0","Level":"0","Task":"13824","Opcode":"0","Keywords":"0x8020000000000000","TimeCreated":{"@SystemTime":"2025-05-02 08:52:18.7919712"},"EventRecordID":"89985","Correlation":{"@ActivityID":"1168e054-bb50-0000-2de1-681150bbdb01"},"Execution":{"@ProcessID":"688","@ThreadID":"744"},"Channel":"Security","Computer":"Server002","Security":null},"EventData":{"Data":[{"@Name":"SubjectUserSid","#text":"S-1-5-21-3962163828-2803415714-1403596700-1001"},{"@Name":"SubjectUserName","#text":"lplui"},{"@Name":"SubjectDomainName","#text":"SERVER002"},{"@Name":"SubjectLogonId","#text":"0x39737"},{"@Name":"TargetName","#text":"MicrosoftAccount:user=lpluigi44@gmail.com"},{"@Name":"Type","#text":"0"},{"@Name":"CountOfCredentialsReturned","#text":"1"},{"@Name":"ReadOperation","#text":"%%8100"},{"@Name":"ReturnCode","#text":"0"},{"@Name":"ProcessCreationTime","#text":"2025-05-02 08:51:23.7368016"},{"@Name":"ClientProcessId","#text":"4704"}]}}}
{"Event":{"System":{"Provider":{"@Name":"Microsoft-Windows-Security-Auditing","@Guid":"54849625-5478-4994-a5ba-3e3b0328c30d"},"EventID":"5379","Version":"0","Level":"0","Task":"13824","Opcode":"0","Keywords":"0x8020000000000000","TimeCreated":{"@SystemTime":"2025-05-02 08:52:18.7921421"},"EventRecordID":"89986","Correlation":{"@ActivityID":"1168e054-bb50-0000-2de1-681150bbdb01"},"Execution":{"@ProcessID":"688","@ThreadID":"744"},"Channel":"Security","Computer":"Server002","Security":null},"EventData":{"Data":[{"@Name":"SubjectUserSid","#text":"S-1-5-21-3962163828-2803415714-1403596700-1001"},{"@Name":"SubjectUserName","#text":"lplui"},{"@Name":"SubjectDomainName","#text":"SERVER002"},{"@Name":"SubjectLogonId","#text":"0x39737"},{"@Name":"TargetName","#text":"MicrosoftAccount:user=lpluigi44@gmail.com"},{"@Name":"Type","#text":"0"},{"@Name":"CountOfCredentialsReturned","#text":"1"},{"@Name":"ReadOperation","#text":"%%8100"},{"@Name":"ReturnCode","#text":"0"},{"@Name":"ProcessCreationTime","#text":"2025-05-02 08:51:23.7368016"},{"@Name":"ClientProcessId","#text":"4704"}]}}}
{"Event":{"System":{"Provider":{"@Name":"Microsoft-Windows-Security-Auditing","@Guid":"54849625-5478-4994-a5ba-3e3b0328c30d"},"EventID":"5379","Version":"0","Level":"0","Task":"13824","Opcode":"0","Keywords":"0x8020000000000000","TimeCreated":{"@SystemTime":"2025-05-02 08:52:18.7925049"},"EventRecordID":"89987","Correlation":{"@ActivityID":"1168e054-bb50-0000-2de1-681150bbdb01"},"Execution":{"@ProcessID":"688","@ThreadID":"744"},"Channel":"Security","Computer":"Server002","Security":null},"EventData":{"Data":[{"@Name":"SubjectUserSid","#text":"S-1-5-21-3962163828-2803415714-1403596700-1001"},{"@Name":"SubjectUserName","#text":"lplui"},{"@Name":"SubjectDomainName","#text":"SERVER002"},{"@Name":"SubjectLogonId","#text":"0x39737"},{"@Name":"TargetName","#text":"MicrosoftAccount:user=lpluigi44@gmail.com"},{"@Name":"Type","#text":"0"},{"@Name":"CountOfCredentialsReturned","#text":"1"},{"@Name":"ReadOperation","#text":"%%8100"},{"@Name":"ReturnCode","#text":"0"},{"@Name":"ProcessCreationTime","#text":"2025-05-02 08:51:23.7368016"},{"@Name":"ClientProcessId","#text":"4704"}]}}}
{"Event":{"System":{"Provider":{"@Name":"Microsoft-Windows-Security-Auditing","@Guid":"54849625-5478-4994-a5ba-3e3b0328c30d"},"EventID":"5379","Version":"0","Level":"0","Task":"13824","Opcode":"0","Keywords":"0x8020000000000000","TimeCreated":{"@SystemTime":"2025-05-02 08:52:18.7928757"},"EventRecordID":"89988","Correlation":{"@ActivityID":"1168e054-bb50-0000-2de1-681150bbdb01"},"Execution":{"@ProcessID":"688","@ThreadID":"744"},"Channel":"Security","Computer":"Server002","Security":null},"EventData":{"Data":[{"@Name":"SubjectUserSid","#text":"S-1-5-21-3962163828-2803415714-1403596700-1001"},{"@Name":"SubjectUserName","#text":"lplui"},{"@Name":"SubjectDomainName","#text":"SERVER002"},{"@Name":"SubjectLogonId","#text":"0x39737"},{"@Name":"TargetName","#text":"MicrosoftAccount:user=lpluigi44@gmail.com"},{"@Name":"Type","#text":"0"},{"@Name":"CountOfCredentialsReturned","#text":"1"},{"@Name":"ReadOperation","#text":"%%8100"},{"@Name":"ReturnCode","#text":"0"},{"@Name":"ProcessCreationTime","#text":"2025-05-02 08:51:23.7368016"},{"@Name":"ClientProcessId","#text":"4704"}]}}}
{"Event":{"System":{"Provider":{"@Name":"Microsoft-Windows-Security-Auditing","@Guid":"54849625-5478-4994-a5ba-3e3b0328c30d"},"EventID":"5379","Version":"0","Level":"0","Task":"13824","Opcode":"0","Keywords":"0x8020000000000000","TimeCreated":{"@SystemTime":"2025-05-02 08:52:18.7932704"},"EventRecordID":"89989","Correlation":{"@ActivityID":"1168e054-bb50-0000-2de1-681150bbdb01"},"Execution":{"@ProcessID":"688","@ThreadID":"744"},"Channel":"Security","Computer":"Server002","Security":null},"EventData":{"Data":[{"@Name":"SubjectUserSid","#text":"S-1-5-21-3962163828-2803415714-1403596700-1001"},{"@Name":"SubjectUserName","#text":"lplui"},{"@Name":"SubjectDomainName","#text":"SERVER002"},{"@Name":"SubjectLogonId","#text":"0x39737"},{"@Name":"TargetName","#text":"MicrosoftAccount:user=lpluigi44@gmail.com"},{"@Name":"Type","#text":"0"},{"@Name":"CountOfCredentialsReturned","#text":"1"},{"@Name":"ReadOperation","#text":"%%8100"},{"@Name":"ReturnCode","#text":"0"},{"@Name":"ProcessCreationTime","#text":"2025-05-02 08:51:23.7368016"},{"@Name":"ClientProcessId","#text":"4704"}]}}}
{"Event":{"System":{"Provider":{"@Name":"Microsoft-Windows-Security-Auditing","@Guid":"54849625-5478-4994-a5ba-3e3b0328c30d"},"EventID":"5379","Version":"0","Level":"0","Task":"13824","Opcode":"0","Keywords":"0x8020000000000000","TimeCreated":{"@SystemTime":"2025-05-02 08:52:18.7937059"},"EventRecordID":"89990","Correlation":{"@ActivityID":"1168e054-bb50-0000-2de1-681150bbdb01"},"Execution":{"@ProcessID":"688","@ThreadID":"744"},"Channel":"Security","Computer":"Server002","Security":null},"EventData":{"Data":[{"@Name":"SubjectUserSid","#text":"S-1-5-21-3962163828-2803415714-1403596700-1001"},{"@Name":"SubjectUserName","#text":"lplui"},{"@Name":"SubjectDomainName","#text":"SERVER002"},{"@Name":"SubjectLogonId","#text":"0x39737"},{"@Name":"TargetName","#text":"MicrosoftAccount:user=lpluigi44@gmail.com"},{"@Name":"Type","#text":"0"},{"@Name":"CountOfCredentialsReturned","#text":"1"},{"@Name":"ReadOperation","#text":"%%8100"},{"@Name":"ReturnCode","#text":"0"},{"@Name":"ProcessCreationTime","#text":"2025-05-02 08:51:23.7368016"},{"@Name":"ClientProcessId","#text":"4704"}]}}}
{"Event":{"System":{"Provider":{"@Name":"Microsoft-Windows-Security-Auditing","@Guid":"54849625-5478-4994-a5ba-3e3b0328c30d"},"EventID":"5379","Version":"0","Level":"0","Task":"13824","Opcode":"0","Keywords":"0x8020000000000000","TimeCreated":{"@SystemTime":"2025-05-02 08:52:18.7941233"},"EventRecordID":"89991","Correlation":{"@ActivityID":"1168e054-bb50-0000-2de1-681150bbdb01"},"Execution":{"@ProcessID":"688","@ThreadID":"744"},"Channel":"Security","Computer":"Server002","Security":null},"EventData":{"Data":[{"@Name":"SubjectUserSid","#text":"S-1-5-21-3962163828-2803415714-1403596700-1001"},{"@Name":"SubjectUserName","#text":"lplui"},{"@Name":"SubjectDomainName","#text":"SERVER002"},{"@Name":"SubjectLogonId","#text":"0x39737"},{"@Name":"TargetName","#text":"MicrosoftAccount:user=lpluigi44@gmail.com"},{"@Name":"Type","#text":"0"},{"@Name":"CountOfCredentialsReturned","#text":"1"},{"@Name":"ReadOperation","#text":"%%8100"},{"@Name":"ReturnCode","#text":"0"},{"@Name":"ProcessCreationTime","#text":"2025-05-02 08:51:23.7368016"},{"@Name":"ClientProcessId","#text":"4704"}]}}}
{"Event":{"System":{"Provider":{"@Name":"Microsoft-Windows-Security-Auditing","@Guid":"54849625-5478-4994-a5ba-3e3b0328c30d"},"EventID":"5379","Version":"0","Level":"0","Task":"13824","Opcode":"0","Keywords":"0x8020000000000000","TimeCreated":{"@SystemTime":"2025-05-02 08:52:18.7942819"},"EventRecordID":"89992","Correlation":{"@ActivityID":"1168e054-bb50-0000-2de1-681150bbdb01"},"Execution":{"@ProcessID":"688","@ThreadID":"744"},"Channel":"Security","Computer":"Server002","Security":null},"EventData":{"Data":[{"@Name":"SubjectUserSid","#text":"S-1-5-21-3962163828-2803415714-1403596700-1001"},{"@Name":"SubjectUserName","#text":"lplui"},{"@Name":"SubjectDomainName","#text":"SERVER002"},{"@Name":"SubjectLogonId","#text":"0x39737"},{"@Name":"TargetName","#text":"MicrosoftAccount:user=lpluigi44@gmail.com"},{"@Name":"Type","#text":"0"},{"@Name":"CountOfCredentialsReturned","#text":"1"},{"@Name":"ReadOperation","#text":"%%8100"},{"@Name":"ReturnCode","#text":"0"},{"@Name":"ProcessCreationTime","#text":"2025-05-02 08:51:23.7368016"},{"@Name":"ClientProcessId","#text":"4704"}]}}}
{"Event":{"System":{"Provider":{"@Name":"Microsoft-Windows-Security-Auditing","@Guid":"54849625-5478-4994-a5ba-3e3b0328c30d"},"EventID":"5379","Version":"0","Level":"0","Task":"13824","Opcode":"0","Keywords":"0x8020000000000000","TimeCreated":{"@SystemTime":"2025-05-02 08:52:18.7944743"},"EventRecordID":"89993","Correlation":{"@ActivityID":"1168e054-bb50-0000-2de1-681150bbdb01"},"Execution":{"@ProcessID":"688","@ThreadID":"744"},"Channel":"Security","Computer":"Server002","Security":null},"EventData":{"Data":[{"@Name":"SubjectUserSid","#text":"S-1-5-21-3962163828-2803415714-1403596700-1001"},{"@Name":"SubjectUserName","#text":"lplui"},{"@Name":"SubjectDomainName","#text":"SERVER002"},{"@Name":"SubjectLogonId","#text":"0x39737"},{"@Name":"TargetName","#text":"MicrosoftAccount:user=lpluigi44@gmail.com"},{"@Name":"Type","#text":"0"},{"@Name":"CountOfCredentialsReturned","#text":"1"},{"@Name":"ReadOperation","#text":"%%8100"},{"@Name":"ReturnCode","#text":"0"},{"@Name":"ProcessCreationTime","#text":"2025-05-02 08:51:23.7368016"},{"@Name":"ClientProcessId","#text":"4704"}]}}}
{"Event":{"System":{"Provider":{"@Name":"Microsoft-Windows-Security-Auditing","@Guid":"54849625-5478-4994-a5ba-3e3b0328c30d"},"EventID":"5379","Version":"0","Level":"0","Task":"13824","Opcode":"0","Keywords":"0x8020000000000000","TimeCreated":{"@SystemTime":"2025-05-02 08:52:18.7952108"},"EventRecordID":"89994","Correlation":{"@ActivityID":"1168e054-bb50-0000-2de1-681150bbdb01"},"Execution":{"@ProcessID":"688","@ThreadID":"744"},"Channel":"Security","Computer":"Server002","Security":null},"EventData":{"Data":[{"@Name":"SubjectUserSid","#text":"S-1-5-21-3962163828-2803415714-1403596700-1001"},{"@Name":"SubjectUserName","#text":"lplui"},{"@Name":"SubjectDomainName","#text":"SERVER002"},{"@Name":"SubjectLogonId","#text":"0x39737"},{"@Name":"TargetName","#text":"MicrosoftAccount:user=lpluigi44@gmail.com"},{"@Name":"Type","#text":"1"},{"@Name":"CountOfCredentialsReturned","#text":"1"},{"@Name":"ReadOperation","#text":"%%8099"},{"@Name":"ReturnCode","#text":"0"},{"@Name":"ProcessCreationTime","#text":"2025-05-02 08:51:23.7368016"},{"@Name":"ClientProcessId","#text":"4704"}]}}}
{"Event":{"System":{"Provider":{"@Name":"Microsoft-Windows-Security-Auditing","@Guid":"54849625-5478-4994-a5ba-3e3b0328c30d"},"EventID":"5379","Version":"0","Level":"0","Task":"13824","Opcode":"0","Keywords":"0x8020000000000000","TimeCreated":{"@SystemTime":"2025-05-02 08:52:18.8020359"},"EventRecordID":"89995","Correlation":{"@ActivityID":"1168e054-bb50-0000-2de1-681150bbdb01"},"Execution":{"@ProcessID":"688","@ThreadID":"744"},"Channel":"Security","Computer":"Server002","Security":null},"EventData":{"Data":[{"@Name":"SubjectUserSid","#text":"S-1-5-21-3962163828-2803415714-1403596700-1001"},{"@Name":"SubjectUserName","#text":"lplui"},{"@Name":"SubjectDomainName","#text":"SERVER002"},{"@Name":"SubjectLogonId","#text":"0x39737"},{"@Name":"TargetName","#text":"MicrosoftAccount:user=lpluigi44@gmail.com"},{"@Name":"Type","#text":"0"},{"@Name":"CountOfCredentialsReturned","#text":"1"},{"@Name":"ReadOperation","#text":"%%8100"},{"@Name":"ReturnCode","#text":"0"},{"@Name":"ProcessCreationTime","#text":"2025-05-02 08:51:23.7368016"},{"@Name":"ClientProcessId","#text":"4704"}]}}}
{"Event":{"System":{"Provider":{"@Name":"Microsoft-Windows-Security-Auditing","@Guid":"54849625-5478-4994-a5ba-3e3b0328c30d"},"EventID":"5379","Version":"0","Level":"0","Task":"13824","Opcode":"0","Keywords":"0x8020000000000000","TimeCreated":{"@SystemTime":"2025-05-02 08:52:18.8022489"},"EventRecordID":"89996","Correlation":{"@ActivityID":"1168e054-bb50-0000-2de1-681150bbdb01"},"Execution":{"@ProcessID":"688","@ThreadID":"744"},"Channel":"Security","Computer":"Server002","Security":null},"EventData":{"Data":[{"@Name":"SubjectUserSid","#text":"S-1-5-21-3962163828-2803415714-1403596700-1001"},{"@Name":"SubjectUserName","#text":"lplui"},{"@Name":"SubjectDomainName","#text":"SERVER002"},{"@Name":"SubjectLogonId","#text":"0x39737"},{"@Name":"TargetName","#text":"MicrosoftAccount:user=lpluigi44@gmail.com"},{"@Name":"Type","#text":"0"},{"@Name":"CountOfCredentialsReturned","#text":"1"},{"@Name":"ReadOperation","#text":"%%8100"},{"@Name":"ReturnCode","#text":"0"},{"@Name":"ProcessCreationTime","#text":"2025-05-02 08:51:23.7368016"},{"@Name":"ClientProcessId","#text":"4704"}]}}}
{"Event":{"System":{"Provider":{"@Name":"Microsoft-Windows-Security-Auditing","@Guid":"54849625-5478-4994-a5ba-3e3b0328c30d"},"EventID":"5379","Version":"0","Level":"0","Task":"13824","Opcode":"0","Keywords":"0x8020000000000000","TimeCreated":{"@SystemTime":"2025-05-02 08:52:18.8024927"},"EventRecordID":"89997","Correlation":{"@ActivityID":"1168e054-bb50-0000-2de1-681150bbdb01"},"Execution":{"@ProcessID":"688","@ThreadID":"744"},"Channel":"Security","Computer":"Server002","Security":null},"EventData":{"Data":[{"@Name":"SubjectUserSid","#text":"S-1-5-21-3962163828-2803415714-1403596700-1001"},{"@Name":"SubjectUserName","#text":"lplui"},{"@Name":"SubjectDomainName","#text":"SERVER002"},{"@Name":"SubjectLogonId","#text":"0x39737"},{"@Name":"TargetName","#text":"MicrosoftAccount:user=lpluigi44@gmail.com"},{"@Name":"Type","#text":"0"},{"@Name":"CountOfCredentialsReturned","#text":"1"},{"@Name":"ReadOperation","#text":"%%8100"},{"@Name":"ReturnCode","#text":"0"},{"@Name":"ProcessCreationTime","#text":"2025-05-02 08:51:23.7368016"},{"@Name":"ClientProcessId","#text":"4704"}]}}}
