{"Event":{"System":{"Provider":{"@Name":"Microsoft-Windows-Security-Auditing","@Guid":"54849625-5478-4994-a5ba-3e3b0328c30d"},"EventID":"5379","Version":"0","Level":"0","Task":"13824","Opcode":"0","Keywords":"0x8020000000000000","TimeCreated":{"@SystemTime":"2025-05-02 14:43:24.7762589"},"EventRecordID":"91990","Correlation":{"@ActivityID":"1168e054-bb50-0000-2de1-681150bbdb01"},"Execution":{"@ProcessID":"688","@ThreadID":"5964"},"Channel":"Security","Computer":"Server002","Security":null},"EventData":{"Data":[{"@Name":"SubjectUserSid","#text":"S-1-5-21-3962163828-2803415714-1403596700-1001"},{"@Name":"SubjectUserName","#text":"lplui"},{"@Name":"SubjectDomainName","#text":"SERVER002"},{"@Name":"SubjectLogonId","#text":"0x39737"},{"@Name":"TargetName","#text":"MicrosoftAccount:user=lpluigi44@gmail.com"},{"@Name":"Type","#text":"0"},{"@Name":"CountOfCredentialsReturned","#text":"1"},{"@Name":"ReadOperation","#text":"%%8100"},{"@Name":"ReturnCode","#text":"0"},{"@Name":"ProcessCreationTime","#text":"2025-05-02 14:41:30.3975537"},{"@Name":"ClientProcessId","#text":"7256"}]}}}
{"Event":{"System":{"Provider":{"@Name":"Microsoft-Windows-Security-Auditing","@Guid":"54849625-5478-4994-a5ba-3e3b0328c30d"},"EventID":"5379","Version":"0","Level":"0","Task":"13824","Opcode":"0","Keywords":"0x8020000000000000","TimeCreated":{"@SystemTime":"2025-05-02 14:43:24.7779169"},"EventRecordID":"91991","Correlation":{"@ActivityID":"1168e054-bb50-0000-2de1-681150bbdb01"},"Execution":{"@ProcessID":"688","@ThreadID":"5964"},"Channel":"Security","Computer":"Server002","Security":null},"EventData":{"Data":[{"@Name":"SubjectUserSid","#text":"S-1-5-21-3962163828-2803415714-1403596700-1001"},{"@Name":"SubjectUserName","#text":"lplui"},{"@Name":"SubjectDomainName","#text":"SERVER002"},{"@Name":"SubjectLogonId","#text":"0x39737"},{"@Name":"TargetName","#text":"MicrosoftAccount:user=lpluigi44@gmail.com"},{"@Name":"Type","#text":"0"},{"@Name":"CountOfCredentialsReturned","#text":"1"},{"@Name":"ReadOperation","#text":"%%8100"},{"@Name":"ReturnCode","#text":"0"},{"@Name":"ProcessCreationTime","#text":"2025-05-02 14:41:30.3975537"},{"@Name":"ClientProcessId","#text":"7256"}]}}}
{"Event":{"System":{"Provider":{"@Name":"Microsoft-Windows-Security-Auditing","@Guid":"54849625-5478-4994-a5ba-3e3b0328c30d"},"EventID":"5379","Version":"0","Level":"0","Task":"13824","Opcode":"0","Keywords":"0x8020000000000000","TimeCreated":{"@SystemTime":"2025-05-02 14:43:24.7787398"},"EventRecordID":"91992","Correlation":{"@ActivityID":"1168e054-bb50-0000-2de1-681150bbdb01"},"Execution":{"@ProcessID":"688","@ThreadID":"5964"},"Channel":"Security","Computer":"Server002","Security":null},"EventData":{"Data":[{"@Name":"SubjectUserSid","#text":"S-1-5-21-3962163828-2803415714-1403596700-1001"},{"@Name":"SubjectUserName","#text":"lplui"},{"@Name":"SubjectDomainName","#text":"SERVER002"},{"@Name":"SubjectLogonId","#text":"0x39737"},{"@Name":"TargetName","#text":"MicrosoftAccount:user=lpluigi44@gmail.com"},{"@Name":"Type","#text":"0"},{"@Name":"CountOfCredentialsReturned","#text":"1"},{"@Name":"ReadOperation","#text":"%%8100"},{"@Name":"ReturnCode","#text":"0"},{"@Name":"ProcessCreationTime","#text":"2025-05-02 14:41:30.3975537"},{"@Name":"ClientProcessId","#text":"7256"}]}}}
{"Event":{"System":{"Provider":{"@Name":"Microsoft-Windows-Security-Auditing","@Guid":"54849625-5478-4994-a5ba-3e3b0328c30d"},"EventID":"5379","Version":"0","Level":"0","Task":"13824","Opcode":"0","Keywords":"0x8020000000000000","TimeCreated":{"@SystemTime":"2025-05-02 14:43:24.7857150"},"EventRecordID":"91993","Correlation":{"@ActivityID":"1168e054-bb50-0000-2de1-681150bbdb01"},"Execution":{"@ProcessID":"688","@ThreadID":"5964"},"Channel":"Security","Computer":"Server002","Security":null},"EventData":{"Data":[{"@Name":"SubjectUserSid","#text":"S-1-5-21-3962163828-2803415714-1403596700-1001"},{"@Name":"SubjectUserName","#text":"lplui"},{"@Name":"SubjectDomainName","#text":"SERVER002"},{"@Name":"SubjectLogonId","#text":"0x39737"},{"@Name":"TargetName","#text":"MicrosoftAccount:user=lpluigi44@gmail.com"},{"@Name":"Type","#text":"0"},{"@Name":"CountOfCredentialsReturned","#text":"1"},{"@Name":"ReadOperation","#text":"%%8100"},{"@Name":"ReturnCode","#text":"0"},{"@Name":"ProcessCreationTime","#text":"2025-05-02 14:41:30.3975537"},{"@Name":"ClientProcessId","#text":"7256"}]}}}
{"Event":{"System":{"Provider":{"@Name":"Microsoft-Windows-Security-Auditing","@Guid":"54849625-5478-4994-a5ba-3e3b0328c30d"},"EventID":"5379","Version":"0","Level":"0","Task":"13824","Opcode":"0","Keywords":"0x8020000000000000","TimeCreated":{"@SystemTime":"2025-05-02 14:43:24.7903845"},"EventRecordID":"91994","Correlation":{"@ActivityID":"1168e054-bb50-0000-2de1-681150bbdb01"},"Execution":{"@ProcessID":"688","@ThreadID":"5964"},"Channel":"Security","Computer":"Server002","Security":null},"EventData":{"Data":[{"@Name":"SubjectUserSid","#text":"S-1-5-21-3962163828-2803415714-1403596700-1001"},{"@Name":"SubjectUserName","#text":"lplui"},{"@Name":"SubjectDomainName","#text":"SERVER002"},{"@Name":"SubjectLogonId","#text":"0x39737"},{"@Name":"TargetName","#text":"MicrosoftAccount:user=lpluigi44@gmail.com"},{"@Name":"Type","#text":"0"},{"@Name":"CountOfCredentialsReturned","#text":"1"},{"@Name":"ReadOperation","#text":"%%8100"},{"@Name":"ReturnCode","#text":"0"},{"@Name":"ProcessCreationTime","#text":"2025-05-02 14:41:30.3975537"},{"@Name":"ClientProcessId","#text":"7256"}]}}}
{"Event":{"System":{"Provider":{"@Name":"Microsoft-Windows-Security-Auditing","@Guid":"54849625-5478-4994-a5ba-3e3b0328c30d"},"EventID":"5379","Version":"0","Level":"0","Task":"13824","Opcode":"0","Keywords":"0x8020000000000000","TimeCreated":{"@SystemTime":"2025-05-02 14:43:24.7937709"},"EventRecordID":"91995","Correlation":{"@ActivityID":"1168e054-bb50-0000-2de1-681150bbdb01"},"Execution":{"@ProcessID":"688","@ThreadID":"5964"},"Channel":"Security","Computer":"Server002","Security":null},"EventData":{"Data":[{"@Name":"SubjectUserSid","#text":"S-1-5-21-3962163828-2803415714-1403596700-1001"},{"@Name":"SubjectUserName","#text":"lplui"},{"@Name":"SubjectDomainName","#text":"SERVER002"},{"@Name":"SubjectLogonId","#text":"0x39737"},{"@Name":"TargetName","#text":"MicrosoftAccount:user=lpluigi44@gmail.com"},{"@Name":"Type","#text":"0"},{"@Name":"CountOfCredentialsReturned","#text":"1"},{"@Name":"ReadOperation","#text":"%%8100"},{"@Name":"ReturnCode","#text":"0"},{"@Name":"ProcessCreationTime","#text":"2025-05-02 14:41:30.3975537"},{"@Name":"ClientProcessId","#text":"7256"}]}}}
{"Event":{"System":{"Provider":{"@Name":"Microsoft-Windows-Security-Auditing","@Guid":"54849625-5478-4994-a5ba-3e3b0328c30d"},"EventID":"5379","Version":"0","Level":"0","Task":"13824","Opcode":"0","Keywords":"0x8020000000000000","TimeCreated":{"@SystemTime":"2025-05-02 14:43:24.8129940"},"EventRecordID":"91996","Correlation":{"@ActivityID":"1168e054-bb50-0000-2de1-681150bbdb01"},"Execution":{"@ProcessID":"688","@ThreadID":"5964"},"Channel":"Security","Computer":"Server002","Security":null},"EventData":{"Data":[{"@Name":"SubjectUserSid","#text":"S-1-5-21-3962163828-2803415714-1403596700-1001"},{"@Name":"SubjectUserName","#text":"lplui"},{"@Name":"SubjectDomainName","#text":"SERVER002"},{"@Name":"SubjectLogonId","#text":"0x39737"},{"@Name":"TargetName","#text":"MicrosoftAccount:user=lpluigi44@gmail.com"},{"@Name":"Type","#text":"0"},{"@Name":"CountOfCredentialsReturned","#text":"1"},{"@Name":"ReadOperation","#text":"%%8100"},{"@Name":"ReturnCode","#text":"0"},{"@Name":"ProcessCreationTime","#text":"2025-05-02 14:41:30.3975537"},{"@Name":"ClientProcessId","#text":"7256"}]}}}
{"Event":{"System":{"Provider":{"@Name":"Microsoft-Windows-Security-Auditing","@Guid":"54849625-5478-4994-a5ba-3e3b0328c30d"},"EventID":"5379","Version":"0","Level":"0","Task":"13824","Opcode":"0","Keywords":"0x8020000000000000","TimeCreated":{"@SystemTime":"2025-05-02 14:43:24.8158930"},"EventRecordID":"91997","Correlation":{"@ActivityID":"1168e054-bb50-0000-2de1-681150bbdb01"},"Execution":{"@ProcessID":"688","@ThreadID":"5964"},"Channel":"Security","Computer":"Server002","Security":null},"EventData":{"Data":[{"@Name":"SubjectUserSid","#text":"S-1-5-21-3962163828-2803415714-1403596700-1001"},{"@Name":"SubjectUserName","#text":"lplui"},{"@Name":"SubjectDomainName","#text":"SERVER002"},{"@Name":"SubjectLogonId","#text":"0x39737"},{"@Name":"TargetName","#text":"MicrosoftAccount:user=lpluigi44@gmail.com"},{"@Name":"Type","#text":"0"},{"@Name":"CountOfCredentialsReturned","#text":"1"},{"@Name":"ReadOperation","#text":"%%8100"},{"@Name":"ReturnCode","#text":"0"},{"@Name":"ProcessCreationTime","#text":"2025-05-02 14:41:30.3975537"},{"@Name":"ClientProcessId","#text":"7256"}]}}}
{"Event":{"System":{"Provider":{"@Name":"Microsoft-Windows-Security-Auditing","@Guid":"54849625-5478-4994-a5ba-3e3b0328c30d"},"EventID":"5379","Version":"0","Level":"0","Task":"13824","Opcode":"0","Keywords":"0x8020000000000000","TimeCreated":{"@SystemTime":"2025-05-02 14:43:24.8165634"},"EventRecordID":"91998","Correlation":{"@ActivityID":"1168e054-bb50-0000-2de1-681150bbdb01"},"Execution":{"@ProcessID":"688","@ThreadID":"5964"},"Channel":"Security","Computer":"Server002","Security":null},"EventData":{"Data":[{"@Name":"SubjectUserSid","#text":"S-1-5-21-3962163828-2803415714-1403596700-1001"},{"@Name":"SubjectUserName","#text":"lplui"},{"@Name":"SubjectDomainName","#text":"SERVER002"},{"@Name":"SubjectLogonId","#text":"0x39737"},{"@Name":"TargetName","#text":"MicrosoftAccount:user=lpluigi44@gmail.com"},{"@Name":"Type","#text":"0"},{"@Name":"CountOfCredentialsReturned","#text":"1"},{"@Name":"ReadOperation","#text":"%%8100"},{"@Name":"ReturnCode","#text":"0"},{"@Name":"ProcessCreationTime","#text":"2025-05-02 14:41:30.3975537"},{"@Name":"ClientProcessId","#text":"7256"}]}}}
{"Event":{"System":{"Provider":{"@Name":"Microsoft-Windows-Security-Auditing","@Guid":"54849625-5478-4994-a5ba-3e3b0328c30d"},"EventID":"5379","Version":"0","Level":"0","Task":"13824","Opcode":"0","Keywords":"0x8020000000000000","TimeCreated":{"@SystemTime":"2025-05-02 14:43:24.8171133"},"EventRecordID":"91999","Correlation":{"@ActivityID":"1168e054-bb50-0000-2de1-681150bbdb01"},"Execution":{"@ProcessID":"688","@ThreadID":"5964"},"Channel":"Security","Computer":"Server002","Security":null},"EventData":{"Data":[{"@Name":"SubjectUserSid","#text":"S-1-5-21-3962163828-2803415714-1403596700-1001"},{"@Name":"SubjectUserName","#text":"lplui"},{"@Name":"SubjectDomainName","#text":"SERVER002"},{"@Name":"SubjectLogonId","#text":"0x39737"},{"@Name":"TargetName","#text":"MicrosoftAccount:user=lpluigi44@gmail.com"},{"@Name":"Type","#text":"0"},{"@Name":"CountOfCredentialsReturned","#text":"1"},{"@Name":"ReadOperation","#text":"%%8100"},{"@Name":"ReturnCode","#text":"0"},{"@Name":"ProcessCreationTime","#text":"2025-05-02 14:41:30.3975537"},{"@Name":"ClientProcessId","#text":"7256"}]}}}
{"Event":{"System":{"Provider":{"@Name":"Microsoft-Windows-Security-Auditing","@Guid":"54849625-5478-4994-a5ba-3e3b0328c30d"},"EventID":"5379","Version":"0","Level":"0","Task":"13824","Opcode":"0","Keywords":"0x8020000000000000","TimeCreated":{"@SystemTime":"2025-05-02 14:43:24.8229501"},"EventRecordID":"92000","Correlation":{"@ActivityID":"1168e054-bb50-0000-2de1-681150bbdb01"},"Execution":{"@ProcessID":"688","@ThreadID":"5964"},"Channel":"Security","Computer":"Server002","Security":null},"EventData":{"Data":[{"@Name":"SubjectUserSid","#text":"S-1-5-21-3962163828-2803415714-1403596700-1001"},{"@Name":"SubjectUserName","#text":"lplui"},{"@Name":"SubjectDomainName","#text":"SERVER002"},{"@Name":"SubjectLogonId","#text":"0x39737"},{"@Name":"TargetName","#text":"MicrosoftAccount:user=lpluigi44@gmail.com"},{"@Name":"Type","#text":"0"},{"@Name":"CountOfCredentialsReturned","#text":"1"},{"@Name":"ReadOperation","#text":"%%8100"},{"@Name":"ReturnCode","#text":"0"},{"@Name":"ProcessCreationTime","#text":"2025-05-02 14:41:30.3975537"},{"@Name":"ClientProcessId","#text":"7256"}]}}}
{"Event":{"System":{"Provider":{"@Name":"Microsoft-Windows-Security-Auditing","@Guid":"54849625-5478-4994-a5ba-3e3b0328c30d"},"EventID":"5379","Version":"0","Level":"0","Task":"13824","Opcode":"0","Keywords":"0x8020000000000000","TimeCreated":{"@SystemTime":"2025-05-02 14:43:34.1507989"},"EventRecordID":"92001","Correlation":{"@ActivityID":"1168e054-bb50-0000-2de1-681150bbdb01"},"Execution":{"@ProcessID":"688","@ThreadID":"5964"},"Channel":"Security","Computer":"Server002","Security":null},"EventData":{"Data":[{"@Name":"SubjectUserSid","#text":"S-1-5-21-3962163828-2803415714-1403596700-1001"},{"@Name":"SubjectUserName","#text":"lplui"},{"@Name":"SubjectDomainName","#text":"SERVER002"},{"@Name":"SubjectLogonId","#text":"0x39737"},{"@Name":"TargetName","#text":"MicrosoftAccount:user=lpluigi44@gmail.com"},{"@Name":"Type","#text":"0"},{"@Name":"CountOfCredentialsReturned","#text":"1"},{"@Name":"ReadOperation","#text":"%%8100"},{"@Name":"ReturnCode","#text":"0"},{"@Name":"ProcessCreationTime","#text":"2025-05-02 14:41:30.3975537"},{"@Name":"ClientProcessId","#text":"7256"}]}}}
{"Event":{"System":{"Provider":{"@Name":"Microsoft-Windows-Security-Auditing","@Guid":"54849625-5478-4994-a5ba-3e3b0328c30d"},"EventID":"5379","Version":"0","Level":"0","Task":"13824","Opcode":"0","Keywords":"0x8020000000000000","TimeCreated":{"@SystemTime":"2025-05-02 14:43:34.1692248"},"EventRecordID":"92002","Correlation":{"@ActivityID":"1168e054-bb50-0000-2de1-681150bbdb01"},"Execution":{"@ProcessID":"688","@ThreadID":"5964"},"Channel":"Security","Computer":"Server002","Security":null},"EventData":{"Data":[{"@Name":"SubjectUserSid","#text":"S-1-5-21-3962163828-2803415714-1403596700-1001"},{"@Name":"SubjectUserName","#text":"lplui"},{"@Name":"SubjectDomainName","#text":"SERVER002"},{"@Name":"SubjectLogonId","#text":"0x39737"},{"@Name":"TargetName","#text":"WindowsLive:(token):name=lpluigi44@gmail.com;serviceuri=*"},{"@Name":"Type","#text":"0"},{"@Name":"CountOfCredentialsReturned","#text":"0"},{"@Name":"ReadOperation","#text":"%%8100"},{"@Name":"ReturnCode","#text":"3221226021"},{"@Name":"ProcessCreationTime","#text":"2025-05-02 14:41:30.3975537"},{"@Name":"ClientProcessId","#text":"7256"}]}}}
{"Event":{"System":{"Provider":{"@Name":"Microsoft-Windows-Security-Auditing","@Guid":"54849625-5478-4994-a5ba-3e3b0328c30d"},"EventID":"5379","Version":"0","Level":"0","Task":"13824","Opcode":"0","Keywords":"0x8020000000000000","TimeCreated":{"@SystemTime":"2025-05-02 14:43:34.1693235"},"EventRecordID":"92003","Correlation":{"@ActivityID":"1168e054-bb50-0000-2de1-681150bbdb01"},"Execution":{"@ProcessID":"688","@ThreadID":"5964"},"Channel":"Security","Computer":"Server002","Security":null},"EventData":{"Data":[{"@Name":"SubjectUserSid","#text":"S-1-5-21-3962163828-2803415714-1403596700-1001"},{"@Name":"SubjectUserName","#text":"lplui"},{"@Name":"SubjectDomainName","#text":"SERVER002"},{"@Name":"SubjectLogonId","#text":"0x39737"},{"@Name":"TargetName","#text":"WindowsLive:(cert):name=lpluigi44@gmail.com;serviceuri=*"},{"@Name":"Type","#text":"0"},{"@Name":"CountOfCredentialsReturned","#text":"0"},{"@Name":"ReadOperation","#text":"%%8100"},{"@Name":"ReturnCode","#text":"3221226021"},{"@Name":"ProcessCreationTime","#text":"2025-05-02 14:41:30.3975537"},{"@Name":"ClientProcessId","#text":"7256"}]}}}
{"Event":{"System":{"Provider":{"@Name":"Microsoft-Windows-Security-Auditing","@Guid":"54849625-5478-4994-a5ba-3e3b0328c30d"},"EventID":"5379","Version":"0","Level":"0","Task":"13824","Opcode":"0","Keywords":"0x8020000000000000","TimeCreated":{"@SystemTime":"2025-05-02 14:43:34.1793137"},"EventRecordID":"92004","Correlation":{"@ActivityID":"1168e054-bb50-0000-2de1-681150bbdb01"},"Execution":{"@ProcessID":"688","@ThreadID":"5964"},"Channel":"Security","Computer":"Server002","Security":null},"EventData":{"Data":[{"@Name":"SubjectUserSid","#text":"S-1-5-21-3962163828-2803415714-1403596700-1001"},{"@Name":"SubjectUserName","#text":"lplui"},{"@Name":"SubjectDomainName","#text":"SERVER002"},{"@Name":"SubjectLogonId","#text":"0x39737"},{"@Name":"TargetName","#text":"MicrosoftAccount:user=lpluigi44@gmail.com"},{"@Name":"Type","#text":"0"},{"@Name":"CountOfCredentialsReturned","#text":"1"},{"@Name":"ReadOperation","#text":"%%8100"},{"@Name":"ReturnCode","#text":"0"},{"@Name":"ProcessCreationTime","#text":"2025-05-02 14:41:30.3975537"},{"@Name":"ClientProcessId","#text":"7256"}]}}}
{"Event":{"System":{"Provider":{"@Name":"Microsoft-Windows-Security-Auditing","@Guid":"54849625-5478-4994-a5ba-3e3b0328c30d"},"EventID":"5379","Version":"0","Level":"0","Task":"13824","Opcode":"0","Keywords":"0x8020000000000000","TimeCreated":{"@SystemTime":"2025-05-02 14:43:34.1864548"},"EventRecordID":"92005","Correlation":{"@ActivityID":"1168e054-bb50-0000-2de1-681150bbdb01"},"Execution":{"@ProcessID":"688","@ThreadID":"5964"},"Channel":"Security","Computer":"Server002","Security":null},"EventData":{"Data":[{"@Name":"SubjectUserSid","#text":"S-1-5-21-3962163828-2803415714-1403596700-1001"},{"@Name":"SubjectUserName","#text":"lplui"},{"@Name":"SubjectDomainName","#text":"SERVER002"},{"@Name":"SubjectLogonId","#text":"0x39737"},{"@Name":"TargetName","#text":"MicrosoftAccount:user=lpluigi44@gmail.com"},{"@Name":"Type","#text":"0"},{"@Name":"CountOfCredentialsReturned","#text":"1"},{"@Name":"ReadOperation","#text":"%%8100"},{"@Name":"ReturnCode","#text":"0"},{"@Name":"ProcessCreationTime","#text":"2025-05-02 14:41:30.3975537"},{"@Name":"ClientProcessId","#text":"7256"}]}}}
{"Event":{"System":{"Provider":{"@Name":"Microsoft-Windows-Security-Auditing","@Guid":"54849625-5478-4994-a5ba-3e3b0328c30d"},"EventID":"5379","Version":"0","Level":"0","Task":"13824","Opcode":"0","Keywords":"0x8020000000000000","TimeCreated":{"@SystemTime":"2025-05-02 14:43:34.6543136"},"EventRecordID":"92006","Correlation":{"@ActivityID":"1168e054-bb50-0000-2de1-681150bbdb01"},"Execution":{"@ProcessID":"688","@ThreadID":"5964"},"Channel":"Security","Computer":"Server002","Security":null},"EventData":{"Data":[{"@Name":"SubjectUserSid","#text":"S-1-5-21-3962163828-2803415714-1403596700-1001"},{"@Name":"SubjectUserName","#text":"lplui"},{"@Name":"SubjectDomainName","#text":"SERVER002"},{"@Name":"SubjectLogonId","#text":"0x39737"},{"@Name":"TargetName","#text":"MicrosoftAccount:user=lpluigi44@gmail.com"},{"@Name":"Type","#text":"0"},{"@Name":"CountOfCredentialsReturned","#text":"1"},{"@Name":"ReadOperation","#text":"%%8100"},{"@Name":"ReturnCode","#text":"0"},{"@Name":"ProcessCreationTime","#text":"2025-05-02 14:41:30.3975537"},{"@Name":"ClientProcessId","#text":"7256"}]}}}
{"Event":{"System":{"Provider":{"@Name":"Microsoft-Windows-Security-Auditing","@Guid":"54849625-5478-4994-a5ba-3e3b0328c30d"},"EventID":"5379","Version":"0","Level":"0","Task":"13824","Opcode":"0","Keywords":"0x8020000000000000","TimeCreated":{"@SystemTime":"2025-05-02 14:43:34.6546685"},"EventRecordID":"92007","Correlation":{"@ActivityID":"1168e054-bb50-0000-2de1-681150bbdb01"},"Execution":{"@ProcessID":"688","@ThreadID":"5964"},"Channel":"Security","Computer":"Server002","Security":null},"EventData":{"Data":[{"@Name":"SubjectUserSid","#text":"S-1-5-21-3962163828-2803415714-1403596700-1001"},{"@Name":"SubjectUserName","#text":"lplui"},{"@Name":"SubjectDomainName","#text":"SERVER002"},{"@Name":"SubjectLogonId","#text":"0x39737"},{"@Name":"TargetName","#text":"MicrosoftAccount:user=lpluigi44@gmail.com"},{"@Name":"Type","#text":"0"},{"@Name":"CountOfCredentialsReturned","#text":"1"},{"@Name":"ReadOperation","#text":"%%8100"},{"@Name":"ReturnCode","#text":"0"},{"@Name":"ProcessCreationTime","#text":"2025-05-02 14:41:30.3975537"},{"@Name":"ClientProcessId","#text":"7256"}]}}}
{"Event":{"System":{"Provider":{"@Name":"Microsoft-Windows-Security-Auditing","@Guid":"54849625-5478-4994-a5ba-3e3b0328c30d"},"EventID":"5379","Version":"0","Level":"0","Task":"13824","Opcode":"0","Keywords":"0x8020000000000000","TimeCreated":{"@SystemTime":"2025-05-02 14:43:34.6549871"},"EventRecordID":"92008","Correlation":{"@ActivityID":"1168e054-bb50-0000-2de1-681150bbdb01"},"Execution":{"@ProcessID":"688","@ThreadID":"5964"},"Channel":"Security","Computer":"Server002","Security":null},"EventData":{"Data":[{"@Name":"SubjectUserSid","#text":"S-1-5-21-3962163828-2803415714-1403596700-1001"},{"@Name":"SubjectUserName","#text":"lplui"},{"@Name":"SubjectDomainName","#text":"SERVER002"},{"@Name":"SubjectLogonId","#text":"0x39737"},{"@Name":"TargetName","#text":"MicrosoftAccount:user=lpluigi44@gmail.com"},{"@Name":"Type","#text":"0"},{"@Name":"CountOfCredentialsReturned","#text":"1"},{"@Name":"ReadOperation","#text":"%%8100"},{"@Name":"ReturnCode","#text":"0"},{"@Name":"ProcessCreationTime","#text":"2025-05-02 14:41:30.3975537"},{"@Name":"ClientProcessId","#text":"7256"}]}}}
{"Event":{"System":{"Provider":{"@Name":"Microsoft-Windows-Security-Auditing","@Guid":"54849625-5478-4994-a5ba-3e3b0328c30d"},"EventID":"5379","Version":"0","Level":"0","Task":"13824","Opcode":"0","Keywords":"0x8020000000000000","TimeCreated":{"@SystemTime":"2025-05-02 14:43:34.6551939"},"EventRecordID":"92009","Correlation":{"@ActivityID":"1168e054-bb50-0000-2de1-681150bbdb01"},"Execution":{"@ProcessID":"688","@ThreadID":"5964"},"Channel":"Security","Computer":"Server002","Security":null},"EventData":{"Data":[{"@Name":"SubjectUserSid","#text":"S-1-5-21-3962163828-2803415714-1403596700-1001"},{"@Name":"SubjectUserName","#text":"lplui"},{"@Name":"SubjectDomainName","#text":"SERVER002"},{"@Name":"SubjectLogonId","#text":"0x39737"},{"@Name":"TargetName","#text":"MicrosoftAccount:user=lpluigi44@gmail.com"},{"@Name":"Type","#text":"0"},{"@Name":"CountOfCredentialsReturned","#text":"1"},{"@Name":"ReadOperation","#text":"%%8100"},{"@Name":"ReturnCode","#text":"0"},{"@Name":"ProcessCreationTime","#text":"2025-05-02 14:41:30.3975537"},{"@Name":"ClientProcessId","#text":"7256"}]}}}
{"Event":{"System":{"Provider":{"@Name":"Microsoft-Windows-Security-Auditing","@Guid":"54849625-5478-4994-a5ba-3e3b0328c30d"},"EventID":"5379","Version":"0","Level":"0","Task":"13824","Opcode":"0","Keywords":"0x8020000000000000","TimeCreated":{"@SystemTime":"2025-05-02 14:43:34.6555308"},"EventRecordID":"92010","Correlation":{"@ActivityID":"1168e054-bb50-0000-2de1-681150bbdb01"},"Execution":{"@ProcessID":"688","@ThreadID":"5964"},"Channel":"Security","Computer":"Server002","Security":null},"EventData":{"Data":[{"@Name":"SubjectUserSid","#text":"S-1-5-21-3962163828-2803415714-1403596700-1001"},{"@Name":"SubjectUserName","#text":"lplui"},{"@Name":"SubjectDomainName","#text":"SERVER002"},{"@Name":"SubjectLogonId","#text":"0x39737"},{"@Name":"TargetName","#text":"MicrosoftAccount:user=lpluigi44@gmail.com"},{"@Name":"Type","#text":"0"},{"@Name":"CountOfCredentialsReturned","#text":"1"},{"@Name":"ReadOperation","#text":"%%8100"},{"@Name":"ReturnCode","#text":"0"},{"@Name":"ProcessCreationTime","#text":"2025-05-02 14:41:30.3975537"},{"@Name":"ClientProcessId","#text":"7256"}]}}}
{"Event":{"System":{"Provider":{"@Name":"Microsoft-Windows-Security-Auditing","@Guid":"54849625-5478-4994-a5ba-3e3b0328c30d"},"EventID":"5379","Version":"0","Level":"0","Task":"13824","Opcode":"0","Keywords":"0x8020000000000000","TimeCreated":{"@SystemTime":"2025-05-02 14:43:34.6557806"},"EventRecordID":"92011","Correlation":{"@ActivityID":"1168e054-bb50-0000-2de1-681150bbdb01"},"Execution":{"@ProcessID":"688","@ThreadID":"5964"},"Channel":"Security","Computer":"Server002","Security":null},"EventData":{"Data":[{"@Name":"SubjectUserSid","#text":"S-1-5-21-3962163828-2803415714-1403596700-1001"},{"@Name":"SubjectUserName","#text":"lplui"},{"@Name":"SubjectDomainName","#text":"SERVER002"},{"@Name":"SubjectLogonId","#text":"0x39737"},{"@Name":"TargetName","#text":"MicrosoftAccount:user=lpluigi44@gmail.com"},{"@Name":"Type","#text":"0"},{"@Name":"CountOfCredentialsReturned","#text":"1"},{"@Name":"ReadOperation","#text":"%%8100"},{"@Name":"ReturnCode","#text":"0"},{"@Name":"ProcessCreationTime","#text":"2025-05-02 14:41:30.3975537"},{"@Name":"ClientProcessId","#text":"7256"}]}}}
{"Event":{"System":{"Provider":{"@Name":"Microsoft-Windows-Security-Auditing","@Guid":"54849625-5478-4994-a5ba-3e3b0328c30d"},"EventID":"5379","Version":"0","Level":"0","Task":"13824","Opcode":"0","Keywords":"0x8020000000000000","TimeCreated":{"@SystemTime":"2025-05-02 14:43:34.6561521"},"EventRecordID":"92012","Correlation":{"@ActivityID":"1168e054-bb50-0000-2de1-681150bbdb01"},"Execution":{"@ProcessID":"688","@ThreadID":"5964"},"Channel":"Security","Computer":"Server002","Security":null},"EventData":{"Data":[{"@Name":"SubjectUserSid","#text":"S-1-5-21-3962163828-2803415714-1403596700-1001"},{"@Name":"SubjectUserName","#text":"lplui"},{"@Name":"SubjectDomainName","#text":"SERVER002"},{"@Name":"SubjectLogonId","#text":"0x39737"},{"@Name":"TargetName","#text":"MicrosoftAccount:user=lpluigi44@gmail.com"},{"@Name":"Type","#text":"0"},{"@Name":"CountOfCredentialsReturned","#text":"1"},{"@Name":"ReadOperation","#text":"%%8100"},{"@Name":"ReturnCode","#text":"0"},{"@Name":"ProcessCreationTime","#text":"2025-05-02 14:41:30.3975537"},{"@Name":"ClientProcessId","#text":"7256"}]}}}
{"Event":{"System":{"Provider":{"@Name":"Microsoft-Windows-Security-Auditing","@Guid":"54849625-5478-4994-a5ba-3e3b0328c30d"},"EventID":"5379","Version":"0","Level":"0","Task":"13824","Opcode":"0","Keywords":"0x8020000000000000","TimeCreated":{"@SystemTime":"2025-05-02 14:43:34.6563425"},"EventRecordID":"92013","Correlation":{"@ActivityID":"1168e054-bb50-0000-2de1-681150bbdb01"},"Execution":{"@ProcessID":"688","@ThreadID":"5964"},"Channel":"Security","Computer":"Server002","Security":null},"EventData":{"Data":[{"@Name":"SubjectUserSid","#text":"S-1-5-21-3962163828-2803415714-1403596700-1001"},{"@Name":"SubjectUserName","#text":"lplui"},{"@Name":"SubjectDomainName","#text":"SERVER002"},{"@Name":"SubjectLogonId","#text":"0x39737"},{"@Name":"TargetName","#text":"MicrosoftAccount:user=lpluigi44@gmail.com"},{"@Name":"Type","#text":"0"},{"@Name":"CountOfCredentialsReturned","#text":"1"},{"@Name":"ReadOperation","#text":"%%8100"},{"@Name":"ReturnCode","#text":"0"},{"@Name":"ProcessCreationTime","#text":"2025-05-02 14:41:30.3975537"},{"@Name":"ClientProcessId","#text":"7256"}]}}}
{"Event":{"System":{"Provider":{"@Name":"Microsoft-Windows-Security-Auditing","@Guid":"54849625-5478-4994-a5ba-3e3b0328c30d"},"EventID":"5379","Version":"0","Level":"0","Task":"13824","Opcode":"0","Keywords":"0x8020000000000000","TimeCreated":{"@SystemTime":"2025-05-02 14:43:34.6566321"},"EventRecordID":"92014","Correlation":{"@ActivityID":"1168e054-bb50-0000-2de1-681150bbdb01"},"Execution":{"@ProcessID":"688","@ThreadID":"5964"},"Channel":"Security","Computer":"Server002","Security":null},"EventData":{"Data":[{"@Name":"SubjectUserSid","#text":"S-1-5-21-3962163828-2803415714-1403596700-1001"},{"@Name":"SubjectUserName","#text":"lplui"},{"@Name":"SubjectDomainName","#text":"SERVER002"},{"@Name":"SubjectLogonId","#text":"0x39737"},{"@Name":"TargetName","#text":"MicrosoftAccount:user=lpluigi44@gmail.com"},{"@Name":"Type","#text":"0"},{"@Name":"CountOfCredentialsReturned","#text":"1"},{"@Name":"ReadOperation","#text":"%%8100"},{"@Name":"ReturnCode","#text":"0"},{"@Name":"ProcessCreationTime","#text":"2025-05-02 14:41:30.3975537"},{"@Name":"ClientProcessId","#text":"7256"}]}}}
{"Event":{"System":{"Provider":{"@Name":"Microsoft-Windows-Security-Auditing","@Guid":"54849625-5478-4994-a5ba-3e3b0328c30d"},"EventID":"5379","Version":"0","Level":"0","Task":"13824","Opcode":"0","Keywords":"0x8020000000000000","TimeCreated":{"@SystemTime":"2025-05-02 14:43:34.6568843"},"EventRecordID":"92015","Correlation":{"@ActivityID":"1168e054-bb50-0000-2de1-681150bbdb01"},"Execution":{"@ProcessID":"688","@ThreadID":"5964"},"Channel":"Security","Computer":"Server002","Security":null},"EventData":{"Data":[{"@Name":"SubjectUserSid","#text":"S-1-5-21-3962163828-2803415714-1403596700-1001"},{"@Name":"SubjectUserName","#text":"lplui"},{"@Name":"SubjectDomainName","#text":"SERVER002"},{"@Name":"SubjectLogonId","#text":"0x39737"},{"@Name":"TargetName","#text":"MicrosoftAccount:user=lpluigi44@gmail.com"},{"@Name":"Type","#text":"0"},{"@Name":"CountOfCredentialsReturned","#text":"1"},{"@Name":"ReadOperation","#text":"%%8100"},{"@Name":"ReturnCode","#text":"0"},{"@Name":"ProcessCreationTime","#text":"2025-05-02 14:41:30.3975537"},{"@Name":"ClientProcessId","#text":"7256"}]}}}
{"Event":{"System":{"Provider":{"@Name":"Microsoft-Windows-Security-Auditing","@Guid":"54849625-5478-4994-a5ba-3e3b0328c30d"},"EventID":"5379","Version":"0","Level":"0","Task":"13824","Opcode":"0","Keywords":"0x8020000000000000","TimeCreated":{"@SystemTime":"2025-05-02 14:43:34.6572020"},"EventRecordID":"92016","Correlation":{"@ActivityID":"1168e054-bb50-0000-2de1-681150bbdb01"},"Execution":{"@ProcessID":"688","@ThreadID":"5964"},"Channel":"Security","Computer":"Server002","Security":null},"EventData":{"Data":[{"@Name":"SubjectUserSid","#text":"S-1-5-21-3962163828-2803415714-1403596700-1001"},{"@Name":"SubjectUserName","#text":"lplui"},{"@Name":"SubjectDomainName","#text":"SERVER002"},{"@Name":"SubjectLogonId","#text":"0x39737"},{"@Name":"TargetName","#text":"MicrosoftAccount:user=lpluigi44@gmail.com"},{"@Name":"Type","#text":"0"},{"@Name":"CountOfCredentialsReturned","#text":"1"},{"@Name":"ReadOperation","#text":"%%8100"},{"@Name":"ReturnCode","#text":"0"},{"@Name":"ProcessCreationTime","#text":"2025-05-02 14:41:30.3975537"},{"@Name":"ClientProcessId","#text":"7256"}]}}}
{"Event":{"System":{"Provider":{"@Name":"Microsoft-Windows-Security-Auditing","@Guid":"54849625-5478-4994-a5ba-3e3b0328c30d"},"EventID":"5379","Version":"0","Level":"0","Task":"13824","Opcode":"0","Keywords":"0x8020000000000000","TimeCreated":{"@SystemTime":"2025-05-02 14:43:34.6574838"},"EventRecordID":"92017","Correlation":{"@ActivityID":"1168e054-bb50-0000-2de1-681150bbdb01"},"Execution":{"@ProcessID":"688","@ThreadID":"5964"},"Channel":"Security","Computer":"Server002","Security":null},"EventData":{"Data":[{"@Name":"SubjectUserSid","#text":"S-1-5-21-3962163828-2803415714-1403596700-1001"},{"@Name":"SubjectUserName","#text":"lplui"},{"@Name":"SubjectDomainName","#text":"SERVER002"},{"@Name":"SubjectLogonId","#text":"0x39737"},{"@Name":"TargetName","#text":"MicrosoftAccount:user=lpluigi44@gmail.com"},{"@Name":"Type","#text":"0"},{"@Name":"CountOfCredentialsReturned","#text":"1"},{"@Name":"ReadOperation","#text":"%%8100"},{"@Name":"ReturnCode","#text":"0"},{"@Name":"ProcessCreationTime","#text":"2025-05-02 14:41:30.3975537"},{"@Name":"ClientProcessId","#text":"7256"}]}}}
{"Event":{"System":{"Provider":{"@Name":"Microsoft-Windows-Security-Auditing","@Guid":"54849625-5478-4994-a5ba-3e3b0328c30d"},"EventID":"5379","Version":"0","Level":"0","Task":"13824","Opcode":"0","Keywords":"0x8020000000000000","TimeCreated":{"@SystemTime":"2025-05-02 14:43:34.6578120"},"EventRecordID":"92018","Correlation":{"@ActivityID":"1168e054-bb50-0000-2de1-681150bbdb01"},"Execution":{"@ProcessID":"688","@ThreadID":"5964"},"Channel":"Security","Computer":"Server002","Security":null},"EventData":{"Data":[{"@Name":"SubjectUserSid","#text":"S-1-5-21-3962163828-2803415714-1403596700-1001"},{"@Name":"SubjectUserName","#text":"lplui"},{"@Name":"SubjectDomainName","#text":"SERVER002"},{"@Name":"SubjectLogonId","#text":"0x39737"},{"@Name":"TargetName","#text":"MicrosoftAccount:user=lpluigi44@gmail.com"},{"@Name":"Type","#text":"0"},{"@Name":"CountOfCredentialsReturned","#text":"1"},{"@Name":"ReadOperation","#text":"%%8100"},{"@Name":"ReturnCode","#text":"0"},{"@Name":"ProcessCreationTime","#text":"2025-05-02 14:41:30.3975537"},{"@Name":"ClientProcessId","#text":"7256"}]}}}
{"Event":{"System":{"Provider":{"@Name":"Microsoft-Windows-Security-Auditing","@Guid":"54849625-5478-4994-a5ba-3e3b0328c30d"},"EventID":"5379","Version":"0","Level":"0","Task":"13824","Opcode":"0","Keywords":"0x8020000000000000","TimeCreated":{"@SystemTime":"2025-05-02 14:43:34.6580501"},"EventRecordID":"92019","Correlation":{"@ActivityID":"1168e054-bb50-0000-2de1-681150bbdb01"},"Execution":{"@ProcessID":"688","@ThreadID":"5964"},"Channel":"Security","Computer":"Server002","Security":null},"EventData":{"Data":[{"@Name":"SubjectUserSid","#text":"S-1-5-21-3962163828-2803415714-1403596700-1001"},{"@Name":"SubjectUserName","#text":"lplui"},{"@Name":"SubjectDomainName","#text":"SERVER002"},{"@Name":"SubjectLogonId","#text":"0x39737"},{"@Name":"TargetName","#text":"MicrosoftAccount:user=lpluigi44@gmail.com"},{"@Name":"Type","#text":"0"},{"@Name":"CountOfCredentialsReturned","#text":"1"},{"@Name":"ReadOperation","#text":"%%8100"},{"@Name":"ReturnCode","#text":"0"},{"@Name":"ProcessCreationTime","#text":"2025-05-02 14:41:30.3975537"},{"@Name":"ClientProcessId","#text":"7256"}]}}}
{"Event":{"System":{"Provider":{"@Name":"Microsoft-Windows-Security-Auditing","@Guid":"54849625-5478-4994-a5ba-3e3b0328c30d"},"EventID":"5379","Version":"0","Level":"0","Task":"13824","Opcode":"0","Keywords":"0x8020000000000000","TimeCreated":{"@SystemTime":"2025-05-02 14:43:34.6583439"},"EventRecordID":"92020","Correlation":{"@ActivityID":"1168e054-bb50-0000-2de1-681150bbdb01"},"Execution":{"@ProcessID":"688","@ThreadID":"5964"},"Channel":"Security","Computer":"Server002","Security":null},"EventData":{"Data":[{"@Name":"SubjectUserSid","#text":"S-1-5-21-3962163828-2803415714-1403596700-1001"},{"@Name":"SubjectUserName","#text":"lplui"},{"@Name":"SubjectDomainName","#text":"SERVER002"},{"@Name":"SubjectLogonId","#text":"0x39737"},{"@Name":"TargetName","#text":"MicrosoftAccount:user=lpluigi44@gmail.com"},{"@Name":"Type","#text":"0"},{"@Name":"CountOfCredentialsReturned","#text":"1"},{"@Name":"ReadOperation","#text":"%%8100"},{"@Name":"ReturnCode","#text":"0"},{"@Name":"ProcessCreationTime","#text":"2025-05-02 14:41:30.3975537"},{"@Name":"ClientProcessId","#text":"7256"}]}}}
{"Event":{"System":{"Provider":{"@Name":"Microsoft-Windows-Security-Auditing","@Guid":"54849625-5478-4994-a5ba-3e3b0328c30d"},"EventID":"5379","Version":"0","Level":"0","Task":"13824","Opcode":"0","Keywords":"0x8020000000000000","TimeCreated":{"@SystemTime":"2025-05-02 14:43:34.6590495"},"EventRecordID":"92021","Correlation":{"@ActivityID":"1168e054-bb50-0000-2de1-681150bbdb01"},"Execution":{"@ProcessID":"688","@ThreadID":"5964"},"Channel":"Security","Computer":"Server002","Security":null},"EventData":{"Data":[{"@Name":"SubjectUserSid","#text":"S-1-5-21-3962163828-2803415714-1403596700-1001"},{"@Name":"SubjectUserName","#text":"lplui"},{"@Name":"SubjectDomainName","#text":"SERVER002"},{"@Name":"SubjectLogonId","#text":"0x39737"},{"@Name":"TargetName","#text":"MicrosoftAccount:user=lpluigi44@gmail.com"},{"@Name":"Type","#text":"1"},{"@Name":"CountOfCredentialsReturned","#text":"1"},{"@Name":"ReadOperation","#text":"%%8099"},{"@Name":"ReturnCode","#text":"0"},{"@Name":"ProcessCreationTime","#text":"2025-05-02 14:41:30.3975537"},{"@Name":"ClientProcessId","#text":"7256"}]}}}
{"Event":{"System":{"Provider":{"@Name":"Microsoft-Windows-Security-Auditing","@Guid":"54849625-5478-4994-a5ba-3e3b0328c30d"},"EventID":"5379","Version":"0","Level":"0","Task":"13824","Opcode":"0","Keywords":"0x8020000000000000","TimeCreated":{"@SystemTime":"2025-05-02 14:43:34.6880466"},"EventRecordID":"92022","Correlation":{"@ActivityID":"1168e054-bb50-0000-2de1-681150bbdb01"},"Execution":{"@ProcessID":"688","@ThreadID":"5964"},"Channel":"Security","Computer":"Server002","Security":null},"EventData":{"Data":[{"@Name":"SubjectUserSid","#text":"S-1-5-21-3962163828-2803415714-1403596700-1001"},{"@Name":"SubjectUserName","#text":"lplui"},{"@Name":"SubjectDomainName","#text":"SERVER002"},{"@Name":"SubjectLogonId","#text":"0x39737"},{"@Name":"TargetName","#text":"MicrosoftAccount:user=lpluigi44@gmail.com"},{"@Name":"Type","#text":"0"},{"@Name":"CountOfCredentialsReturned","#text":"1"},{"@Name":"ReadOperation","#text":"%%8100"},{"@Name":"ReturnCode","#text":"0"},{"@Name":"ProcessCreationTime","#text":"2025-05-02 14:41:30.3975537"},{"@Name":"ClientProcessId","#text":"7256"}]}}}
{"Event":{"System":{"Provider":{"@Name":"Microsoft-Windows-Security-Auditing","@Guid":"54849625-5478-4994-a5ba-3e3b0328c30d"},"EventID":"5379","Version":"0","Level":"0","Task":"13824","Opcode":"0","Keywords":"0x8020000000000000","TimeCreated":{"@SystemTime":"2025-05-02 14:43:34.6884456"},"EventRecordID":"92023","Correlation":{"@ActivityID":"1168e054-bb50-0000-2de1-681150bbdb01"},"Execution":{"@ProcessID":"688","@ThreadID":"5964"},"Channel":"Security","Computer":"Server002","Security":null},"EventData":{"Data":[{"@Name":"SubjectUserSid","#text":"S-1-5-21-3962163828-2803415714-1403596700-1001"},{"@Name":"SubjectUserName","#text":"lplui"},{"@Name":"SubjectDomainName","#text":"SERVER002"},{"@Name":"SubjectLogonId","#text":"0x39737"},{"@Name":"TargetName","#text":"MicrosoftAccount:user=lpluigi44@gmail.com"},{"@Name":"Type","#text":"0"},{"@Name":"CountOfCredentialsReturned","#text":"1"},{"@Name":"ReadOperation","#text":"%%8100"},{"@Name":"ReturnCode","#text":"0"},{"@Name":"ProcessCreationTime","#text":"2025-05-02 14:41:30.3975537"},{"@Name":"ClientProcessId","#text":"7256"}]}}}
{"Event":{"System":{"Provider":{"@Name":"Microsoft-Windows-Security-Auditing","@Guid":"54849625-5478-4994-a5ba-3e3b0328c30d"},"EventID":"5379","Version":"0","Level":"0","Task":"13824","Opcode":"0","Keywords":"0x8020000000000000","TimeCreated":{"@SystemTime":"2025-05-02 14:43:34.6887269"},"EventRecordID":"92024","Correlation":{"@ActivityID":"1168e054-bb50-0000-2de1-681150bbdb01"},"Execution":{"@ProcessID":"688","@ThreadID":"5964"},"Channel":"Security","Computer":"Server002","Security":null},"EventData":{"Data":[{"@Name":"SubjectUserSid","#text":"S-1-5-21-3962163828-2803415714-1403596700-1001"},{"@Name":"SubjectUserName","#text":"lplui"},{"@Name":"SubjectDomainName","#text":"SERVER002"},{"@Name":"SubjectLogonId","#text":"0x39737"},{"@Name":"TargetName","#text":"MicrosoftAccount:user=lpluigi44@gmail.com"},{"@Name":"Type","#text":"0"},{"@Name":"CountOfCredentialsReturned","#text":"1"},{"@Name":"ReadOperation","#text":"%%8100"},{"@Name":"ReturnCode","#text":"0"},{"@Name":"ProcessCreationTime","#text":"2025-05-02 14:41:30.3975537"},{"@Name":"ClientProcessId","#text":"7256"}]}}}
{"Event":{"System":{"Provider":{"@Name":"Microsoft-Windows-Security-Auditing","@Guid":"54849625-5478-4994-a5ba-3e3b0328c30d"},"EventID":"5379","Version":"0","Level":"0","Task":"13824","Opcode":"0","Keywords":"0x8020000000000000","TimeCreated":{"@SystemTime":"2025-05-02 14:43:34.6889054"},"EventRecordID":"92025","Correlation":{"@ActivityID":"1168e054-bb50-0000-2de1-681150bbdb01"},"Execution":{"@ProcessID":"688","@ThreadID":"5964"},"Channel":"Security","Computer":"Server002","Security":null},"EventData":{"Data":[{"@Name":"SubjectUserSid","#text":"S-1-5-21-3962163828-2803415714-1403596700-1001"},{"@Name":"SubjectUserName","#text":"lplui"},{"@Name":"SubjectDomainName","#text":"SERVER002"},{"@Name":"SubjectLogonId","#text":"0x39737"},{"@Name":"TargetName","#text":"MicrosoftAccount:user=lpluigi44@gmail.com"},{"@Name":"Type","#text":"0"},{"@Name":"CountOfCredentialsReturned","#text":"1"},{"@Name":"ReadOperation","#text":"%%8100"},{"@Name":"ReturnCode","#text":"0"},{"@Name":"ProcessCreationTime","#text":"2025-05-02 14:41:30.3975537"},{"@Name":"ClientProcessId","#text":"7256"}]}}}
{"Event":{"System":{"Provider":{"@Name":"Microsoft-Windows-Security-Auditing","@Guid":"54849625-5478-4994-a5ba-3e3b0328c30d"},"EventID":"5379","Version":"0","Level":"0","Task":"13824","Opcode":"0","Keywords":"0x8020000000000000","TimeCreated":{"@SystemTime":"2025-05-02 14:43:34.6942975"},"EventRecordID":"92026","Correlation":{"@ActivityID":"1168e054-bb50-0000-2de1-681150bbdb01"},"Execution":{"@ProcessID":"688","@ThreadID":"5964"},"Channel":"Security","Computer":"Server002","Security":null},"EventData":{"Data":[{"@Name":"SubjectUserSid","#text":"S-1-5-21-3962163828-2803415714-1403596700-1001"},{"@Name":"SubjectUserName","#text":"lplui"},{"@Name":"SubjectDomainName","#text":"SERVER002"},{"@Name":"SubjectLogonId","#text":"0x39737"},{"@Name":"TargetName","#text":"MicrosoftAccount:user=lpluigi44@gmail.com"},{"@Name":"Type","#text":"0"},{"@Name":"CountOfCredentialsReturned","#text":"1"},{"@Name":"ReadOperation","#text":"%%8100"},{"@Name":"ReturnCode","#text":"0"},{"@Name":"ProcessCreationTime","#text":"2025-05-02 14:41:30.3975537"},{"@Name":"ClientProcessId","#text":"7256"}]}}}
{"Event":{"System":{"Provider":{"@Name":"Microsoft-Windows-Security-Auditing","@Guid":"54849625-5478-4994-a5ba-3e3b0328c30d"},"EventID":"5379","Version":"0","Level":"0","Task":"13824","Opcode":"0","Keywords":"0x8020000000000000","TimeCreated":{"@SystemTime":"2025-05-02 14:43:34.7055516"},"EventRecordID":"92027","Correlation":{"@ActivityID":"1168e054-bb50-0000-2de1-681150bbdb01"},"Execution":{"@ProcessID":"688","@ThreadID":"5964"},"Channel":"Security","Computer":"Server002","Security":null},"EventData":{"Data":[{"@Name":"SubjectUserSid","#text":"S-1-5-21-3962163828-2803415714-1403596700-1001"},{"@Name":"SubjectUserName","#text":"lplui"},{"@Name":"SubjectDomainName","#text":"SERVER002"},{"@Name":"SubjectLogonId","#text":"0x39737"},{"@Name":"TargetName","#text":"MicrosoftAccount:user=lpluigi44@gmail.com"},{"@Name":"Type","#text":"0"},{"@Name":"CountOfCredentialsReturned","#text":"1"},{"@Name":"ReadOperation","#text":"%%8100"},{"@Name":"ReturnCode","#text":"0"},{"@Name":"ProcessCreationTime","#text":"2025-05-02 14:41:30.3975537"},{"@Name":"ClientProcessId","#text":"7256"}]}}}
{"Event":{"System":{"Provider":{"@Name":"Microsoft-Windows-Security-Auditing","@Guid":"54849625-5478-4994-a5ba-3e3b0328c30d"},"EventID":"5379","Version":"0","Level":"0","Task":"13824","Opcode":"0","Keywords":"0x8020000000000000","TimeCreated":{"@SystemTime":"2025-05-02 14:43:34.7063578"},"EventRecordID":"92028","Correlation":{"@ActivityID":"1168e054-bb50-0000-2de1-681150bbdb01"},"Execution":{"@ProcessID":"688","@ThreadID":"5964"},"Channel":"Security","Computer":"Server002","Security":null},"EventData":{"Data":[{"@Name":"SubjectUserSid","#text":"S-1-5-21-3962163828-2803415714-1403596700-1001"},{"@Name":"SubjectUserName","#text":"lplui"},{"@Name":"SubjectDomainName","#text":"SERVER002"},{"@Name":"SubjectLogonId","#text":"0x39737"},{"@Name":"TargetName","#text":"MicrosoftAccount:user=lpluigi44@gmail.com"},{"@Name":"Type","#text":"0"},{"@Name":"CountOfCredentialsReturned","#text":"1"},{"@Name":"ReadOperation","#text":"%%8100"},{"@Name":"ReturnCode","#text":"0"},{"@Name":"ProcessCreationTime","#text":"2025-05-02 14:41:30.3975537"},{"@Name":"ClientProcessId","#text":"7256"}]}}}
{"Event":{"System":{"Provider":{"@Name":"Microsoft-Windows-Security-Auditing","@Guid":"54849625-5478-4994-a5ba-3e3b0328c30d"},"EventID":"5379","Version":"0","Level":"0","Task":"13824","Opcode":"0","Keywords":"0x8020000000000000","TimeCreated":{"@SystemTime":"2025-05-02 14:43:34.7066778"},"EventRecordID":"92029","Correlation":{"@ActivityID":"1168e054-bb50-0000-2de1-681150bbdb01"},"Execution":{"@ProcessID":"688","@ThreadID":"5964"},"Channel":"Security","Computer":"Server002","Security":null},"EventData":{"Data":[{"@Name":"SubjectUserSid","#text":"S-1-5-21-3962163828-2803415714-1403596700-1001"},{"@Name":"SubjectUserName","#text":"lplui"},{"@Name":"SubjectDomainName","#text":"SERVER002"},{"@Name":"SubjectLogonId","#text":"0x39737"},{"@Name":"TargetName","#text":"MicrosoftAccount:user=lpluigi44@gmail.com"},{"@Name":"Type","#text":"0"},{"@Name":"CountOfCredentialsReturned","#text":"1"},{"@Name":"ReadOperation","#text":"%%8100"},{"@Name":"ReturnCode","#text":"0"},{"@Name":"ProcessCreationTime","#text":"2025-05-02 14:41:30.3975537"},{"@Name":"ClientProcessId","#text":"7256"}]}}}
{"Event":{"System":{"Provider":{"@Name":"Microsoft-Windows-Security-Auditing","@Guid":"54849625-5478-4994-a5ba-3e3b0328c30d"},"EventID":"5379","Version":"0","Level":"0","Task":"13824","Opcode":"0","Keywords":"0x8020000000000000","TimeCreated":{"@SystemTime":"2025-05-02 14:43:34.7117830"},"EventRecordID":"92030","Correlation":{"@ActivityID":"1168e054-bb50-0000-2de1-681150bbdb01"},"Execution":{"@ProcessID":"688","@ThreadID":"5964"},"Channel":"Security","Computer":"Server002","Security":null},"EventData":{"Data":[{"@Name":"SubjectUserSid","#text":"S-1-5-21-3962163828-2803415714-1403596700-1001"},{"@Name":"SubjectUserName","#text":"lplui"},{"@Name":"SubjectDomainName","#text":"SERVER002"},{"@Name":"SubjectLogonId","#text":"0x39737"},{"@Name":"TargetName","#text":"MicrosoftAccount:user=lpluigi44@gmail.com"},{"@Name":"Type","#text":"0"},{"@Name":"CountOfCredentialsReturned","#text":"1"},{"@Name":"ReadOperation","#text":"%%8100"},{"@Name":"ReturnCode","#text":"0"},{"@Name":"ProcessCreationTime","#text":"2025-05-02 14:41:30.3975537"},{"@Name":"ClientProcessId","#text":"7256"}]}}}
{"Event":{"System":{"Provider":{"@Name":"Microsoft-Windows-Security-Auditing","@Guid":"54849625-5478-4994-a5ba-3e3b0328c30d"},"EventID":"5379","Version":"0","Level":"0","Task":"13824","Opcode":"0","Keywords":"0x8020000000000000","TimeCreated":{"@SystemTime":"2025-05-02 14:43:34.7120173"},"EventRecordID":"92031","Correlation":{"@ActivityID":"1168e054-bb50-0000-2de1-681150bbdb01"},"Execution":{"@ProcessID":"688","@ThreadID":"5964"},"Channel":"Security","Computer":"Server002","Security":null},"EventData":{"Data":[{"@Name":"SubjectUserSid","#text":"S-1-5-21-3962163828-2803415714-1403596700-1001"},{"@Name":"SubjectUserName","#text":"lplui"},{"@Name":"SubjectDomainName","#text":"SERVER002"},{"@Name":"SubjectLogonId","#text":"0x39737"},{"@Name":"TargetName","#text":"MicrosoftAccount:user=lpluigi44@gmail.com"},{"@Name":"Type","#text":"0"},{"@Name":"CountOfCredentialsReturned","#text":"1"},{"@Name":"ReadOperation","#text":"%%8100"},{"@Name":"ReturnCode","#text":"0"},{"@Name":"ProcessCreationTime","#text":"2025-05-02 14:41:30.3975537"},{"@Name":"ClientProcessId","#text":"7256"}]}}}
{"Event":{"System":{"Provider":{"@Name":"Microsoft-Windows-Security-Auditing","@Guid":"54849625-5478-4994-a5ba-3e3b0328c30d"},"EventID":"5379","Version":"0","Level":"0","Task":"13824","Opcode":"0","Keywords":"0x8020000000000000","TimeCreated":{"@SystemTime":"2025-05-02 14:43:34.7129041"},"EventRecordID":"92032","Correlation":{"@ActivityID":"1168e054-bb50-0000-2de1-681150bbdb01"},"Execution":{"@ProcessID":"688","@ThreadID":"5964"},"Channel":"Security","Computer":"Server002","Security":null},"EventData":{"Data":[{"@Name":"SubjectUserSid","#text":"S-1-5-21-3962163828-2803415714-1403596700-1001"},{"@Name":"SubjectUserName","#text":"lplui"},{"@Name":"SubjectDomainName","#text":"SERVER002"},{"@Name":"SubjectLogonId","#text":"0x39737"},{"@Name":"TargetName","#text":"MicrosoftAccount:user=lpluigi44@gmail.com"},{"@Name":"Type","#text":"0"},{"@Name":"CountOfCredentialsReturned","#text":"1"},{"@Name":"ReadOperation","#text":"%%8100"},{"@Name":"ReturnCode","#text":"0"},{"@Name":"ProcessCreationTime","#text":"2025-05-02 14:41:30.3975537"},{"@Name":"ClientProcessId","#text":"7256"}]}}}
{"Event":{"System":{"Provider":{"@Name":"Microsoft-Windows-Security-Auditing","@Guid":"54849625-5478-4994-a5ba-3e3b0328c30d"},"EventID":"5379","Version":"0","Level":"0","Task":"13824","Opcode":"0","Keywords":"0x8020000000000000","TimeCreated":{"@SystemTime":"2025-05-02 14:43:34.7747841"},"EventRecordID":"92033","Correlation":{"@ActivityID":"1168e054-bb50-0000-2de1-681150bbdb01"},"Execution":{"@ProcessID":"688","@ThreadID":"6580"},"Channel":"Security","Computer":"Server002","Security":null},"EventData":{"Data":[{"@Name":"SubjectUserSid","#text":"S-1-5-21-3962163828-2803415714-1403596700-1001"},{"@Name":"SubjectUserName","#text":"lplui"},{"@Name":"SubjectDomainName","#text":"SERVER002"},{"@Name":"SubjectLogonId","#text":"0x39737"},{"@Name":"TargetName","#text":"MicrosoftAccount:user=lpluigi44@gmail.com"},{"@Name":"Type","#text":"0"},{"@Name":"CountOfCredentialsReturned","#text":"1"},{"@Name":"ReadOperation","#text":"%%8100"},{"@Name":"ReturnCode","#text":"0"},{"@Name":"ProcessCreationTime","#text":"2025-05-02 14:41:30.3975537"},{"@Name":"ClientProcessId","#text":"7256"}]}}}
{"Event":{"System":{"Provider":{"@Name":"Microsoft-Windows-Security-Auditing","@Guid":"54849625-5478-4994-a5ba-3e3b0328c30d"},"EventID":"5379","Version":"0","Level":"0","Task":"13824","Opcode":"0","Keywords":"0x8020000000000000","TimeCreated":{"@SystemTime":"2025-05-02 14:43:34.7835417"},"EventRecordID":"92034","Correlation":{"@ActivityID":"1168e054-bb50-0000-2de1-681150bbdb01"},"Execution":{"@ProcessID":"688","@ThreadID":"6580"},"Channel":"Security","Computer":"Server002","Security":null},"EventData":{"Data":[{"@Name":"SubjectUserSid","#text":"S-1-5-21-3962163828-2803415714-1403596700-1001"},{"@Name":"SubjectUserName","#text":"lplui"},{"@Name":"SubjectDomainName","#text":"SERVER002"},{"@Name":"SubjectLogonId","#text":"0x39737"},{"@Name":"TargetName","#text":"MicrosoftAccount:user=lpluigi44@gmail.com"},{"@Name":"Type","#text":"0"},{"@Name":"CountOfCredentialsReturned","#text":"1"},{"@Name":"ReadOperation","#text":"%%8100"},{"@Name":"ReturnCode","#text":"0"},{"@Name":"ProcessCreationTime","#text":"2025-05-02 14:41:30.3975537"},{"@Name":"ClientProcessId","#text":"7256"}]}}}
{"Event":{"System":{"Provider":{"@Name":"Microsoft-Windows-Security-Auditing","@Guid":"54849625-5478-4994-a5ba-3e3b0328c30d"},"EventID":"5379","Version":"0","Level":"0","Task":"13824","Opcode":"0","Keywords":"0x8020000000000000","TimeCreated":{"@SystemTime":"2025-05-02 14:43:34.7854521"},"EventRecordID":"92035","Correlation":{"@ActivityID":"1168e054-bb50-0000-2de1-681150bbdb01"},"Execution":{"@ProcessID":"688","@ThreadID":"6580"},"Channel":"Security","Computer":"Server002","Security":null},"EventData":{"Data":[{"@Name":"SubjectUserSid","#text":"S-1-5-21-3962163828-2803415714-1403596700-1001"},{"@Name":"SubjectUserName","#text":"lplui"},{"@Name":"SubjectDomainName","#text":"SERVER002"},{"@Name":"SubjectLogonId","#text":"0x39737"},{"@Name":"TargetName","#text":"MicrosoftAccount:user=lpluigi44@gmail.com"},{"@Name":"Type","#text":"0"},{"@Name":"CountOfCredentialsReturned","#text":"1"},{"@Name":"ReadOperation","#text":"%%8100"},{"@Name":"ReturnCode","#text":"0"},{"@Name":"ProcessCreationTime","#text":"2025-05-02 14:41:30.3975537"},{"@Name":"ClientProcessId","#text":"7256"}]}}}
{"Event":{"System":{"Provider":{"@Name":"Microsoft-Windows-Security-Auditing","@Guid":"54849625-5478-4994-a5ba-3e3b0328c30d"},"EventID":"5379","Version":"0","Level":"0","Task":"13824","Opcode":"0","Keywords":"0x8020000000000000","TimeCreated":{"@SystemTime":"2025-05-02 14:43:34.7902163"},"EventRecordID":"92036","Correlation":{"@ActivityID":"1168e054-bb50-0000-2de1-681150bbdb01"},"Execution":{"@ProcessID":"688","@ThreadID":"6580"},"Channel":"Security","Computer":"Server002","Security":null},"EventData":{"Data":[{"@Name":"SubjectUserSid","#text":"S-1-5-21-3962163828-2803415714-1403596700-1001"},{"@Name":"SubjectUserName","#text":"lplui"},{"@Name":"SubjectDomainName","#text":"SERVER002"},{"@Name":"SubjectLogonId","#text":"0x39737"},{"@Name":"TargetName","#text":"MicrosoftAccount:user=lpluigi44@gmail.com"},{"@Name":"Type","#text":"0"},{"@Name":"CountOfCredentialsReturned","#text":"1"},{"@Name":"ReadOperation","#text":"%%8100"},{"@Name":"ReturnCode","#text":"0"},{"@Name":"ProcessCreationTime","#text":"2025-05-02 14:41:30.3975537"},{"@Name":"ClientProcessId","#text":"7256"}]}}}
{"Event":{"System":{"Provider":{"@Name":"Microsoft-Windows-Security-Auditing","@Guid":"54849625-5478-4994-a5ba-3e3b0328c30d"},"EventID":"5379","Version":"0","Level":"0","Task":"13824","Opcode":"0","Keywords":"0x8020000000000000","TimeCreated":{"@SystemTime":"2025-05-02 14:43:34.7936357"},"EventRecordID":"92037","Correlation":{"@ActivityID":"1168e054-bb50-0000-2de1-681150bbdb01"},"Execution":{"@ProcessID":"688","@ThreadID":"6580"},"Channel":"Security","Computer":"Server002","Security":null},"EventData":{"Data":[{"@Name":"SubjectUserSid","#text":"S-1-5-21-3962163828-2803415714-1403596700-1001"},{"@Name":"SubjectUserName","#text":"lplui"},{"@Name":"SubjectDomainName","#text":"SERVER002"},{"@Name":"SubjectLogonId","#text":"0x39737"},{"@Name":"TargetName","#text":"MicrosoftAccount:user=lpluigi44@gmail.com"},{"@Name":"Type","#text":"0"},{"@Name":"CountOfCredentialsReturned","#text":"1"},{"@Name":"ReadOperation","#text":"%%8100"},{"@Name":"ReturnCode","#text":"0"},{"@Name":"ProcessCreationTime","#text":"2025-05-02 14:41:30.3975537"},{"@Name":"ClientProcessId","#text":"7256"}]}}}
{"Event":{"System":{"Provider":{"@Name":"Microsoft-Windows-Security-Auditing","@Guid":"54849625-5478-4994-a5ba-3e3b0328c30d"},"EventID":"5379","Version":"0","Level":"0","Task":"13824","Opcode":"0","Keywords":"0x8020000000000000","TimeCreated":{"@SystemTime":"2025-05-02 14:43:34.7946769"},"EventRecordID":"92038","Correlation":{"@ActivityID":"1168e054-bb50-0000-2de1-681150bbdb01"},"Execution":{"@ProcessID":"688","@ThreadID":"6580"},"Channel":"Security","Computer":"Server002","Security":null},"EventData":{"Data":[{"@Name":"SubjectUserSid","#text":"S-1-5-21-3962163828-2803415714-1403596700-1001"},{"@Name":"SubjectUserName","#text":"lplui"},{"@Name":"SubjectDomainName","#text":"SERVER002"},{"@Name":"SubjectLogonId","#text":"0x39737"},{"@Name":"TargetName","#text":"MicrosoftAccount:user=lpluigi44@gmail.com"},{"@Name":"Type","#text":"0"},{"@Name":"CountOfCredentialsReturned","#text":"1"},{"@Name":"ReadOperation","#text":"%%8100"},{"@Name":"ReturnCode","#text":"0"},{"@Name":"ProcessCreationTime","#text":"2025-05-02 14:41:30.3975537"},{"@Name":"ClientProcessId","#text":"7256"}]}}}
{"Event":{"System":{"Provider":{"@Name":"Microsoft-Windows-Security-Auditing","@Guid":"54849625-5478-4994-a5ba-3e3b0328c30d"},"EventID":"5379","Version":"0","Level":"0","Task":"13824","Opcode":"0","Keywords":"0x8020000000000000","TimeCreated":{"@SystemTime":"2025-05-02 14:43:34.7951737"},"EventRecordID":"92039","Correlation":{"@ActivityID":"1168e054-bb50-0000-2de1-681150bbdb01"},"Execution":{"@ProcessID":"688","@ThreadID":"6580"},"Channel":"Security","Computer":"Server002","Security":null},"EventData":{"Data":[{"@Name":"SubjectUserSid","#text":"S-1-5-21-3962163828-2803415714-1403596700-1001"},{"@Name":"SubjectUserName","#text":"lplui"},{"@Name":"SubjectDomainName","#text":"SERVER002"},{"@Name":"SubjectLogonId","#text":"0x39737"},{"@Name":"TargetName","#text":"MicrosoftAccount:user=lpluigi44@gmail.com"},{"@Name":"Type","#text":"0"},{"@Name":"CountOfCredentialsReturned","#text":"1"},{"@Name":"ReadOperation","#text":"%%8100"},{"@Name":"ReturnCode","#text":"0"},{"@Name":"ProcessCreationTime","#text":"2025-05-02 14:41:30.3975537"},{"@Name":"ClientProcessId","#text":"7256"}]}}}
{"Event":{"System":{"Provider":{"@Name":"Microsoft-Windows-Security-Auditing","@Guid":"54849625-5478-4994-a5ba-3e3b0328c30d"},"EventID":"5379","Version":"0","Level":"0","Task":"13824","Opcode":"0","Keywords":"0x8020000000000000","TimeCreated":{"@SystemTime":"2025-05-02 14:43:34.7954400"},"EventRecordID":"92040","Correlation":{"@ActivityID":"1168e054-bb50-0000-2de1-681150bbdb01"},"Execution":{"@ProcessID":"688","@ThreadID":"6580"},"Channel":"Security","Computer":"Server002","Security":null},"EventData":{"Data":[{"@Name":"SubjectUserSid","#text":"S-1-5-21-3962163828-2803415714-1403596700-1001"},{"@Name":"SubjectUserName","#text":"lplui"},{"@Name":"SubjectDomainName","#text":"SERVER002"},{"@Name":"SubjectLogonId","#text":"0x39737"},{"@Name":"TargetName","#text":"MicrosoftAccount:user=lpluigi44@gmail.com"},{"@Name":"Type","#text":"0"},{"@Name":"CountOfCredentialsReturned","#text":"1"},{"@Name":"ReadOperation","#text":"%%8100"},{"@Name":"ReturnCode","#text":"0"},{"@Name":"ProcessCreationTime","#text":"2025-05-02 14:41:30.3975537"},{"@Name":"ClientProcessId","#text":"7256"}]}}}
{"Event":{"System":{"Provider":{"@Name":"Microsoft-Windows-Security-Auditing","@Guid":"54849625-5478-4994-a5ba-3e3b0328c30d"},"EventID":"5379","Version":"0","Level":"0","Task":"13824","Opcode":"0","Keywords":"0x8020000000000000","TimeCreated":{"@SystemTime":"2025-05-02 14:43:34.7980914"},"EventRecordID":"92041","Correlation":{"@ActivityID":"1168e054-bb50-0000-2de1-681150bbdb01"},"Execution":{"@ProcessID":"688","@ThreadID":"6580"},"Channel":"Security","Computer":"Server002","Security":null},"EventData":{"Data":[{"@Name":"SubjectUserSid","#text":"S-1-5-21-3962163828-2803415714-1403596700-1001"},{"@Name":"SubjectUserName","#text":"lplui"},{"@Name":"SubjectDomainName","#text":"SERVER002"},{"@Name":"SubjectLogonId","#text":"0x39737"},{"@Name":"TargetName","#text":"MicrosoftAccount:user=lpluigi44@gmail.com"},{"@Name":"Type","#text":"0"},{"@Name":"CountOfCredentialsReturned","#text":"1"},{"@Name":"ReadOperation","#text":"%%8100"},{"@Name":"ReturnCode","#text":"0"},{"@Name":"ProcessCreationTime","#text":"2025-05-02 14:41:30.3975537"},{"@Name":"ClientProcessId","#text":"7256"}]}}}
{"Event":{"System":{"Provider":{"@Name":"Microsoft-Windows-Security-Auditing","@Guid":"54849625-5478-4994-a5ba-3e3b0328c30d"},"EventID":"5379","Version":"0","Level":"0","Task":"13824","Opcode":"0","Keywords":"0x8020000000000000","TimeCreated":{"@SystemTime":"2025-05-02 14:43:34.7983953"},"EventRecordID":"92042","Correlation":{"@ActivityID":"1168e054-bb50-0000-2de1-681150bbdb01"},"Execution":{"@ProcessID":"688","@ThreadID":"6580"},"Channel":"Security","Computer":"Server002","Security":null},"EventData":{"Data":[{"@Name":"SubjectUserSid","#text":"S-1-5-21-3962163828-2803415714-1403596700-1001"},{"@Name":"SubjectUserName","#text":"lplui"},{"@Name":"SubjectDomainName","#text":"SERVER002"},{"@Name":"SubjectLogonId","#text":"0x39737"},{"@Name":"TargetName","#text":"MicrosoftAccount:user=lpluigi44@gmail.com"},{"@Name":"Type","#text":"0"},{"@Name":"CountOfCredentialsReturned","#text":"1"},{"@Name":"ReadOperation","#text":"%%8100"},{"@Name":"ReturnCode","#text":"0"},{"@Name":"ProcessCreationTime","#text":"2025-05-02 14:41:30.3975537"},{"@Name":"ClientProcessId","#text":"7256"}]}}}
{"Event":{"System":{"Provider":{"@Name":"Microsoft-Windows-Security-Auditing","@Guid":"54849625-5478-4994-a5ba-3e3b0328c30d"},"EventID":"5379","Version":"0","Level":"0","Task":"13824","Opcode":"0","Keywords":"0x8020000000000000","TimeCreated":{"@SystemTime":"2025-05-02 14:43:34.7986989"},"EventRecordID":"92043","Correlation":{"@ActivityID":"1168e054-bb50-0000-2de1-681150bbdb01"},"Execution":{"@ProcessID":"688","@ThreadID":"6580"},"Channel":"Security","Computer":"Server002","Security":null},"EventData":{"Data":[{"@Name":"SubjectUserSid","#text":"S-1-5-21-3962163828-2803415714-1403596700-1001"},{"@Name":"SubjectUserName","#text":"lplui"},{"@Name":"SubjectDomainName","#text":"SERVER002"},{"@Name":"SubjectLogonId","#text":"0x39737"},{"@Name":"TargetName","#text":"MicrosoftAccount:user=lpluigi44@gmail.com"},{"@Name":"Type","#text":"0"},{"@Name":"CountOfCredentialsReturned","#text":"1"},{"@Name":"ReadOperation","#text":"%%8100"},{"@Name":"ReturnCode","#text":"0"},{"@Name":"ProcessCreationTime","#text":"2025-05-02 14:41:30.3975537"},{"@Name":"ClientProcessId","#text":"7256"}]}}}
{"Event":{"System":{"Provider":{"@Name":"Microsoft-Windows-Security-Auditing","@Guid":"54849625-5478-4994-a5ba-3e3b0328c30d"},"EventID":"5379","Version":"0","Level":"0","Task":"13824","Opcode":"0","Keywords":"0x8020000000000000","TimeCreated":{"@SystemTime":"2025-05-02 14:43:34.8171111"},"EventRecordID":"92044","Correlation":{"@ActivityID":"1168e054-bb50-0000-2de1-681150bbdb01"},"Execution":{"@ProcessID":"688","@ThreadID":"6580"},"Channel":"Security","Computer":"Server002","Security":null},"EventData":{"Data":[{"@Name":"SubjectUserSid","#text":"S-1-5-21-3962163828-2803415714-1403596700-1001"},{"@Name":"SubjectUserName","#text":"lplui"},{"@Name":"SubjectDomainName","#text":"SERVER002"},{"@Name":"SubjectLogonId","#text":"0x39737"},{"@Name":"TargetName","#text":"MicrosoftAccount:user=lpluigi44@gmail.com"},{"@Name":"Type","#text":"0"},{"@Name":"CountOfCredentialsReturned","#text":"1"},{"@Name":"ReadOperation","#text":"%%8100"},{"@Name":"ReturnCode","#text":"0"},{"@Name":"ProcessCreationTime","#text":"2025-05-02 14:41:30.3975537"},{"@Name":"ClientProcessId","#text":"7256"}]}}}
{"Event":{"System":{"Provider":{"@Name":"Microsoft-Windows-Security-Auditing","@Guid":"54849625-5478-4994-a5ba-3e3b0328c30d"},"EventID":"5379","Version":"0","Level":"0","Task":"13824","Opcode":"0","Keywords":"0x8020000000000000","TimeCreated":{"@SystemTime":"2025-05-02 14:43:35.2458485"},"EventRecordID":"92045","Correlation":{"@ActivityID":"1168e054-bb50-0000-2de1-681150bbdb01"},"Execution":{"@ProcessID":"688","@ThreadID":"6580"},"Channel":"Security","Computer":"Server002","Security":null},"EventData":{"Data":[{"@Name":"SubjectUserSid","#text":"S-1-5-21-3962163828-2803415714-1403596700-1001"},{"@Name":"SubjectUserName","#text":"lplui"},{"@Name":"SubjectDomainName","#text":"SERVER002"},{"@Name":"SubjectLogonId","#text":"0x39737"},{"@Name":"TargetName","#text":"MicrosoftAccount:user=lpluigi44@gmail.com"},{"@Name":"Type","#text":"0"},{"@Name":"CountOfCredentialsReturned","#text":"1"},{"@Name":"ReadOperation","#text":"%%8100"},{"@Name":"ReturnCode","#text":"0"},{"@Name":"ProcessCreationTime","#text":"2025-05-02 14:41:30.3975537"},{"@Name":"ClientProcessId","#text":"7256"}]}}}
{"Event":{"System":{"Provider":{"@Name":"Microsoft-Windows-Security-Auditing","@Guid":"54849625-5478-4994-a5ba-3e3b0328c30d"},"EventID":"5379","Version":"0","Level":"0","Task":"13824","Opcode":"0","Keywords":"0x8020000000000000","TimeCreated":{"@SystemTime":"2025-05-02 14:43:35.2463026"},"EventRecordID":"92046","Correlation":{"@ActivityID":"1168e054-bb50-0000-2de1-681150bbdb01"},"Execution":{"@ProcessID":"688","@ThreadID":"6580"},"Channel":"Security","Computer":"Server002","Security":null},"EventData":{"Data":[{"@Name":"SubjectUserSid","#text":"S-1-5-21-3962163828-2803415714-1403596700-1001"},{"@Name":"SubjectUserName","#text":"lplui"},{"@Name":"SubjectDomainName","#text":"SERVER002"},{"@Name":"SubjectLogonId","#text":"0x39737"},{"@Name":"TargetName","#text":"MicrosoftAccount:user=lpluigi44@gmail.com"},{"@Name":"Type","#text":"0"},{"@Name":"CountOfCredentialsReturned","#text":"1"},{"@Name":"ReadOperation","#text":"%%8100"},{"@Name":"ReturnCode","#text":"0"},{"@Name":"ProcessCreationTime","#text":"2025-05-02 14:41:30.3975537"},{"@Name":"ClientProcessId","#text":"7256"}]}}}
{"Event":{"System":{"Provider":{"@Name":"Microsoft-Windows-Security-Auditing","@Guid":"54849625-5478-4994-a5ba-3e3b0328c30d"},"EventID":"5379","Version":"0","Level":"0","Task":"13824","Opcode":"0","Keywords":"0x8020000000000000","TimeCreated":{"@SystemTime":"2025-05-02 14:43:35.2467860"},"EventRecordID":"92047","Correlation":{"@ActivityID":"1168e054-bb50-0000-2de1-681150bbdb01"},"Execution":{"@ProcessID":"688","@ThreadID":"6580"},"Channel":"Security","Computer":"Server002","Security":null},"EventData":{"Data":[{"@Name":"SubjectUserSid","#text":"S-1-5-21-3962163828-2803415714-1403596700-1001"},{"@Name":"SubjectUserName","#text":"lplui"},{"@Name":"SubjectDomainName","#text":"SERVER002"},{"@Name":"SubjectLogonId","#text":"0x39737"},{"@Name":"TargetName","#text":"MicrosoftAccount:user=lpluigi44@gmail.com"},{"@Name":"Type","#text":"0"},{"@Name":"CountOfCredentialsReturned","#text":"1"},{"@Name":"ReadOperation","#text":"%%8100"},{"@Name":"ReturnCode","#text":"0"},{"@Name":"ProcessCreationTime","#text":"2025-05-02 14:41:30.3975537"},{"@Name":"ClientProcessId","#text":"7256"}]}}}
{"Event":{"System":{"Provider":{"@Name":"Microsoft-Windows-Security-Auditing","@Guid":"54849625-5478-4994-a5ba-3e3b0328c30d"},"EventID":"5379","Version":"0","Level":"0","Task":"13824","Opcode":"0","Keywords":"0x8020000000000000","TimeCreated":{"@SystemTime":"2025-05-02 14:43:35.2470974"},"EventRecordID":"92048","Correlation":{"@ActivityID":"1168e054-bb50-0000-2de1-681150bbdb01"},"Execution":{"@ProcessID":"688","@ThreadID":"6580"},"Channel":"Security","Computer":"Server002","Security":null},"EventData":{"Data":[{"@Name":"SubjectUserSid","#text":"S-1-5-21-3962163828-2803415714-1403596700-1001"},{"@Name":"SubjectUserName","#text":"lplui"},{"@Name":"SubjectDomainName","#text":"SERVER002"},{"@Name":"SubjectLogonId","#text":"0x39737"},{"@Name":"TargetName","#text":"MicrosoftAccount:user=lpluigi44@gmail.com"},{"@Name":"Type","#text":"0"},{"@Name":"CountOfCredentialsReturned","#text":"1"},{"@Name":"ReadOperation","#text":"%%8100"},{"@Name":"ReturnCode","#text":"0"},{"@Name":"ProcessCreationTime","#text":"2025-05-02 14:41:30.3975537"},{"@Name":"ClientProcessId","#text":"7256"}]}}}
{"Event":{"System":{"Provider":{"@Name":"Microsoft-Windows-Security-Auditing","@Guid":"54849625-5478-4994-a5ba-3e3b0328c30d"},"EventID":"5379","Version":"0","Level":"0","Task":"13824","Opcode":"0","Keywords":"0x8020000000000000","TimeCreated":{"@SystemTime":"2025-05-02 14:43:35.2474504"},"EventRecordID":"92049","Correlation":{"@ActivityID":"1168e054-bb50-0000-2de1-681150bbdb01"},"Execution":{"@ProcessID":"688","@ThreadID":"6580"},"Channel":"Security","Computer":"Server002","Security":null},"EventData":{"Data":[{"@Name":"SubjectUserSid","#text":"S-1-5-21-3962163828-2803415714-1403596700-1001"},{"@Name":"SubjectUserName","#text":"lplui"},{"@Name":"SubjectDomainName","#text":"SERVER002"},{"@Name":"SubjectLogonId","#text":"0x39737"},{"@Name":"TargetName","#text":"MicrosoftAccount:user=lpluigi44@gmail.com"},{"@Name":"Type","#text":"0"},{"@Name":"CountOfCredentialsReturned","#text":"1"},{"@Name":"ReadOperation","#text":"%%8100"},{"@Name":"ReturnCode","#text":"0"},{"@Name":"ProcessCreationTime","#text":"2025-05-02 14:41:30.3975537"},{"@Name":"ClientProcessId","#text":"7256"}]}}}
{"Event":{"System":{"Provider":{"@Name":"Microsoft-Windows-Security-Auditing","@Guid":"54849625-5478-4994-a5ba-3e3b0328c30d"},"EventID":"5379","Version":"0","Level":"0","Task":"13824","Opcode":"0","Keywords":"0x8020000000000000","TimeCreated":{"@SystemTime":"2025-05-02 14:43:35.2477468"},"EventRecordID":"92050","Correlation":{"@ActivityID":"1168e054-bb50-0000-2de1-681150bbdb01"},"Execution":{"@ProcessID":"688","@ThreadID":"6580"},"Channel":"Security","Computer":"Server002","Security":null},"EventData":{"Data":[{"@Name":"SubjectUserSid","#text":"S-1-5-21-3962163828-2803415714-1403596700-1001"},{"@Name":"SubjectUserName","#text":"lplui"},{"@Name":"SubjectDomainName","#text":"SERVER002"},{"@Name":"SubjectLogonId","#text":"0x39737"},{"@Name":"TargetName","#text":"MicrosoftAccount:user=lpluigi44@gmail.com"},{"@Name":"Type","#text":"0"},{"@Name":"CountOfCredentialsReturned","#text":"1"},{"@Name":"ReadOperation","#text":"%%8100"},{"@Name":"ReturnCode","#text":"0"},{"@Name":"ProcessCreationTime","#text":"2025-05-02 14:41:30.3975537"},{"@Name":"ClientProcessId","#text":"7256"}]}}}
{"Event":{"System":{"Provider":{"@Name":"Microsoft-Windows-Security-Auditing","@Guid":"54849625-5478-4994-a5ba-3e3b0328c30d"},"EventID":"5379","Version":"0","Level":"0","Task":"13824","Opcode":"0","Keywords":"0x8020000000000000","TimeCreated":{"@SystemTime":"2025-05-02 14:43:35.2481662"},"EventRecordID":"92051","Correlation":{"@ActivityID":"1168e054-bb50-0000-2de1-681150bbdb01"},"Execution":{"@ProcessID":"688","@ThreadID":"6580"},"Channel":"Security","Computer":"Server002","Security":null},"EventData":{"Data":[{"@Name":"SubjectUserSid","#text":"S-1-5-21-3962163828-2803415714-1403596700-1001"},{"@Name":"SubjectUserName","#text":"lplui"},{"@Name":"SubjectDomainName","#text":"SERVER002"},{"@Name":"SubjectLogonId","#text":"0x39737"},{"@Name":"TargetName","#text":"MicrosoftAccount:user=lpluigi44@gmail.com"},{"@Name":"Type","#text":"0"},{"@Name":"CountOfCredentialsReturned","#text":"1"},{"@Name":"ReadOperation","#text":"%%8100"},{"@Name":"ReturnCode","#text":"0"},{"@Name":"ProcessCreationTime","#text":"2025-05-02 14:41:30.3975537"},{"@Name":"ClientProcessId","#text":"7256"}]}}}
{"Event":{"System":{"Provider":{"@Name":"Microsoft-Windows-Security-Auditing","@Guid":"54849625-5478-4994-a5ba-3e3b0328c30d"},"EventID":"5379","Version":"0","Level":"0","Task":"13824","Opcode":"0","Keywords":"0x8020000000000000","TimeCreated":{"@SystemTime":"2025-05-02 14:43:35.2484752"},"EventRecordID":"92052","Correlation":{"@ActivityID":"1168e054-bb50-0000-2de1-681150bbdb01"},"Execution":{"@ProcessID":"688","@ThreadID":"6580"},"Channel":"Security","Computer":"Server002","Security":null},"EventData":{"Data":[{"@Name":"SubjectUserSid","#text":"S-1-5-21-3962163828-2803415714-1403596700-1001"},{"@Name":"SubjectUserName","#text":"lplui"},{"@Name":"SubjectDomainName","#text":"SERVER002"},{"@Name":"SubjectLogonId","#text":"0x39737"},{"@Name":"TargetName","#text":"MicrosoftAccount:user=lpluigi44@gmail.com"},{"@Name":"Type","#text":"0"},{"@Name":"CountOfCredentialsReturned","#text":"1"},{"@Name":"ReadOperation","#text":"%%8100"},{"@Name":"ReturnCode","#text":"0"},{"@Name":"ProcessCreationTime","#text":"2025-05-02 14:41:30.3975537"},{"@Name":"ClientProcessId","#text":"7256"}]}}}
{"Event":{"System":{"Provider":{"@Name":"Microsoft-Windows-Security-Auditing","@Guid":"54849625-5478-4994-a5ba-3e3b0328c30d"},"EventID":"5379","Version":"0","Level":"0","Task":"13824","Opcode":"0","Keywords":"0x8020000000000000","TimeCreated":{"@SystemTime":"2025-05-02 14:43:35.2488356"},"EventRecordID":"92053","Correlation":{"@ActivityID":"1168e054-bb50-0000-2de1-681150bbdb01"},"Execution":{"@ProcessID":"688","@ThreadID":"6580"},"Channel":"Security","Computer":"Server002","Security":null},"EventData":{"Data":[{"@Name":"SubjectUserSid","#text":"S-1-5-21-3962163828-2803415714-1403596700-1001"},{"@Name":"SubjectUserName","#text":"lplui"},{"@Name":"SubjectDomainName","#text":"SERVER002"},{"@Name":"SubjectLogonId","#text":"0x39737"},{"@Name":"TargetName","#text":"MicrosoftAccount:user=lpluigi44@gmail.com"},{"@Name":"Type","#text":"0"},{"@Name":"CountOfCredentialsReturned","#text":"1"},{"@Name":"ReadOperation","#text":"%%8100"},{"@Name":"ReturnCode","#text":"0"},{"@Name":"ProcessCreationTime","#text":"2025-05-02 14:41:30.3975537"},{"@Name":"ClientProcessId","#text":"7256"}]}}}
{"Event":{"System":{"Provider":{"@Name":"Microsoft-Windows-Security-Auditing","@Guid":"54849625-5478-4994-a5ba-3e3b0328c30d"},"EventID":"5379","Version":"0","Level":"0","Task":"13824","Opcode":"0","Keywords":"0x8020000000000000","TimeCreated":{"@SystemTime":"2025-05-02 14:43:35.2491334"},"EventRecordID":"92054","Correlation":{"@ActivityID":"1168e054-bb50-0000-2de1-681150bbdb01"},"Execution":{"@ProcessID":"688","@ThreadID":"6580"},"Channel":"Security","Computer":"Server002","Security":null},"EventData":{"Data":[{"@Name":"SubjectUserSid","#text":"S-1-5-21-3962163828-2803415714-1403596700-1001"},{"@Name":"SubjectUserName","#text":"lplui"},{"@Name":"SubjectDomainName","#text":"SERVER002"},{"@Name":"SubjectLogonId","#text":"0x39737"},{"@Name":"TargetName","#text":"MicrosoftAccount:user=lpluigi44@gmail.com"},{"@Name":"Type","#text":"0"},{"@Name":"CountOfCredentialsReturned","#text":"1"},{"@Name":"ReadOperation","#text":"%%8100"},{"@Name":"ReturnCode","#text":"0"},{"@Name":"ProcessCreationTime","#text":"2025-05-02 14:41:30.3975537"},{"@Name":"ClientProcessId","#text":"7256"}]}}}
{"Event":{"System":{"Provider":{"@Name":"Microsoft-Windows-Security-Auditing","@Guid":"54849625-5478-4994-a5ba-3e3b0328c30d"},"EventID":"5379","Version":"0","Level":"0","Task":"13824","Opcode":"0","Keywords":"0x8020000000000000","TimeCreated":{"@SystemTime":"2025-05-02 14:43:35.2511972"},"EventRecordID":"92055","Correlation":{"@ActivityID":"1168e054-bb50-0000-2de1-681150bbdb01"},"Execution":{"@ProcessID":"688","@ThreadID":"5964"},"Channel":"Security","Computer":"Server002","Security":null},"EventData":{"Data":[{"@Name":"SubjectUserSid","#text":"S-1-5-21-3962163828-2803415714-1403596700-1001"},{"@Name":"SubjectUserName","#text":"lplui"},{"@Name":"SubjectDomainName","#text":"SERVER002"},{"@Name":"SubjectLogonId","#text":"0x39737"},{"@Name":"TargetName","#text":"MicrosoftAccount:user=lpluigi44@gmail.com"},{"@Name":"Type","#text":"0"},{"@Name":"CountOfCredentialsReturned","#text":"1"},{"@Name":"ReadOperation","#text":"%%8100"},{"@Name":"ReturnCode","#text":"0"},{"@Name":"ProcessCreationTime","#text":"2025-05-02 14:41:30.3975537"},{"@Name":"ClientProcessId","#text":"7256"}]}}}
{"Event":{"System":{"Provider":{"@Name":"Microsoft-Windows-Security-Auditing","@Guid":"54849625-5478-4994-a5ba-3e3b0328c30d"},"EventID":"5379","Version":"0","Level":"0","Task":"13824","Opcode":"0","Keywords":"0x8020000000000000","TimeCreated":{"@SystemTime":"2025-05-02 14:43:35.2518549"},"EventRecordID":"92056","Correlation":{"@ActivityID":"1168e054-bb50-0000-2de1-681150bbdb01"},"Execution":{"@ProcessID":"688","@ThreadID":"6580"},"Channel":"Security","Computer":"Server002","Security":null},"EventData":{"Data":[{"@Name":"SubjectUserSid","#text":"S-1-5-21-3962163828-2803415714-1403596700-1001"},{"@Name":"SubjectUserName","#text":"lplui"},{"@Name":"SubjectDomainName","#text":"SERVER002"},{"@Name":"SubjectLogonId","#text":"0x39737"},{"@Name":"TargetName","#text":"MicrosoftAccount:user=lpluigi44@gmail.com"},{"@Name":"Type","#text":"0"},{"@Name":"CountOfCredentialsReturned","#text":"1"},{"@Name":"ReadOperation","#text":"%%8100"},{"@Name":"ReturnCode","#text":"0"},{"@Name":"ProcessCreationTime","#text":"2025-05-02 14:41:30.3975537"},{"@Name":"ClientProcessId","#text":"7256"}]}}}
{"Event":{"System":{"Provider":{"@Name":"Microsoft-Windows-Security-Auditing","@Guid":"54849625-5478-4994-a5ba-3e3b0328c30d"},"EventID":"5379","Version":"0","Level":"0","Task":"13824","Opcode":"0","Keywords":"0x8020000000000000","TimeCreated":{"@SystemTime":"2025-05-02 14:43:35.8497643"},"EventRecordID":"92057","Correlation":{"@ActivityID":"1168e054-bb50-0000-2de1-681150bbdb01"},"Execution":{"@ProcessID":"688","@ThreadID":"6580"},"Channel":"Security","Computer":"Server002","Security":null},"EventData":{"Data":[{"@Name":"SubjectUserSid","#text":"S-1-5-21-3962163828-2803415714-1403596700-1001"},{"@Name":"SubjectUserName","#text":"lplui"},{"@Name":"SubjectDomainName","#text":"SERVER002"},{"@Name":"SubjectLogonId","#text":"0x39737"},{"@Name":"TargetName","#text":"MicrosoftAccount:user=lpluigi44@gmail.com"},{"@Name":"Type","#text":"0"},{"@Name":"CountOfCredentialsReturned","#text":"1"},{"@Name":"ReadOperation","#text":"%%8100"},{"@Name":"ReturnCode","#text":"0"},{"@Name":"ProcessCreationTime","#text":"2025-05-02 14:41:30.3975537"},{"@Name":"ClientProcessId","#text":"7256"}]}}}
{"Event":{"System":{"Provider":{"@Name":"Microsoft-Windows-Security-Auditing","@Guid":"54849625-5478-4994-a5ba-3e3b0328c30d"},"EventID":"5379","Version":"0","Level":"0","Task":"13824","Opcode":"0","Keywords":"0x8020000000000000","TimeCreated":{"@SystemTime":"2025-05-02 14:43:35.8526994"},"EventRecordID":"92058","Correlation":{"@ActivityID":"1168e054-bb50-0000-2de1-681150bbdb01"},"Execution":{"@ProcessID":"688","@ThreadID":"6580"},"Channel":"Security","Computer":"Server002","Security":null},"EventData":{"Data":[{"@Name":"SubjectUserSid","#text":"S-1-5-21-3962163828-2803415714-1403596700-1001"},{"@Name":"SubjectUserName","#text":"lplui"},{"@Name":"SubjectDomainName","#text":"SERVER002"},{"@Name":"SubjectLogonId","#text":"0x39737"},{"@Name":"TargetName","#text":"WindowsLive:(token):name=lpluigi44@gmail.com;serviceuri=*"},{"@Name":"Type","#text":"0"},{"@Name":"CountOfCredentialsReturned","#text":"0"},{"@Name":"ReadOperation","#text":"%%8100"},{"@Name":"ReturnCode","#text":"3221226021"},{"@Name":"ProcessCreationTime","#text":"2025-05-02 14:41:30.3975537"},{"@Name":"ClientProcessId","#text":"7256"}]}}}
{"Event":{"System":{"Provider":{"@Name":"Microsoft-Windows-Security-Auditing","@Guid":"54849625-5478-4994-a5ba-3e3b0328c30d"},"EventID":"5379","Version":"0","Level":"0","Task":"13824","Opcode":"0","Keywords":"0x8020000000000000","TimeCreated":{"@SystemTime":"2025-05-02 14:43:35.8528528"},"EventRecordID":"92059","Correlation":{"@ActivityID":"1168e054-bb50-0000-2de1-681150bbdb01"},"Execution":{"@ProcessID":"688","@ThreadID":"6580"},"Channel":"Security","Computer":"Server002","Security":null},"EventData":{"Data":[{"@Name":"SubjectUserSid","#text":"S-1-5-21-3962163828-2803415714-1403596700-1001"},{"@Name":"SubjectUserName","#text":"lplui"},{"@Name":"SubjectDomainName","#text":"SERVER002"},{"@Name":"SubjectLogonId","#text":"0x39737"},{"@Name":"TargetName","#text":"WindowsLive:(cert):name=lpluigi44@gmail.com;serviceuri=*"},{"@Name":"Type","#text":"0"},{"@Name":"CountOfCredentialsReturned","#text":"0"},{"@Name":"ReadOperation","#text":"%%8100"},{"@Name":"ReturnCode","#text":"3221226021"},{"@Name":"ProcessCreationTime","#text":"2025-05-02 14:41:30.3975537"},{"@Name":"ClientProcessId","#text":"7256"}]}}}
{"Event":{"System":{"Provider":{"@Name":"Microsoft-Windows-Security-Auditing","@Guid":"54849625-5478-4994-a5ba-3e3b0328c30d"},"EventID":"5379","Version":"0","Level":"0","Task":"13824","Opcode":"0","Keywords":"0x8020000000000000","TimeCreated":{"@SystemTime":"2025-05-02 14:43:35.8808946"},"EventRecordID":"92060","Correlation":{"@ActivityID":"1168e054-bb50-0000-2de1-681150bbdb01"},"Execution":{"@ProcessID":"688","@ThreadID":"6580"},"Channel":"Security","Computer":"Server002","Security":null},"EventData":{"Data":[{"@Name":"SubjectUserSid","#text":"S-1-5-21-3962163828-2803415714-1403596700-1001"},{"@Name":"SubjectUserName","#text":"lplui"},{"@Name":"SubjectDomainName","#text":"SERVER002"},{"@Name":"SubjectLogonId","#text":"0x39737"},{"@Name":"TargetName","#text":"MicrosoftAccount:user=lpluigi44@gmail.com"},{"@Name":"Type","#text":"0"},{"@Name":"CountOfCredentialsReturned","#text":"1"},{"@Name":"ReadOperation","#text":"%%8100"},{"@Name":"ReturnCode","#text":"0"},{"@Name":"ProcessCreationTime","#text":"2025-05-02 14:41:30.3975537"},{"@Name":"ClientProcessId","#text":"7256"}]}}}
{"Event":{"System":{"Provider":{"@Name":"Microsoft-Windows-Security-Auditing","@Guid":"54849625-5478-4994-a5ba-3e3b0328c30d"},"EventID":"5379","Version":"0","Level":"0","Task":"13824","Opcode":"0","Keywords":"0x8020000000000000","TimeCreated":{"@SystemTime":"2025-05-02 14:43:35.8942789"},"EventRecordID":"92061","Correlation":{"@ActivityID":"1168e054-bb50-0000-2de1-681150bbdb01"},"Execution":{"@ProcessID":"688","@ThreadID":"6580"},"Channel":"Security","Computer":"Server002","Security":null},"EventData":{"Data":[{"@Name":"SubjectUserSid","#text":"S-1-5-21-3962163828-2803415714-1403596700-1001"},{"@Name":"SubjectUserName","#text":"lplui"},{"@Name":"SubjectDomainName","#text":"SERVER002"},{"@Name":"SubjectLogonId","#text":"0x39737"},{"@Name":"TargetName","#text":"MicrosoftAccount:user=lpluigi44@gmail.com"},{"@Name":"Type","#text":"0"},{"@Name":"CountOfCredentialsReturned","#text":"1"},{"@Name":"ReadOperation","#text":"%%8100"},{"@Name":"ReturnCode","#text":"0"},{"@Name":"ProcessCreationTime","#text":"2025-05-02 14:41:30.3975537"},{"@Name":"ClientProcessId","#text":"7256"}]}}}
{"Event":{"System":{"Provider":{"@Name":"Microsoft-Windows-Security-Auditing","@Guid":"54849625-5478-4994-a5ba-3e3b0328c30d"},"EventID":"5379","Version":"0","Level":"0","Task":"13824","Opcode":"0","Keywords":"0x8020000000000000","TimeCreated":{"@SystemTime":"2025-05-02 14:43:36.1953966"},"EventRecordID":"92062","Correlation":{"@ActivityID":"1168e054-bb50-0000-2de1-681150bbdb01"},"Execution":{"@ProcessID":"688","@ThreadID":"6580"},"Channel":"Security","Computer":"Server002","Security":null},"EventData":{"Data":[{"@Name":"SubjectUserSid","#text":"S-1-5-21-3962163828-2803415714-1403596700-1001"},{"@Name":"SubjectUserName","#text":"lplui"},{"@Name":"SubjectDomainName","#text":"SERVER002"},{"@Name":"SubjectLogonId","#text":"0x39737"},{"@Name":"TargetName","#text":"MicrosoftAccount:user=lpluigi44@gmail.com"},{"@Name":"Type","#text":"0"},{"@Name":"CountOfCredentialsReturned","#text":"1"},{"@Name":"ReadOperation","#text":"%%8100"},{"@Name":"ReturnCode","#text":"0"},{"@Name":"ProcessCreationTime","#text":"2025-05-02 14:41:30.3975537"},{"@Name":"ClientProcessId","#text":"7256"}]}}}
{"Event":{"System":{"Provider":{"@Name":"Microsoft-Windows-Security-Auditing","@Guid":"54849625-5478-4994-a5ba-3e3b0328c30d"},"EventID":"5379","Version":"0","Level":"0","Task":"13824","Opcode":"0","Keywords":"0x8020000000000000","TimeCreated":{"@SystemTime":"2025-05-02 14:43:36.2022594"},"EventRecordID":"92063","Correlation":{"@ActivityID":"1168e054-bb50-0000-2de1-681150bbdb01"},"Execution":{"@ProcessID":"688","@ThreadID":"6580"},"Channel":"Security","Computer":"Server002","Security":null},"EventData":{"Data":[{"@Name":"SubjectUserSid","#text":"S-1-5-21-3962163828-2803415714-1403596700-1001"},{"@Name":"SubjectUserName","#text":"lplui"},{"@Name":"SubjectDomainName","#text":"SERVER002"},{"@Name":"SubjectLogonId","#text":"0x39737"},{"@Name":"TargetName","#text":"MicrosoftAccount:user=lpluigi44@gmail.com"},{"@Name":"Type","#text":"0"},{"@Name":"CountOfCredentialsReturned","#text":"1"},{"@Name":"ReadOperation","#text":"%%8100"},{"@Name":"ReturnCode","#text":"0"},{"@Name":"ProcessCreationTime","#text":"2025-05-02 14:41:30.3975537"},{"@Name":"ClientProcessId","#text":"7256"}]}}}
{"Event":{"System":{"Provider":{"@Name":"Microsoft-Windows-Security-Auditing","@Guid":"54849625-5478-4994-a5ba-3e3b0328c30d"},"EventID":"5379","Version":"0","Level":"0","Task":"13824","Opcode":"0","Keywords":"0x8020000000000000","TimeCreated":{"@SystemTime":"2025-05-02 14:43:36.2063051"},"EventRecordID":"92064","Correlation":{"@ActivityID":"1168e054-bb50-0000-2de1-681150bbdb01"},"Execution":{"@ProcessID":"688","@ThreadID":"6580"},"Channel":"Security","Computer":"Server002","Security":null},"EventData":{"Data":[{"@Name":"SubjectUserSid","#text":"S-1-5-21-3962163828-2803415714-1403596700-1001"},{"@Name":"SubjectUserName","#text":"lplui"},{"@Name":"SubjectDomainName","#text":"SERVER002"},{"@Name":"SubjectLogonId","#text":"0x39737"},{"@Name":"TargetName","#text":"MicrosoftAccount:user=lpluigi44@gmail.com"},{"@Name":"Type","#text":"0"},{"@Name":"CountOfCredentialsReturned","#text":"1"},{"@Name":"ReadOperation","#text":"%%8100"},{"@Name":"ReturnCode","#text":"0"},{"@Name":"ProcessCreationTime","#text":"2025-05-02 14:41:30.3975537"},{"@Name":"ClientProcessId","#text":"7256"}]}}}
{"Event":{"System":{"Provider":{"@Name":"Microsoft-Windows-Security-Auditing","@Guid":"54849625-5478-4994-a5ba-3e3b0328c30d"},"EventID":"5379","Version":"0","Level":"0","Task":"13824","Opcode":"0","Keywords":"0x8020000000000000","TimeCreated":{"@SystemTime":"2025-05-02 14:43:36.2065362"},"EventRecordID":"92065","Correlation":{"@ActivityID":"1168e054-bb50-0000-2de1-681150bbdb01"},"Execution":{"@ProcessID":"688","@ThreadID":"6580"},"Channel":"Security","Computer":"Server002","Security":null},"EventData":{"Data":[{"@Name":"SubjectUserSid","#text":"S-1-5-21-3962163828-2803415714-1403596700-1001"},{"@Name":"SubjectUserName","#text":"lplui"},{"@Name":"SubjectDomainName","#text":"SERVER002"},{"@Name":"SubjectLogonId","#text":"0x39737"},{"@Name":"TargetName","#text":"MicrosoftAccount:user=lpluigi44@gmail.com"},{"@Name":"Type","#text":"0"},{"@Name":"CountOfCredentialsReturned","#text":"1"},{"@Name":"ReadOperation","#text":"%%8100"},{"@Name":"ReturnCode","#text":"0"},{"@Name":"ProcessCreationTime","#text":"2025-05-02 14:41:30.3975537"},{"@Name":"ClientProcessId","#text":"7256"}]}}}
{"Event":{"System":{"Provider":{"@Name":"Microsoft-Windows-Security-Auditing","@Guid":"54849625-5478-4994-a5ba-3e3b0328c30d"},"EventID":"5379","Version":"0","Level":"0","Task":"13824","Opcode":"0","Keywords":"0x8020000000000000","TimeCreated":{"@SystemTime":"2025-05-02 14:43:36.2068194"},"EventRecordID":"92066","Correlation":{"@ActivityID":"1168e054-bb50-0000-2de1-681150bbdb01"},"Execution":{"@ProcessID":"688","@ThreadID":"6580"},"Channel":"Security","Computer":"Server002","Security":null},"EventData":{"Data":[{"@Name":"SubjectUserSid","#text":"S-1-5-21-3962163828-2803415714-1403596700-1001"},{"@Name":"SubjectUserName","#text":"lplui"},{"@Name":"SubjectDomainName","#text":"SERVER002"},{"@Name":"SubjectLogonId","#text":"0x39737"},{"@Name":"TargetName","#text":"MicrosoftAccount:user=lpluigi44@gmail.com"},{"@Name":"Type","#text":"0"},{"@Name":"CountOfCredentialsReturned","#text":"1"},{"@Name":"ReadOperation","#text":"%%8100"},{"@Name":"ReturnCode","#text":"0"},{"@Name":"ProcessCreationTime","#text":"2025-05-02 14:41:30.3975537"},{"@Name":"ClientProcessId","#text":"7256"}]}}}
{"Event":{"System":{"Provider":{"@Name":"Microsoft-Windows-Security-Auditing","@Guid":"54849625-5478-4994-a5ba-3e3b0328c30d"},"EventID":"5379","Version":"0","Level":"0","Task":"13824","Opcode":"0","Keywords":"0x8020000000000000","TimeCreated":{"@SystemTime":"2025-05-02 14:43:36.2069877"},"EventRecordID":"92067","Correlation":{"@ActivityID":"1168e054-bb50-0000-2de1-681150bbdb01"},"Execution":{"@ProcessID":"688","@ThreadID":"6580"},"Channel":"Security","Computer":"Server002","Security":null},"EventData":{"Data":[{"@Name":"SubjectUserSid","#text":"S-1-5-21-3962163828-2803415714-1403596700-1001"},{"@Name":"SubjectUserName","#text":"lplui"},{"@Name":"SubjectDomainName","#text":"SERVER002"},{"@Name":"SubjectLogonId","#text":"0x39737"},{"@Name":"TargetName","#text":"MicrosoftAccount:user=lpluigi44@gmail.com"},{"@Name":"Type","#text":"0"},{"@Name":"CountOfCredentialsReturned","#text":"1"},{"@Name":"ReadOperation","#text":"%%8100"},{"@Name":"ReturnCode","#text":"0"},{"@Name":"ProcessCreationTime","#text":"2025-05-02 14:41:30.3975537"},{"@Name":"ClientProcessId","#text":"7256"}]}}}
{"Event":{"System":{"Provider":{"@Name":"Microsoft-Windows-Security-Auditing","@Guid":"54849625-5478-4994-a5ba-3e3b0328c30d"},"EventID":"5379","Version":"0","Level":"0","Task":"13824","Opcode":"0","Keywords":"0x8020000000000000","TimeCreated":{"@SystemTime":"2025-05-02 14:43:36.2072433"},"EventRecordID":"92068","Correlation":{"@ActivityID":"1168e054-bb50-0000-2de1-681150bbdb01"},"Execution":{"@ProcessID":"688","@ThreadID":"6580"},"Channel":"Security","Computer":"Server002","Security":null},"EventData":{"Data":[{"@Name":"SubjectUserSid","#text":"S-1-5-21-3962163828-2803415714-1403596700-1001"},{"@Name":"SubjectUserName","#text":"lplui"},{"@Name":"SubjectDomainName","#text":"SERVER002"},{"@Name":"SubjectLogonId","#text":"0x39737"},{"@Name":"TargetName","#text":"MicrosoftAccount:user=lpluigi44@gmail.com"},{"@Name":"Type","#text":"0"},{"@Name":"CountOfCredentialsReturned","#text":"1"},{"@Name":"ReadOperation","#text":"%%8100"},{"@Name":"ReturnCode","#text":"0"},{"@Name":"ProcessCreationTime","#text":"2025-05-02 14:41:30.3975537"},{"@Name":"ClientProcessId","#text":"7256"}]}}}
{"Event":{"System":{"Provider":{"@Name":"Microsoft-Windows-Security-Auditing","@Guid":"54849625-5478-4994-a5ba-3e3b0328c30d"},"EventID":"5379","Version":"0","Level":"0","Task":"13824","Opcode":"0","Keywords":"0x8020000000000000","TimeCreated":{"@SystemTime":"2025-05-02 14:43:36.2074182"},"EventRecordID":"92069","Correlation":{"@ActivityID":"1168e054-bb50-0000-2de1-681150bbdb01"},"Execution":{"@ProcessID":"688","@ThreadID":"6580"},"Channel":"Security","Computer":"Server002","Security":null},"EventData":{"Data":[{"@Name":"SubjectUserSid","#text":"S-1-5-21-3962163828-2803415714-1403596700-1001"},{"@Name":"SubjectUserName","#text":"lplui"},{"@Name":"SubjectDomainName","#text":"SERVER002"},{"@Name":"SubjectLogonId","#text":"0x39737"},{"@Name":"TargetName","#text":"MicrosoftAccount:user=lpluigi44@gmail.com"},{"@Name":"Type","#text":"0"},{"@Name":"CountOfCredentialsReturned","#text":"1"},{"@Name":"ReadOperation","#text":"%%8100"},{"@Name":"ReturnCode","#text":"0"},{"@Name":"ProcessCreationTime","#text":"2025-05-02 14:41:30.3975537"},{"@Name":"ClientProcessId","#text":"7256"}]}}}
{"Event":{"System":{"Provider":{"@Name":"Microsoft-Windows-Security-Auditing","@Guid":"54849625-5478-4994-a5ba-3e3b0328c30d"},"EventID":"5379","Version":"0","Level":"0","Task":"13824","Opcode":"0","Keywords":"0x8020000000000000","TimeCreated":{"@SystemTime":"2025-05-02 14:43:36.2077004"},"EventRecordID":"92070","Correlation":{"@ActivityID":"1168e054-bb50-0000-2de1-681150bbdb01"},"Execution":{"@ProcessID":"688","@ThreadID":"6580"},"Channel":"Security","Computer":"Server002","Security":null},"EventData":{"Data":[{"@Name":"SubjectUserSid","#text":"S-1-5-21-3962163828-2803415714-1403596700-1001"},{"@Name":"SubjectUserName","#text":"lplui"},{"@Name":"SubjectDomainName","#text":"SERVER002"},{"@Name":"SubjectLogonId","#text":"0x39737"},{"@Name":"TargetName","#text":"MicrosoftAccount:user=lpluigi44@gmail.com"},{"@Name":"Type","#text":"0"},{"@Name":"CountOfCredentialsReturned","#text":"1"},{"@Name":"ReadOperation","#text":"%%8100"},{"@Name":"ReturnCode","#text":"0"},{"@Name":"ProcessCreationTime","#text":"2025-05-02 14:41:30.3975537"},{"@Name":"ClientProcessId","#text":"7256"}]}}}
{"Event":{"System":{"Provider":{"@Name":"Microsoft-Windows-Security-Auditing","@Guid":"54849625-5478-4994-a5ba-3e3b0328c30d"},"EventID":"5379","Version":"0","Level":"0","Task":"13824","Opcode":"0","Keywords":"0x8020000000000000","TimeCreated":{"@SystemTime":"2025-05-02 14:43:36.2079048"},"EventRecordID":"92071","Correlation":{"@ActivityID":"1168e054-bb50-0000-2de1-681150bbdb01"},"Execution":{"@ProcessID":"688","@ThreadID":"6580"},"Channel":"Security","Computer":"Server002","Security":null},"EventData":{"Data":[{"@Name":"SubjectUserSid","#text":"S-1-5-21-3962163828-2803415714-1403596700-1001"},{"@Name":"SubjectUserName","#text":"lplui"},{"@Name":"SubjectDomainName","#text":"SERVER002"},{"@Name":"SubjectLogonId","#text":"0x39737"},{"@Name":"TargetName","#text":"MicrosoftAccount:user=lpluigi44@gmail.com"},{"@Name":"Type","#text":"0"},{"@Name":"CountOfCredentialsReturned","#text":"1"},{"@Name":"ReadOperation","#text":"%%8100"},{"@Name":"ReturnCode","#text":"0"},{"@Name":"ProcessCreationTime","#text":"2025-05-02 14:41:30.3975537"},{"@Name":"ClientProcessId","#text":"7256"}]}}}
{"Event":{"System":{"Provider":{"@Name":"Microsoft-Windows-Security-Auditing","@Guid":"54849625-5478-4994-a5ba-3e3b0328c30d"},"EventID":"5379","Version":"0","Level":"0","Task":"13824","Opcode":"0","Keywords":"0x8020000000000000","TimeCreated":{"@SystemTime":"2025-05-02 14:43:36.2081379"},"EventRecordID":"92072","Correlation":{"@ActivityID":"1168e054-bb50-0000-2de1-681150bbdb01"},"Execution":{"@ProcessID":"688","@ThreadID":"6580"},"Channel":"Security","Computer":"Server002","Security":null},"EventData":{"Data":[{"@Name":"SubjectUserSid","#text":"S-1-5-21-3962163828-2803415714-1403596700-1001"},{"@Name":"SubjectUserName","#text":"lplui"},{"@Name":"SubjectDomainName","#text":"SERVER002"},{"@Name":"SubjectLogonId","#text":"0x39737"},{"@Name":"TargetName","#text":"MicrosoftAccount:user=lpluigi44@gmail.com"},{"@Name":"Type","#text":"0"},{"@Name":"CountOfCredentialsReturned","#text":"1"},{"@Name":"ReadOperation","#text":"%%8100"},{"@Name":"ReturnCode","#text":"0"},{"@Name":"ProcessCreationTime","#text":"2025-05-02 14:41:30.3975537"},{"@Name":"ClientProcessId","#text":"7256"}]}}}
